Workbook

Sheet Presupuesto equipo
A1: Névola · Cimentación del piloto · Presupuesto del equipo
A2: Pasado del manuscrito del 20/10/2026 (foto en ofertas-proveedores/). Importes sin IVA. Celdas amarillas: editables.
A4: Nº | B4: Partida | C4: Medición (como en el manuscrito) | D4: Ud | E4: Cantidad | F4: Precio | G4: Importe
A5: 1 | B5: Muro a dos caras: muros longitudinales | C5: 4 muros × 9,50 m × 2 caras | D5: ml | E5: =4*9.5*2 -> 76 | F5: 36 | G5: =E5*F5 -> 2736
A6: 2 | B6: Muro a dos caras: muretes transversales | C6: 2 muretes × 7,95 m × 2 caras | D6: ml | E6: =2*7.95*2 -> 31.8 | F6: 36 | G6: =E6*F6 -> 1144.8
A7: 3 | B7: Vertido de hormigón: muros | C7: Según el equipo | D7: m³ | E7: 11 | F7: 16.5 | G7: =E7*F7 -> 181.5
A8: 4 | B8: Vertido de hormigón: zapatas | C8: Según el equipo | D8: m³ | E8: 26 | F8: 16.5 | G8: =E8*F8 -> 429
A9: 5 | B9: Hierro elaborado y armado | C9: Según el equipo | D9: kg | E9: 3000 | F9: 0.67 | G9: =E9*F9 -> 2010
A10: 6 | B10: Placas de anclaje | C10: 3 por muro × 4 muros | D10: ud | E10: 12 | F10: 32 | G10: =E10*F10 -> 384
A11: 7 | B11: Solera de limpieza (mano de obra) | C11: Superficie de zapatas del croquis. Añadida por Iván (20/10/2026) | D11: m² | E11: =10*(0.75+0.9+0.9+0.75)+2*8.5*0.75 -> 45.75 | F11: 11 | G11: =E11*F11 -> 503.25
B12: Total del presupuesto del equipo | G12: =SUM(G5:G11) -> 7388.55
B13: En el manuscrito: 6.885,00 €, sin la solera de limpieza, que se añadió después. Los céntimos son redondeos del papel (1.144,80 → 1.145 y 610,50 → 610).
A15: Lo que no aparece en el manuscrito (a confirmar con el equipo)
A16: Los precios del manuscrito son de mano de obra: encofrado por metro, vertido (no suministro) a 16,50 €/m³ y armado por kg. El hormigón (95 €/m³) y el acero (0,95 €/kg) se suministran aparte. Precios en blanco: rellenar cuando estén confirmados.
B17: Partida | C17: De dónde sale la cantidad | D17: Ud | E17: Cantidad | F17: Precio | G17: Importe
B18: Suministro de hormigón HA-25 | C18: Los 37 m³ vertidos. Precio de Iván (20/10/2026) | D18: m³ | E18: =E7+E8 -> 37 | F18: 115 | G18: =IF(F18="","",E18*F18) -> 4255
B19: Suministro de acero B500S | C19: Los 3.000 kg, aparte de los 0,67 €/kg de elaboración y armado. Precio de Iván (20/10/2026) | D19: kg | E19: =E9 -> 3000 | F19: 0.95 | G19: =IF(F19="","",E19*F19) -> 2850
B20: Suministro de placas de anclaje | C20: Las 12 placas del presupuesto; la colocación va en mano de obra. Precio de Iván (20/10/2026) | D20: ud | E20: =E10 -> 12 | F20: 220 | G20: =IF(F20="","",E20*F20) -> 2640
B21: Hormigón de limpieza bajo zapatas | C21: Superficie de zapatas del croquis: 10,00 × (0,75 + 0,90 + 0,90 + 0,75) + 2 × 8,50 × 0,75. Precio: 10 cm de espesor al precio del hormigón | D21: m² | E21: =10*(0.75+0.9+0.9+0.75)+2*8.5*0.75 -> 45.75 | F21: =0.1*F18 -> 11.5 | G21: =IF(F21="","",E21*F21) -> 526.125
B22: Excavación de zanjas y retirada de tierras | C22: Superficie de zapatas (45,75 m²) × 1,30 m de fondo, como en la estimación A (coronación a −0,05, muro, zapata y limpieza). Sin descontar cruces. Precio de Iván (20/10/2026) | D22: m³ | E22: =(10*(0.75+0.9+0.9+0.75)+2*8.5*0.75)*1.3 -> 59.475 | F22: 18 | G22: =IF(F22="","",E22*F22) -> 1070.55
B23: Grava en la cámara sanitaria | C23: Huella de planta baja: 7,85 × 9,50 m, sin descontar muros, como en la estimación A. Precio de Iván (20/10/2026) | D23: m² | E23: =7.85*9.5 -> 74.575 | F23: 12 | G23: =IF(F23="","",E23*F23) -> 894.9
B24: Bombeo de hormigón | C24: Una partida por vivienda. Precio de Iván (20/10/2026) | D24: ud | E24: =1 -> 1 | F24: 250 | G24: =IF(F24="","",E24*F24) -> 250
B25: Replanteo topográfico | C25: Ejes de muros y placas, por vivienda. Precio de Iván (20/10/2026) | D25: ud | E25: =1 -> 1 | F25: 300 | G25: =IF(F25="","",E25*F25) -> 300
B26: Subtotal de lo pendiente (solo lo que tenga precio) | G26: =SUM(G18:G25) -> 12786.575
B27: Total cimentación con lo pendiente | G27: =G12+G26 -> 20175.125

Sheet Comprobaciones
A1: Comprobaciones del presupuesto del equipo
A2: Geometría leída del croquis y comparación con nuestra estimación A (web /cimentacion/).
A4: Concepto | B4: Equipo | C4: Estimación A | D4: Diferencia | E4: Comentario
A5: Hormigón en muros (m³) | B5: ='Presupuesto equipo'!E7 -> 11 | C5: 8.58 | D5: =B5-C5 -> 2.42 | E5: Equipo: muros de 0,70 m de alto; nosotros 0,65 m.
A6: Hormigón en zapatas (m³) | B6: ='Presupuesto equipo'!E8 -> 26 | C6: 20.48 | D6: =B6-C6 -> 5.52 | E6: Croquis: zapatas de 0,75 y 0,90 m de ancho. Nosotros 0,80 y 1,00 m, y zapata común de 1,20 m en la medianera.
A7: Hormigón total (m³) | B7: =B5+B6 -> 37 | C7: =C5+C6 -> 29.06 | D7: =B7-C7 -> 7.94
A8: Acero (kg) | B8: ='Presupuesto equipo'!E9 -> 3000 | C8: 1667 | D8: =B8-C8 -> 1333 | E8: Nosotros: 50 kg/m³ en zapatas y 75 kg/m³ en muros.
A9: Cuantía de acero (kg/m³) | B9: =B8/B7 -> 81.081081 | C9: =C8/C7 -> 57.364074 | D9: =B9-C9 -> 23.717007 | E9: Razonable en los dos casos para cimentación corrida.
A10: Placas de anclaje (ud) | B10: ='Presupuesto equipo'!E10 -> 12 | C10: 18 | D10: =B10-C10 -> -6 | E10: Nosotros ponemos 2 placas en cada eje de los muros interiores (una por módulo): 18. El croquis tiene 3 por muro: 12.
A11: Altura de muro (m) | B11: 0.7 | C11: 0.65 | D11: =B11-C11 -> 0.05
A12: Longitud de muretes transversales (m) | B12: 7.95 | C12: 6.9 | D12: =B12-C12 -> 1.05 | E12: En el croquis pone 7,85 y en el cálculo 7,95. Nosotros medimos el murete entre muros.
A14: Geometría leída del croquis
A15: Muros longitudinales | B15: 4 × 9,50 m × 0,70 m de alto; espesores 0,25 · 0,30 · 0,30 · 0,25 m
A16: Muretes transversales | B16: 2 × 7,85 m (7,95 en el cálculo)
A17: Zapatas longitudinales | B17: 10,00 m de largo; anchos 0,75 · 0,90 · 0,90 · 0,75 m
A18: Zapatas laterales | B18: 2 × 8,50 × 0,75 m
A19: Canto de zapata implícito | B19: =B6/(10*(0.75+0.9+0.9+0.75)+2*8.5*0.75) -> 0.56830601
A21: Contraste con Menorca Pino (banco de precios, 2024, precios de venta)
A22: Partida | B22: €/m³ 2024 | C22: €/m³ 2026 (+12 %) | D22: Volumen equipo | E22: Importe
A23: Zapatas corridas, completas | B23: 254 | C23: =B23*1.12 -> 284.48 | D23: =B6 -> 26 | E23: =C23*D23 -> 7396.48
A24: Muros de cimentación, completos | B24: 251.99 | C24: =B24*1.12 -> 282.2288 | D24: =B5 -> 11 | E24: =C24*D24 -> 3104.5168
A25: Cimentación con precios de Pino | E25: =E23+E24 -> 10500.997
A26: Presupuesto del equipo, por m³ | D26: ='Presupuesto equipo'!G12/B7 -> 199.69054 | E26: ='Presupuesto equipo'!G12 -> 7388.55
A27: Las partidas de Pino incluyen hormigón, acero, encofrado y mano de obra. La diferencia con el equipo es del orden del suministro de hormigón: por eso creemos que el manuscrito es solo mano de obra.

Sheet Preguntas al equipo
A1: Preguntas para cerrar el presupuesto
A2: Antes de darlo por bueno.
A4: 1 | B4: Hormigón (95 €/m³) y acero (0,95 €/kg) van aparte. ¿Confirmáis que vuestro precio no incluye ningún material salvo las placas?
A5: 2 | B5: ¿Quién hace y paga la excavación de zanjas, la retirada de tierras, el hormigón de limpieza y la grava de la cámara sanitaria?
A6: 3 | B6: Canto de las zapatas: con 26 m³ sale ≈ 0,57 m. ¿Qué canto han previsto?
A7: 4 | B7: Placas: el croquis tiene 12 (3 por muro). En cada muro interior apoyan dos módulos y cada uno lleva su pilar, así que salen 2 placas por eje: 18 en total. Las 32 € son la colocación; la placa se compra aparte a 220 €. ¿Incluye los pernos?
A8: 5 | B8: Muretes transversales: 7,85 m en el croquis y 7,95 m en el cálculo. ¿Cuál es la buena?
A9: 6 | B9: Medianera: ¿zapata propia de 0,75 m o común con la vivienda vecina, como la planteamos nosotros (1,20 m, mitad por vivienda)?
A10: 7 | B10: Cota de coronación: con el suelo a +0,20, el marco queda a −0,05. ¿Lo tienen en cuenta en la altura de 0,70 m?
A11: 8 | B11: ¿Incluye bombeo, desencofrado, curado y limpieza de obra? ¿Plazo de ejecución?
