Workbook

Sheet Resumen
A1: NÉVOLA: PRESUPUESTO TÉCNICO MODULAR SOBRE EL PROYECTO DE EJECUCIÓN
A2: Base: BC3 «NEVOLA EJECUCIÓN_DEF julio 2026» (PEM 2.915.671,71 €, 16 viviendas). Importes por vivienda pareada (148,30 m²) y sin IVA.
A4: Concepto | B4: Por vivienda | C4: €/m² construido | D4: Serie de 16
A5: PROYECTO TRADICIONAL (alcance vivienda: sin urbanización, cimentación, piscina ni acometidas)
A6: PEM de lo que sustituye el sistema modular (estructura, cubierta, fachada, aislamientos) | B6: =SUMIF('Proyecto por alcance'!$A$5:$A$314,"SUSTITUYE",'Proyecto por alcance'!$J$5:$J$314) | C6: =B6/Supuestos!$B$8 | D6: =B6*Supuestos!$B$34
A7: PEM de lo que se ejecuta igual (instalaciones, carpinterías, acabados) | B7: =SUMIF('Proyecto por alcance'!$A$5:$A$314,"IGUAL",'Proyecto por alcance'!$J$5:$J$314) | C7: =B7/Supuestos!$B$8 | D7: =B7*Supuestos!$B$34
A8: PEM alcance vivienda | B8: =SUM(B6:B7) | C8: =B8/Supuestos!$B$8 | D8: =B8*Supuestos!$B$34
A9: Precio de contrata tradicional (PEM + GG + BI) | B9: =B8*(1+Supuestos!$B$39) | C9: =B9/Supuestos!$B$8 | D9: =B9*Supuestos!$B$34
A11: RG21 MODULAR (coste real)
A12: Sistema modular (sustituye) | B12: ='Sistema modular'!$E$18 | C12: =B12/Supuestos!$B$8 | D12: =B12*Supuestos!$B$34
A13: Partidas iguales a precio de proyecto, con ahorro de fábrica | B13: =B7*(1-Supuestos!$B$37) | C13: =B13/Supuestos!$B$8 | D13: =B13*Supuestos!$B$34
A14: Específicos modulares: transporte, grúa, montaje, ingeniería, fábrica | B14: ='Sistema modular'!$E$27 | C14: =B14/Supuestos!$B$8 | D14: =B14*Supuestos!$B$34
A15: COSTE RG21 | B15: =SUM(B12:B14) | C15: =B15/Supuestos!$B$8 | D15: =B15*Supuestos!$B$34
A16: Margen RG21 (GG + beneficio) | B16: =B15*Supuestos!$B$38 | C16: =B16/Supuestos!$B$8 | D16: =B16*Supuestos!$B$34
A17: PRECIO RG21 | B17: =B15+B16 | C17: =B17/Supuestos!$B$8 | D17: =B17*Supuestos!$B$34
A19: Diferencia del precio RG21 con la contrata tradicional | B19: =B17-B9 | C19: =B19/Supuestos!$B$8 | D19: =B19*Supuestos!$B$34
A20: Diferencia en % | B20: =IF(B9=0,"",B19/B9)
A21: Precio de la oferta comercial de septiembre (pareada, serie) | B21: =250600 | C21: =B21/Supuestos!$B$8 | D21: =B21*Supuestos!$B$34
A22: Bajada sobre la oferta comercial | B22: =B17-B21 | C22: =B22/Supuestos!$B$8 | D22: =B22*Supuestos!$B$34
A25: ESCENARIOS: PRECIO RG21 POR VIVIENDA
A26: Cambia el acero por m² (filas) y el ahorro de fábrica en partidas iguales (columnas). Resto de supuestos como en la hoja Supuestos.
A27: Acero (kg/m²) | B27: Ahorro 0 % | C27: Ahorro 8 % | D27: Ahorro 12 %
A28: 90 kg/m² | B28: =((B15-'Sistema modular'!$E$5-B13)+90*Supuestos!$B$8*Supuestos!$B$7+$B$7*(1-0))*(1+Supuestos!$B$38) | C28: =((B15-'Sistema modular'!$E$5-B13)+90*Supuestos!$B$8*Supuestos!$B$7+$B$7*(1-0.08))*(1+Supuestos!$B$38) | D28: =((B15-'Sistema modular'!$E$5-B13)+90*Supuestos!$B$8*Supuestos!$B$7+$B$7*(1-0.12))*(1+Supuestos!$B$38)
A29: 75 kg/m² | B29: =((B15-'Sistema modular'!$E$5-B13)+75*Supuestos!$B$8*Supuestos!$B$7+$B$7*(1-0))*(1+Supuestos!$B$38) | C29: =((B15-'Sistema modular'!$E$5-B13)+75*Supuestos!$B$8*Supuestos!$B$7+$B$7*(1-0.08))*(1+Supuestos!$B$38) | D29: =((B15-'Sistema modular'!$E$5-B13)+75*Supuestos!$B$8*Supuestos!$B$7+$B$7*(1-0.12))*(1+Supuestos!$B$38)
A30: 65 kg/m² | B30: =((B15-'Sistema modular'!$E$5-B13)+65*Supuestos!$B$8*Supuestos!$B$7+$B$7*(1-0))*(1+Supuestos!$B$38) | C30: =((B15-'Sistema modular'!$E$5-B13)+65*Supuestos!$B$8*Supuestos!$B$7+$B$7*(1-0.08))*(1+Supuestos!$B$38) | D30: =((B15-'Sistema modular'!$E$5-B13)+65*Supuestos!$B$8*Supuestos!$B$7+$B$7*(1-0.12))*(1+Supuestos!$B$38)
A31: 55 kg/m² | B31: =((B15-'Sistema modular'!$E$5-B13)+55*Supuestos!$B$8*Supuestos!$B$7+$B$7*(1-0))*(1+Supuestos!$B$38) | C31: =((B15-'Sistema modular'!$E$5-B13)+55*Supuestos!$B$8*Supuestos!$B$7+$B$7*(1-0.08))*(1+Supuestos!$B$38) | D31: =((B15-'Sistema modular'!$E$5-B13)+55*Supuestos!$B$8*Supuestos!$B$7+$B$7*(1-0.12))*(1+Supuestos!$B$38)
A32: 45 kg/m² | B32: =((B15-'Sistema modular'!$E$5-B13)+45*Supuestos!$B$8*Supuestos!$B$7+$B$7*(1-0))*(1+Supuestos!$B$38) | C32: =((B15-'Sistema modular'!$E$5-B13)+45*Supuestos!$B$8*Supuestos!$B$7+$B$7*(1-0.08))*(1+Supuestos!$B$38) | D32: =((B15-'Sistema modular'!$E$5-B13)+45*Supuestos!$B$8*Supuestos!$B$7+$B$7*(1-0.12))*(1+Supuestos!$B$38)
A33: Referencia: contrata tradicional del mismo alcance | B33: =B9
A35: LECTURA
A36: 1. La oferta comercial de septiembre salía cara porque sumaba márgenes: precios de venta de DWHAI a Tini de 2024, más IPC, más un 12 %. Aquí todo va a coste real y el margen se aplica una vez.
A37: 2. Las partidas que se hacen igual (carpinterías, instalaciones, acabados, sanitarios) se valoran con las mediciones y los precios del propio proyecto. Son precios de mercado de 2026 y el promotor los reconoce.
A38: 3. El acero va a 90 kg/m², el dato real de Mahón (dos plantas, 2024). Cada 10 kg/m² que el cálculo consiga bajar son unos 3.900 € menos por vivienda.
A39: 4. Queda fuera lo que el proyecto pone en urbanización, cimentación, movimiento de tierras, saneamiento enterrado, acometidas, piscina, seguridad y salud, control de calidad y residuos: 51.368 €/vivienda de PEM que el promotor sigue teniendo.
A40: 5. El modular ahorra al promotor la solera ventilada Cáviti, las ayudas de albañilería y buena parte del plazo de obra (costes financieros, seguridad y salud, gastos de obra). No está valorado aquí.

Sheet Supuestos
A1: SUPUESTOS DEL PRESUPUESTO TÉCNICO MODULAR (vivienda pareada tipo)
A2: Amarillo = dato que se puede cambiar. Costes reales de fábrica, no precios de venta. El margen se aplica una sola vez, en el Resumen.
A4: Concepto | B4: Valor | C4: Origen
A5: Actualización de costes 2024→2026 | B5: 0.12 | C5: Costes de construcción +5,46 % en 2025 (ACR) y +3,5 % interanual en abril de 2026 (Banco de España)
A6: Acero estructural por m² construido (kg/m²) | B6: 90 | C6: Dato real: Mahón (proyecto 182, dos plantas) 13.516 kg / 151,2 m² = 89 kg/m². Bajar exige rediseñar el módulo con cálculo
A7: Coste del acero fabricado (€/kg): material, corte, soldadura, imprimación y pintura | B7: 2.6 | C7: Material 0,80 €/kg en 2024 (Mahón) + soldadura propia. En 2024 el kg soldado costó 3,0–4,9 € subcontratado
A8: Superficie construida de la vivienda pareada (m²) | B8: 148.3 | C8: Proyecto de ejecución, cuadro de superficies
A9: Envolvente vertical opaca, fachadas + medianera (m²) | B9: 166.54 | C9: Proyecto: XPS 100 mm en fachadas 2.664,64 m² / 16 viviendas
A10: Fachada con acabado exterior (m²) | B10: 140 | C10: Envolvente opaca sin medianera, con los petos
A11: Medianera de la pareada (m²) | B11: 26.94 | C11: Proyecto, justificación del DB HE1
A12: Cubierta (m²) | B12: 74.7 | C12: Proyecto: cubierta no transitable 1.195,45 m² / 16
A13: Suelo de planta baja (m²) | B13: 74.58 | C13: Superficie construida de planta baja
A14: Forjado entre plantas (m²) | B14: 73.72 | C14: Superficie construida de planta primera
A15: Mano de obra de fábrica (€/h, nómina + S.S.) | B15: 23 | C15: Nóminas DWHAI sep–nov 2024
A16: Horas de montaje de panel por m² | B16: 0.5 | C16: Estimado: cuadrilla de 2 personas a 4 m²/h
... A33: Ingeniería: cálculo modular y proyecto de fabricación (total) | B33: 25000 | C33: Estimado, una vez para toda la serie
A34: Viviendas de la serie | B34: 16
A35: Gastos fijos de fábrica sin mano de obra (€/mes) | B35: 20430 | C35: Nave 8.500 + oficina técnica 6.100 + gestión 3.830 + suministros 1.600 + seguros 400
A36: Viviendas fabricadas al mes con la cadena llena | B36: 2 | C36: Supuesto. Con 9 operarios: ≈ 520 h/vivienda de estructura y panel
A37: Ahorro en fábrica sobre los precios del proyecto (partidas que se hacen igual) | B37: 0 | C37: Prudente: 0 %. En fábrica es razonable un 8–12 %, porque no hay ayudas, andamios ni esperas
A38: Margen RG21: gastos generales + beneficio | B38: 0.1 | C38: Sobre el coste total
A39: GG + BI de una contrata tradicional sobre PEM | B39: 0.19 | C39: 13 % de gastos generales + 6 % de beneficio industrial (habitual)

Sheet Proyecto por alcance
A1: PROYECTO DE EJECUCIÓN NÉVOLA (BC3 julio 2026): 309 PARTIDAS CLASIFICADAS POR ALCANCE
A2: FUERA = lo ejecuta el promotor u otra contrata (urbanización, cimentación, piscina, acometidas). SUSTITUYE = lo cambia el sistema modular. IGUAL = se ejecuta igual en fábrica que en obra.
A4: Alcance | B4: Capítulo | C4: Código | D4: Descripción | E4: Ud | F4: Cantidad total | G4: Cant./vivienda | H4: Precio proyecto | I4: Importe total | J4: Importe/vivienda
A5: SUSTITUYE | B5: C.03 | C5: ISS010cc | D5: COLECTOR SUSPENDIDO PVC 52 mm | E5: m | F5: 27.2 | G5: =F5/Supuestos!$B$34 | H5: 17.53 | I5: =F5*H5 | J5: =I5/Supuestos!$B$34
A6: SUSTITUYE | B6: C.03 | C6: ISS010c | D6: COLECTOR SUSPENDIDO PVC 90 mm | E6: m | F6: 84.8 | G6: =F6/Supuestos!$B$34 | H6: 27.09 | I6: =F6*H6 | J6: =I6/Supuestos!$B$34
A7: SUSTITUYE | B7: C.03 | C7: ISS010cb | D7: COLECTOR SUSPENDIDO PVC 110 mm | E7: m | F7: 408 | G7: =F7/Supuestos!$B$34 | H7: 30.1 | I7: =F7*H7 | J7: =I7/Supuestos!$B$34
A8: SUSTITUYE | B8: C.04 | C8: ANS030 | D8: SOLERA VENTILADA C-50 "CÁVITI" 50+5 cm | E8: m² | F8: 1207.85 | G8: =F8/Supuestos!$B$34 | H8: 39.45 | I8: =F8*H8 | J8: =I8/Supuestos!$B$34
A9: SUSTITUYE | B9: C.04 | C9: EHU030b | D9: FORJADO UNIDIRECCIONAL 30 cm SEMIVIGUETA ARMADA/BOV HORMIGÓN/PILARES Y VIGAS 0,134 m³/m² | E9: m² | F9: 1285.15 | G9: =F9/Supuestos!$B$34 | H9: 83.78 | I9: =F9*H9 | J9: =I9/Supuestos!$B$34
A10: SUSTITUYE | B10: C.04 | C10: EHU030 | D10: FORJADO UNIDIRECCIONAL 30 cm SEMIVIGUETA ARMADA/BOV HORMIGÓN/PILARES Y VIGAS 0,147 m³/m² | E10: m² | F10: 1091.6 | G10: =F10/Supuestos!$B$34 | H10: 85.14 | I10: =F10*H10 | J10: =I10/Supuestos!$B$34
A11: SUSTITUYE | B11: C.04 | C11: EHE010 | D11: LOSA DE ESCALERA h=17 cm | E11: m² | F11: 112 | G11: =F11/Supuestos!$B$34 | H11: 69.16 | I11: =F11*H11 | J11: =I11/Supuestos!$B$34
A12: SUSTITUYE | B12: C.05 | C12: D08PD002 | D12: CUBIERTA PLANA NO TRANSITABLE/GRAVA | E12: m² | F12: 1195.45 | G12: =F12/Supuestos!$B$34 | H12: 88.8 | I12: =F12*H12 | J12: =I12/Supuestos!$B$34
A13: SUSTITUYE | B13: C.05 | C13: QAB010b | D13: CUBIERTA PLANA TRANSITABLE/SOLADO FIJO | E13: m² | F13: 143.1 | G13: =F13/Supuestos!$B$34 | H13: 97.54 | I13: =F13*H13 | J13: =I13/Supuestos!$B$34
A14: SUSTITUYE | B14: C.05 | C14: QAB010bb | D14: CUBIERTA PLANA TRANSITABLE/SOLADO FIJO | E14: m² | F14: 21 | G14: =F14/Supuestos!$B$34 | H14: 81.52 | I14: =F14*H14 | J14: =I14/Supuestos!$B$34
A15: SUSTITUYE | B15: C.06 | C15: 504 | D15: HOJA EXTERIOR DE FACHADA, 1/2 PIE, DE LADRILLO CERÁMICO PERFORADO TOSCO | E15: m² | F15: 3070.32 | G15: =F15/Supuestos!$B$34 | H15: 23.49 | I15: =F15*H15 | J15: =I15/Supuestos!$B$34
A16: SUSTITUYE | B16: C.06 | C16: 504b | D16: HOJA EXTERIOR DE FACHADA, 1 PIE, DE LADRILLO CERÁMICO PERFORADO TOSCO | E16: m² | F16: 306.38 | G16: =F16/Supuestos!$B$34 | H16: 34.06 | I16: =F16*H16 | J16: =I16/Supuestos!$B$34
... A314: FUERA | B314: C.20 | C314: GRB010 | D314: CANON VERTIDO RESIDUOS INERTES | E314: Ud | F314: 80 | G314: =F314/Supuestos!$B$34 | H314: 57.76 | I314: =F314*H314 | J314: =I314/Supuestos!$B$34
D316: TOTAL PEM DEL PROYECTO | I316: =SUM(I5:I314)
D317: Comprobación: PEM del BC3 | I317: 2915671.7

Sheet Sistema modular
A1: COSTE DEL SISTEMA MODULAR QUE SUSTITUYE ESTRUCTURA Y ENVOLVENTE (por vivienda pareada)
A2: Sustituye a forjados, solera ventilada, losa de escalera, cubiertas, fábrica de ladrillo, enfoscados, monocapa, aislamientos y trasdosado del proyecto.
A4: Partida | B4: Ud | C4: Cantidad | D4: Coste unitario | E4: Importe | F4: Cómo se calcula
A5: Estructura de acero de los 6 módulos (pilares, vigas, correas, arriostramientos) | B5: kg | C5: =Supuestos!$B$6*Supuestos!$B$8 | D5: =Supuestos!$B$7 | E5: =C5*D5 | F5: kg/m² × m² construidos × coste del kg fabricado
A6: Panel sándwich 8+50+8 en fachadas y medianera, colocado | B6: m² | C6: =Supuestos!$B$9 | D6: =(Supuestos!$B$18*(1+Supuestos!$B$5)*(1+Supuestos!$B$17)+Supuestos!$B$16*Supuestos!$B$15) | E6: =C6*D6 | F6: Panel con IPC y merma + horas de montaje
A7: Trasdosado interior con aislamiento (como el proyecto) | B7: m² | C7: =Supuestos!$B$9 | D7: =Supuestos!$B$21 | E7: =C7*D7 | F7: Precio del proyecto
A8: Suplemento de aislamiento para U = 0,20 | B8: m² | C8: =Supuestos!$B$9 | D8: =Supuestos!$B$22 | E8: =C8*D8
A9: Acabado exterior sobre panel | B9: m² | C9: =Supuestos!$B$10 | D9: =Supuestos!$B$23 | E9: =C9*D9 | F9: ESTIMADO: pedir precio
A10: Doble placa de protección contra incendios en medianera | B10: m² | C10: =Supuestos!$B$11 | D10: =13.56*(1+Supuestos!$B$5) | E10: =C10*D10 | F10: Placa 13 mm del banco de precios
A11: Panel sándwich 8+65+8 de cubierta, colocado | B11: m² | C11: =Supuestos!$B$12 | D11: =(Supuestos!$B$19*(1+Supuestos!$B$5)*(1+Supuestos!$B$17)+Supuestos!$B$16*Supuestos!$B$15) | E11: =C11*D11
A12: Sistema de cubierta sobre panel: pendientes, impermeabilización y grava | B12: m² | C12: =Supuestos!$B$12 | D12: =Supuestos!$B$24 | E12: =C12*D12 | F12: Precio del proyecto, sin su XPS
A13: Panel sándwich 8+120+8 en suelo de planta baja, colocado | B13: m² | C13: =Supuestos!$B$13 | D13: =(Supuestos!$B$20*(1+Supuestos!$B$5)*(1+Supuestos!$B$17)+Supuestos!$B$16*Supuestos!$B$15) | E13: =C13*D13 | F13: Sustituye a la solera ventilada Cáviti
A14: Panel sándwich 8+65+8 en suelo de planta primera, colocado | B14: m² | C14: =Supuestos!$B$14 | D14: =(Supuestos!$B$19*(1+Supuestos!$B$5)*(1+Supuestos!$B$17)+Supuestos!$B$16*Supuestos!$B$15) | E14: =C14*D14 | F14: Sustituye al forjado unidireccional
A15: Escalera metálica con peldaños | B15: ud | C15: =1 | D15: =Supuestos!$B$25 | E15: =C15*D15 | F15: Sustituye a losa + peldañeado
A16: Juntas, sellados y remates entre módulos | B16: ud | C16: =1 | D16: =Supuestos!$B$26 | E16: =C16*D16
A17: Colectores suspendidos bajo planta baja (como el proyecto) | B17: ud | C17: =1 | D17: =Supuestos!$B$27 | E17: =C17*D17
A18: COSTE SISTEMA MODULAR (sustituye) | E18: =SUM(E5:E17)
A20: ESPECÍFICOS DE LA CONSTRUCCIÓN MODULAR
A21: Partida | B21: Ud | C21: Cantidad | D21: Coste unitario | E21: Importe | F21: Cómo se calcula
A22: Transporte de módulos Seseña – Guadalix | B22: ud | C22: =Supuestos!$B$28 | D22: =Supuestos!$B$29*(1+Supuestos!$B$5) | E22: =C22*D22
A23: Grúa de colocación | B23: ud | C23: =1 | D23: =Supuestos!$B$30 | E23: =C23*D23 | F23: Compartida: 2 viviendas por jornada
A24: Montaje en parcela: uniones, conexión de instalaciones y remates | B24: h | C24: =Supuestos!$B$31 | D24: =Supuestos!$B$15*(1+Supuestos!$B$32) | E24: =C24*D24
A25: Ingeniería: cálculo modular y proyecto de fabricación | B25: ud | C25: =1 | D25: =Supuestos!$B$33/Supuestos!$B$34 | E25: =C25*D25 | F25: Repartida entre las 16 viviendas
A26: Gastos fijos de fábrica (nave, oficina técnica, gestión) | B26: ud | C26: =1 | D26: =Supuestos!$B$35/Supuestos!$B$36 | E26: =C26*D26 | F26: Gasto mensual / viviendas al mes
A27: COSTE ESPECÍFICOS MODULARES | E27: =SUM(E22:E26)
