Workbook

Sheet Resumen
A1: Névola · Mediciones por oficio para pedir ofertas · 16 viviendas
A2: Fuente: BC3 del proyecto de ejecución (julio de 2026), con medición, desglose y descripción completa de cada partida. Importes PEM del proyecto, sin IVA, solo como referencia.
A4: Cap. | B4: Oficio (pestaña) | C4: Partidas | D4: Se piden igual | E4: Las sustituye el módulo | F4: Fuera de la vivienda | G4: PEM del proyecto
A5: C.01 | B5: Actuaciones previas | C5: 5 | D5: 0 | E5: 0 | F5: 5 | G5: ='01 Actuaciones previas'!J10 -> 26049.747
A6: C.02 | B6: Movimiento de tierras | C6: 5 | D6: 0 | E6: 0 | F6: 5 | G6: ='02 Movimiento de tierras'!J10 -> 74690.011
A7: C.03 | B7: Saneamiento enterrado | C7: 18 | D7: 2 | E7: 3 | F7: 13 | G7: ='03 Saneamiento enterrado'!J23 -> 91944.62
A8: C.04 | B8: Cimentación y estructura | C8: 14 | D8: 0 | E8: 4 | F8: 10 | G8: ='04 Cimentación y estructura'!J19 -> 371011.56
A9: C.05 | B9: Cubiertas | C9: 3 | D9: 0 | E9: 3 | F9: 0 | G9: ='05 Cubiertas'!J8 -> 121825.85
A10: C.06 | B10: Albañilería | C10: 12 | D10: 0 | E10: 12 | F10: 0 | G10: ='06 Albañilería'!J17 -> 237331.28
A11: C.07 | B11: Impermeabilización y aislamiento | C11: 15 | D11: 2 | E11: 10 | F11: 3 | G11: ='07 Impermeabilización y aislami'!J20 -> 128361.62
A12: C.08 | B12: Pladur: trasdosados, tabiques y techos | C12: 9 | D12: 8 | E12: 1 | F12: 0 | G12: ='08 Pladur trasdosados, tabiques'!J14 -> 250503.1
A13: C.09 | B13: Alicatados y solados | C13: 12 | D13: 9 | E13: 0 | F13: 3 | G13: ='09 Alicatados y solados'!J17 -> 250268.09
A14: C.10 | B14: Carpintería interior | C14: 4 | D14: 4 | E14: 0 | F14: 0 | G14: ='10 Carpintería interior'!J9 -> 62785.372
A15: C.11 | B15: Carpintería exterior y cerrajería | C15: 20 | D15: 14 | E15: 0 | F15: 6 | G15: ='11 Carpintería exterior y cerra'!J25 -> 258815.76
A16: C.12 | B16: Pintura | C16: 2 | D16: 2 | E16: 0 | F16: 0 | G16: ='12 Pintura'!J7 -> 59969.531
A17: C.13 | B17: Electricidad y telecomunicaciones | C17: 55 | D17: 39 | E17: 0 | F17: 16 | G17: ='13 Electricidad y telecomunicac'!J60 -> 237477.9
A18: C.14 | B18: Fontanería, saneamiento y sanitarios | C18: 38 | D18: 23 | E18: 0 | F18: 15 | G18: ='14 Fontanería, saneamiento y sa'!J43 -> 123201.48
A19: C.15 | B19: Climatización, ACS y ventilación | C19: 30 | D19: 30 | E19: 0 | F19: 0 | G19: ='15 Climatización, ACS y ventila'!J35 -> 299448.12
A20: C.16 | B20: Piscina | C20: 19 | D20: 0 | E20: 0 | F20: 19 | G20: ='16 Piscina'!J24 -> 34929.443
A21: C.17 | B21: Urbanización | C21: 25 | D21: 0 | E21: 0 | F21: 25 | G21: ='17 Urbanización'!J30 -> 192743.34
A22: C.18 | B22: Seguridad y salud | C22: 1 | D22: 0 | E22: 0 | F22: 1 | G22: ='18 Seguridad y salud'!J6 -> 31714.16
A23: C.19 | B23: Control de calidad | C23: 14 | D23: 3 | E23: 0 | F23: 11 | G23: ='19 Control de calidad'!J19 -> 50487.98
A24: C.20 | B24: Gestión de residuos | C24: 8 | D24: 0 | E24: 0 | F24: 8 | G24: ='20 Gestión de residuos'!J13 -> 12112.75
B25: Total proyecto (PEM) | C25: =SUM(C5:C24) -> 309 | G25: =SUM(G5:G24) -> 2915671.7
B27: Acero de los módulos (16 viviendas)
B28: Panel y envolvente de los módulos (16 viviendas)
B30: «Se piden igual»: partidas que se ejecutan como en el proyecto, en fábrica o en obra (carpinterías, instalaciones, acabados, sanitarios…). Son las que hay que pedir a cada oficio.
B31: «Las sustituye el módulo»: estructura, forjados, fábricas, cubierta y aislamientos del proyecto convencional. No se piden: los cubren el acero y el panel de las dos últimas pestañas.
B32: «Fuera de la vivienda»: movimiento de tierras, cimentación, acometidas, piscina, urbanización y gastos de obra. Solo entran en las opciones 2, 3 y 4 de NIDO.
B33: La columna «Desglose» reproduce las líneas de medición del proyecto (tipo, unidades y medidas). La de «Datos clave» resume medidas, colores y marcas sacados del texto; la descripción completa va al lado.

Sheet 01 Actuaciones previas
A1: Névola · Actuaciones previas · 16 viviendas
A2: Capítulo C.01 del proyecto de ejecución (BC3 de julio de 2026). Medición de toda la promoción y su desglose tal como viene en el proyecto. Precios del proyecto (CYPE, PEM, sin IVA), solo como referencia.
A4: Código | B4: Partida | C4: Ud | D4: Total 16 viv. | E4: Media por vivienda | F4: Desglose de la medición (proyecto) | G4: Datos clave (medidas, color, marca) | H4: Descripción completa del proyecto | I4: Precio proyecto | J4: Importe PEM | K4: Alcance en el sistema modular
A5: D01QG110 | B5: DESMONTAJE Y RETIRADA CARTEL PUB. INC CARGA/TRANSP | C5: m² | D5: 20 | E5: =D5/16 -> 1.25 | F5: 1 × 5.00 × 4.00 | H5: DESMONTAJE Y RETIRADA CARTEL PUB. INC CARGA/TRANSPDesmontaje y retirada de cartel publicitario formados por vigas y pilares metálicos, i/anclaje previo, recuperación de material aprovechable, apilado y p.p. de costes indirectos, según NTE/ADD-15 y 16. | I5: 53.41 | J5: =D5*I5 -> 1068.2 | K5: Fuera de la vivienda (promotor o Knubo)
A6: D36BA005 | B6: RETIRADA ARBOL INC DESTOCONADO / TROCEADO / CARGA / TRANS | C6: Ud | D6: 4 | E6: =D6/16 -> 0.25 | F6: 4 | H6: RETIRADA ARBOL INC DESTOCONADO / TROCEADO / CARGA / TRANSCortado y troceado por medio de sierra mecánica y transporte fuera de la obra de tronco de árbol, hasta 30 cms de diametro, medido a un metro de altura sobre la rasante del terreno circundante. | I6: 177.3 | J6: =D6*I6 -> 709.2 | K6: Fuera de la vivienda (promotor o Knubo)
A7: DEF040 | B7: DEMOLICIÓN MOCHETAS INSTALACIONES | C7: m³ | D7: 12.43 | E7: =D7/16 -> 0.776875 | F7: Agua: 16 × 1.20 × 0.38 × 1.00 Electricidad: 9 × 1.00 × 0.38 × 1.50 | H7: DEMOLICIÓN MOCHETAS INSTALACIONESDemolición de muro de fábrica de ladrillo cerámico perforado, con martillo neumático, transporte del material a vertedero, con camión basculante cargado a máquina, canon de vertedero y p.p. de medios auxiliares, considerando tambien la carga. | I7: 40.32 | J7: =D7*I7 -> 501.1776 | K7: Fuera de la vivienda (promotor o Knubo)
A8: DMX050 | B8: DEMOLICIÓN ACERADO | C8: m² | D8: 447.95 | E8: =D8/16 -> 27.996875 | F8: Acera: 1 × 289.00 × 1.55 | H8: DEMOLICIÓN ACERADODemolición de pavimento exterior de baldosas y/o losetas de hormigón incluyendo bordillo y base soporte, con martillo neumático, transporte del material a vertedero, con camión basculante cargado a máquina, canon de vertedero y p.p. de medios auxiliares, considerando tambien la carga. | I8: 7.75 | J8: =D8*I8 -> 3471.6125 | K8: Fuera de la vivienda (promotor o Knubo)
A9: 101 | B9: DESBROCE Y LIMPIEZA DEL TERRENO | C9: m² | D9: 7328.36 | E9: =D9/16 -> 458.0225 | F9: Toda la parcela (incluye P17 y P18): 1 × 7328.36 | H9: DESBROCE Y LIMPIEZA DEL TERRENODesbroce y limpieza superficial del terreno por medios mecánicos, para un espesor medio de 20 cm., incluso carga y transporte de tierras al vertedero, a una distancia menor de 20km., considerando ida y vuelta con camión basculante cargado a máquina, canon de vertedero y p.p. de medios auxilares, considerando también la carga. | I9: 2.77 | J9: =D9*I9 -> 20299.557 | K9: Fuera de la vivienda (promotor o Knubo)
B10: Total del capítulo (PEM del proyecto) | J10: =SUM(J5:J9) -> 26049.747

Sheet 02 Movimiento de tierras
A1: Névola · Movimiento de tierras · 16 viviendas
A2: Capítulo C.02 del proyecto de ejecución (BC3 de julio de 2026). Medición de toda la promoción y su desglose tal como viene en el proyecto. Precios del proyecto (CYPE, PEM, sin IVA), solo como referencia.
A4: Código | B4: Partida | C4: Ud | D4: Total 16 viv. | E4: Media por vivienda | F4: Desglose de la medición (proyecto) | G4: Datos clave (medidas, color, marca) | H4: Descripción completa del proyecto | I4: Precio proyecto | J4: Importe PEM | K4: Alcance en el sistema modular
A5: ADE005 | B5: EXCAVACIÓN SÓTANOS | C5: m³ | D5: 140 | E5: =D5/16 -> 8.75 | F5: Cuarto técnico piscinas: 1 × 40.00 × 3.50 | H5: EXCAVACIÓN SÓTANOSExcavación de sótanos de más de 2 m de profundidad, que en todo su perímetro quedan por debajo de la rasante natural, en suelos de compacidad media, por medios mecánicos,transporte de tierras al vertedero, con camión basculante cargado a máquina, canon de vertedero y p.p. de medios auxiliares, considerando tambien la carga. | I5: 2.36 | J5: =D5*I5 -> 330.4 | K5: Fuera de la vivienda (promotor o Knubo)
A6: ADE010 | B6: EXCAVACIÓN POZOS DE CIMENTACIÓN | C6: m³ | D6: 265.92 | E6: =D6/16 -> 16.62 | F6: Zapatas aisladas (demasía incluida en cota variable) PAREADO 1-2: 1 × 24.65 × 1.15 PAREADO 3-4: 1 × 30.20 × 0.75 AISLADA 5: 1 × 12.75 × 1.55 PAREADO 6-7: 1 × 24.65 × 0.95 PAREADO 8-9: 1 × 30.20 × 1.30 AISLADA 10: 1 × 12.60 × 1.25 PAREADO 11-12: 1 × 24.65 × 1.55 PAREADO 13-14: 1 × 30.20 × 0.95 PAREADO 15-16: 1 × 30.20 × 1.65 | H6: EXCAVACIÓN POZOS DE CIMENTACIÓNExcavación de pozos para cimentaciones hasta una profundidad de 2 m, en suelos de compacidad media, por medios mecánicos,transporte de tierras al vertedero, con camión basculante cargado a máquina, canon de vertedero y p.p. de medios auxiliares, considerando tambien la carga. | I6: 11.1 | J6: =D6*I6 -> 2951.712 | K6: Fuera de la vivienda (promotor o Knubo)
A7: ADE010b | B7: EXCAVACIÓN ZANJAS CIMENTACIÓN | C7: m³ | D7: 194.3 | E7: =D7/16 -> 12.14375 | F7: Vigas de atado PAREADO 1-2: 1 × 17.20 × 0.40 PAREADO 3-4: 1 × 16.30 × 0.40 AISLADA 5: 1 × 9.95 × 0.40 PAREADO 6-7: 1 × 17.20 × 0.40 PAREADO 8-9: 1 × 16.30 × 0.40 AISLADA 10: 1 × 10.15 × 0.40 PAREADO 11-12: 1 × 17.20 × 0.40 PAREADO 13-14: 1 × 16.30 × 0.40 PAREADO 15-16: 1 × 16.30 × 0.40 MUROS BLOQUE H.A. para revestir Vallados a calle Perímetro parcela total: 1 × 289.00 × 0.40 × 0.40 Muros separación pareados VIV 1-VIV 2: 1 × 8.35 × 0.40 × 0.40 VIV 3-VIV 4: 1 × 8.80 × 0.40 × 0.40 VIV 6-VIV 7: 1 × 8.35 × 0.40 × 0.40 VIV 8-VIV 9: 1 × 8.35 × 0.40 × 0.40 VIV 11-VIV 12: 1 × 8.70 × 0.40 × 0.40 VIV 13-VIV 14: 1 × 8.35 × 0.40 × 0.40 VIV 15-VIV 16: 1 × 8.35 × 0.40 × 0.40 MUROS BLOQUE H.A. cara vista Separación entre viviendas VIV 1-VIV 2: 1 × 1.90 × 0.40 × 0.40 VIV 2-VIV 3: 1 × 19.75 × 0.40 × 0.40 VIV 3-VIV 4: 1 × 1.50 × 0.40 × 0.40 VIV 4-VIV 5: 1 × 19.75 × 0.40 × 0.40 VIV 5-VIV 6: 1 × 19.75 × 0.40 × 0.40 VIV 6-VIV 7: 1 × 1.90 × 0.40 × 0.40 VIV 8-VIV 9: 1 × 3.90 × 0.40 × 0.40 VIV 9-VIV 10: 1 × 21.75 × 0.40 × 0.40 VIV 10-VIV 11: 1 × 21.75 × 0.40 × 0.40 VIV 11-VIV 12: 1 × 3.60 × 0.40 × 0.40 VIV 13-VIV 14: 1 × 3.00 × 0.40 × 0.40 VIV 14-VIV 15: 1 × 20.85 × 0.40 × 0.40 VIV 15-VIV 16: 1 × 3.00 × 0.40 × 0.40 VIV 16-PARCELA 17: 1 × 21.10 × 0.40 × 0.40 Separación viviendas-Zona común Contención diferencia de niveles VIV 1-VIV 2: 1 × 30.90 × 0.40 × 0.40 VIV 3-VIV 4: 1 × 28.60 × 0.40 × 0.40 VIV 5: 1 × 15.75 × 0.40 × 0.40 VIV 6-VIV 7: 1 × 28.70 × 0.40 × 0.40 1 × 20.60 × 0.40 × 0.40 VIV 8-VIV 9: 1 × 25.65 × 0.40 × 0.40 VIV 10: 1 × 14.15 × 0.40 × 0.40 VIV 11-VIV 12: 1 × 28.75 × 0.40 × 0.40 VIV 13-VIV 14: 1 × 29.90 × 0.40 × 0.40 1 × 21.00 × 0.40 × 0.40 VIV 15-VIV 16: 1 × 31.50 × 0.40 × 0.40 CASETA APEROS: 1 × 13.45 × 0.40 × 0.40 PERÍMETRO PISCINA: 1 × 71.40 × 0.40 × 0.40 | H7: EXCAVACIÓN ZANJAS CIMENTACIÓNExcavación de zanjas para cimentaciones hasta una profundidad de 2 m, en suelos de compacidad media, por medios mecánicos,transporte de tierras al vertedero, con camión basculante cargado a máquina, canon de vertedero y p.p. de medios auxiliares, considerando tambien la carga. | I7: 9.56 | J7: =D7*I7 -> 1857.508 | K7: Fuera de la vivienda (promotor o Knubo)
A8: ADE010c | B8: EXCAVACIÓN ZANJAS INSTALACIONES | C8: m³ | D8: 233 | E8: =D8/16 -> 14.5625 | F8: Red saneamiento enterrada ZONA COMÚN: 1 × 81.00 × 0.40 × 0.40 VIV 1: 1 × 27.60 × 0.40 × 0.40 VIV 2: 1 × 27.60 × 0.40 × 0.40 VIV 3: 1 × 27.60 × 0.40 × 0.40 VIV 4: 1 × 27.60 × 0.40 × 0.40 VIV 5: 1 × 39.40 × 0.40 × 0.40 VIV 6: 1 × 36.60 × 0.40 × 0.40 VIV 7: 1 × 36.60 × 0.40 × 0.40 VIV 8: 1 × 33.10 × 0.40 × 0.40 VIV 9: 1 × 33.80 × 0.40 × 0.40 VIV 10: 1 × 31.45 × 0.40 × 0.40 VIV 11: 1 × 27.60 × 0.40 × 0.40 VIV 12: 1 × 27.60 × 0.40 × 0.40 VIV 13: 1 × 27.60 × 0.40 × 0.40 VIV 14: 1 × 27.60 × 0.40 × 0.40 VIV 15: 1 × 27.60 × 0.40 × 0.40 VIV 16: 1 × 27.60 × 0.40 × 0.40 Agua ZONA COMÚN: 1 × 110.00 × 0.40 × 0.40 VIVIENDAS: 16 × 24.00 × 0.40 × 0.40 Electricidad ZONA COMÚN: 1 × 255.00 × 0.40 × 0.40 VIVIENDAS: 12 × 6.00 × 0.40 × 0.40 2 × 14.00 × 0.40 × 0.40 2 × 19.50 × 0.40 × 0.40 | H8: EXCAVACIÓN ZANJAS INSTALACIONESExcavación de zanjas para instalaciones hasta una profundidad de 2 m, en suelos de compacidad media, por medios mecánicos,transporte de tierras al vertedero, con camión basculante cargado a máquina, canon de vertedero y p.p. de medios auxiliares, considerando tambien la carga. | I8: 12.01 | J8: =D8*I8 -> 2798.33 | K8: Fuera de la vivienda (promotor o Knubo)
A9: ADR030 | B9: RELLENO Y COMPACTACIÓN | C9: m³ | D9: 7681.48 | E9: =D9/16 -> 480.0925 | F9: Toda la parcela (hmedia=1.15 m): 1 × 6679.55 × 1.15 Incluye relleno bordes cimentación encofrada | H9: RELLENO Y COMPACTACIÓNBase de pavimento realizada mediante relleno a cielo abierto, con tierra de préstamo, y compactación en tongadas sucesivas de 30 cm de espesor máximo con rodillo vibrante de guiado manual, hasta alcanzar una densidad seca no inferior al 98% de la máxima obtenida en el ensayo Proctor Modificado, realizado según UNE 103501. El precio incluye el ensayo de Proctor Modificado. | I9: 8.69 | J9: =D9*I9 -> 66752.061 | K9: Fuera de la vivienda (promotor o Knubo)
B10: Total del capítulo (PEM del proyecto) | J10: =SUM(J5:J9) -> 74690.011

Sheet 03 Saneamiento enterrado
A1: Névola · Saneamiento enterrado · 16 viviendas
A2: Capítulo C.03 del proyecto de ejecución (BC3 de julio de 2026). Medición de toda la promoción y su desglose tal como viene en el proyecto. Precios del proyecto (CYPE, PEM, sin IVA), solo como referencia.
A4: Código | B4: Partida | C4: Ud | D4: Total 16 viv. | E4: Media por vivienda | F4: Desglose de la medición (proyecto) | G4: Datos clave (medidas, color, marca) | H4: Descripción completa del proyecto | I4: Precio proyecto | J4: Importe PEM | K4: Alcance en el sistema modular
A5: UAP011 | B5: ARQUETA DE ARRANQUE | C5: Ud | D5: 33 | E5: =D5/16 -> 2.0625 | F5: AA Pluviales: 16 × 1.00 Fecales: 16 × 1.00 Zona común: 1 × 1.00 | G5: Medidas: 125x125x100cm, 150x150cm | H5: ARQUETA DE ARRANQUEFormación de pozo de registro de elementos prefabricados de hormigón en masa, de 0,90 m de diámetro interior y de 2,1 m de altura útil interior máxima, formado por: solera de 25 cm de espesor de hormigón armado HA-30/B/20/IIb+Qb ligeramente armada con malla electrosoldada ME 20x20 Ø 8-8 B 500 T 6x2,20 UNE-EN 10080; base prefabricada de hormigón en masa, de 125x125x100 cm, con dos orificios de 30 cm de diámetro para conexión de colectores, de 90 cm de diámetro interior, con unión rígida machihembrada con junta de goma, según UNE-EN 1917, resistencia a compresión mayor de 250 kg/cm²; anillo prefabricado de hormigón en masa, con unión rígida machihembrada con junta de goma, según UNE-EN 1917, de 100 cm de diámetro interior y 50 cm de altura, resistencia a compresión mayor de 250 kg/cm²; cono asimétrico prefabricado de hormigón en masa, con unión rígida machihembrada con junta de goma, según UNE-EN 1917, de 100 a 60 cm de diámetro interior y 60 cm de altura, resistencia a compresión mayor de 250 kg/cm² y losa alrededor de la boca del cono de 150x150 cm y 20 cm de espesor de hormigón en masa HM-30/B/20/I+Qb; con cierre de tapa circular con bloqueo y marco de fundición clase D-400 según UNE-EN 124, instalado en calzadas de calles, incluyendo las peatonales, o zonas de aparcamiento para todo tipo de vehículos. Incluso hormigón en masa HM-30/B/20/I+Qb para formación de canal en el fondo del pozo y lubricante para montaje.El precio incluye los equipos y la maquinaria necesarios para el desplazamiento y la disposición en obra de los elementos, así como la excavación y el relleno del trasdós. | I5: 699.92 | J5: =D5*I5 -> 23097.36 | K5: Fuera de la vivienda (promotor o Knubo)
A6: ASB020 | B6: CONEXIÓN ACOMETIDA | C6: Ud | D6: 33 | E6: =D6/16 -> 2.0625 | F6: Pozos Pluviales: 16 × 1.00 Fecales: 16 × 1.00 Zona común: 1 × 1.00 | H6: CONEXIÓN ACOMETIDASuministro y montaje de la conexión de la acometida del edificio a la red general de saneamiento del municipio a través de pozo de registro. Incluso junta flexible para el empalme de la acometida y mortero de cemento, industrial, M-5 para repaso y bruñido en el interior del pozo. | I6: 148.82 | J6: =D6*I6 -> 4911.06 | K6: Fuera de la vivienda (promotor o Knubo)
A7: ASB010b | B7: ACOMETIDA DE SANEAMIENTO (ALBAÑAL) | C7: m | D7: 181.15 | E7: =D7/16 -> 11.321875 | F7: Pluviales VIV 1: 1 × 5.10 VIV 2: 1 × 5.75 VIV 3: 1 × 5.00 VIV 4: 1 × 6.20 VIV 5: 1 × 4.90 VIV 6: 1 × 4.90 VIV 7: 1 × 5.00 VIV 8: 1 × 7.60 VIV 9: 1 × 6.20 VIV 10: 1 × 6.70 VIV 11: 1 × 5.75 VIV 12: 1 × 5.45 VIV 13: 1 × 6.75 VIV 14: 1 × 6.25 VIV 15: 1 × 7.10 VIV 16: 1 × 6.70 Fecales VIV 1: 1 × 3.90 VIV 2: 1 × 5.10 VIV 3: 1 × 3.80 VIV 4: 1 × 5.20 VIV 5: 1 × 3.85 VIV 6: 1 × 4.10 VIV 7: 1 × 3.80 VIV 8: 1 × 6.70 VIV 9: 1 × 6.15 VIV 10: 1 × 5.90 VIV 11: 1 × 4.90 VIV 12: 1 × 4.90 VIV 13: 1 × 5.40 VIV 14: 1 × 5.20 VIV 15: 1 × 5.60 VIV 16: 1 × 5.60 ZONA COMÚN: 1 × 5.70 | H7: ACOMETIDA DE SANEAMIENTO (ALBAÑAL)Suministro y montaje de acometida general de saneamiento, para la evacuación de aguas residuales y/o pluviales a la red general del municipio, con una pendiente mínima del 2%, para la evacuación de aguas residuales y/o pluviales, formada por tubo de PVC corrugado, rigidez anular nominal 8 kN/m², de 250 mm de diámetro exterior, con junta elástica, colocado sobre lecho de arena de 10 cm de espesor, debidamente compactada y nivelada con pisón vibrante de guiado manual, relleno lateral compactando hasta los riñones y posterior relleno con la misma arena hasta 30 cm por encima de la generatriz superior de la tubería, con sus correspondientes juntas y piezas especiales. Incluso lubricante para montaje y hormigón en masa HM-20/P/20/I para la posterior reposición del firme existente. El precio incluye la demolición y el levantado del firme existente, así como la excavación y el relleno. | I7: 82.99 | J7: =D7*I7 -> 15033.638 | K7: Fuera de la vivienda (promotor o Knubo)
A8: 0324SH0502 | B8: VÁLVULA ANTIRRETORNO ACOMETIDA | C8: Ud | D8: 33 | E8: =D8/16 -> 2.0625 | F8: Pluviales: 16 × 1.00 Fecales: 16 × 1.00 Zona común: 1 × 1.00 | H8: VÁLVULA ANTIRRETORNO ACOMETIDASuministro, instalación y montaje de válvula antirretorno de doble clapeta con cierre manual para colector de diámetro igual al de la acometida. Totalmente instalada y funcionado de acuerdo con CTE-HS-5 e instrucciones del fabricante, incluida p.p. de accesorios de conexión adecuados, incluso piezas especiales necesarias, ayudas de albañilería y medios auxiliares necesarios, totalmente terminada.Totalmente instalada, probada su estanqueidad y funcionamiento y en servicio según indicaciones de la D.F., CTE DB-HS, y especificaciones técnicas del fabricante. | I8: 122.38 | J8: =D8*I8 -> 4038.54 | K8: Fuera de la vivienda (promotor o Knubo)
A9: 203b | B9: ARQUETA DE PASO 50x50x60 | C9: Ud | D9: 68 | E9: =D9/16 -> 4.25 | F9: AF01: 16 × 2.00 AP01: 16 × 2.00 Zona común: 1 × 4.00 | G9: Medidas: 50x50x60cm | H9: ARQUETA DE PASO 50x50x60Formación de arqueta de paso, enterrada, registrable, construida con fábrica de ladrillo cerámico macizo, de 1/2 pie de espesor, recibido con mortero de cemento, industrial, M-5, de dimensiones interiores 50x50x60 cm, sobre solera de hormigón en masa HM-30/B/20/I+Qb de 15 cm de espesor, formación de pendiente mínima del 2%, con el mismo tipo de hormigón, enfoscada y bruñida interiormente con mortero de cemento, industrial, con aditivo hidrófugo, M-15 formando aristas y esquinas a media caña, cerrada superiormente con tablero cerámico hueco machihembrado y losa de hormigón HA-30/B/20/IIb+Qb, armada con malla electrosoldada y sellada herméticamente con mortero de cemento. Incluso mortero para sellado de juntas y piezas de PVC cortadas longitudinalmente para formación del canal en el fondo de la arqueta. | I9: 124.39 | J9: =D9*I9 -> 8458.52 | K9: Fuera de la vivienda (promotor o Knubo)
A10: 208 | B10: COLECTOR ENTERRADO PVC 110 mm | C10: m | D10: 124 | E10: =D10/16 -> 7.75 | F10: Fecales: 16 × 2.00 Pluviales: 16 × 2.25 Previsión piscina (fecales): 16 × 3.50 | H10: COLECTOR ENTERRADO PVC 110 mmSuministro y montaje de colector enterrado de red horizontal de saneamiento, con arquetas, con una pendiente mínima del 2%, para la evacuación de aguas residuales y/o pluviales, formado por tubo de PVC liso, serie SN-4, rigidez anular nominal 4 kN/m², de 110 mm de diámetro exterior, pegado mediante adhesivo, colocado sobre lecho de arena de 10 cm de espesor, debidamente compactada y nivelada con pisón vibrante de guiado manual, relleno lateral compactando hasta los riñones y posterior relleno con la misma arena hasta 30 cm por encima de la generatriz superior de la tubería. Incluso líquido limpiador y adhesivo para tubos y accesorios de PVC. | I10: 11.81 | J10: =D10*I10 -> 1464.44 | K10: Fuera de la vivienda (promotor o Knubo)
A11: 209 | B11: COLECTOR ENTERRADO PVC 125 mm | C11: m | D11: 221.3 | E11: =D11/16 -> 13.83125 | F11: Pluviales (general cubiertas): 16 × 8.50 Sumideros zona aparcamiento: 13 × 2.40 1 × 5.35 1 × 11.25 1 × 3.85 Zona común: 1 × 33.65 | H11: COLECTOR ENTERRADO PVC 125 mmSuministro y montaje de colector enterrado de red horizontal de saneamiento, con arquetas, con una pendiente mínima del 2%, para la evacuación de aguas residuales y/o pluviales, formado por tubo de PVC liso, serie SN-4, rigidez anular nominal 4 kN/m², de 125 mm de diámetro exterior, pegado mediante adhesivo, colocado sobre lecho de arena de 10 cm de espesor, debidamente compactada y nivelada con pisón vibrante de guiado manual, relleno lateral compactando hasta los riñones y posterior relleno con la misma arena hasta 30 cm por encima de la generatriz superior de la tubería. Incluso líquido limpiador y adhesivo para tubos y accesorios de PVC. | I11: 13.41 | J11: =D11*I11 -> 2967.633 | K11: Fuera de la vivienda (promotor o Knubo)
A12: 210 | B12: COLECTOR ENTERRADO PVC 160 mm | C12: m | D12: 255.1 | E12: =D12/16 -> 15.94375 | F12: Pluviales VIV 1: 1 × 8.50 VIV 2: 1 × 7.65 VIV 3: 1 × 8.50 VIV 4: 1 × 7.65 VIV 5: 1 × 4.55 VIV 6: 1 × 6.55 VIV 7: 1 × 7.50 VIV 8: 1 × 4.05 VIV 9: 1 × 6.40 VIV 10: 1 × 9.30 VIV 11: 1 × 8.50 VIV 12: 1 × 7.65 VIV 13: 1 × 8.50 VIV 14: 1 × 7.65 VIV 15: 1 × 8.50 VIV 16: 1 × 7.65 Fecales VIV 1: 1 × 4.55 VIV 2: 1 × 4.55 VIV 3: 1 × 4.55 VIV 4: 1 × 4.55 VIV 5: 1 × 9.55 VIV 6: 1 × 13.95 VIV 7: 1 × 12.65 VIV 8: 1 × 9.25 VIV 9: 1 × 11.40 VIV 10: 1 × 3.90 VIV 11: 1 × 4.55 VIV 12: 1 × 4.55 VIV 13: 1 × 4.55 VIV 14: 1 × 4.55 VIV 15: 1 × 4.55 VIV 16: 1 × 4.55 Zona común: 1 × 29.80 | H12: COLECTOR ENTERRADO PVC 160 mmSuministro y montaje de colector enterrado de red horizontal de saneamiento, con arquetas, con una pendiente mínima del 2%, para la evacuación de aguas residuales y/o pluviales, formado por tubo de PVC liso, serie SN-4, rigidez anular nominal 4 kN/m², de 160 mm de diámetro exterior, pegado mediante adhesivo, colocado sobre lecho de arena de 10 cm de espesor, debidamente compactada y nivelada con pisón vibrante de guiado manual, relleno lateral compactando hasta los riñones y posterior relleno con la misma arena hasta 30 cm por encima de la generatriz superior de la tubería. Incluso líquido limpiador y adhesivo para tubos y accesorios de PVC. | I12: 17.16 | J12: =D12*I12 -> 4377.516 | K12: Fuera de la vivienda (promotor o Knubo)
A13: ISS010cc | B13: COLECTOR SUSPENDIDO PVC 52 mm | C13: m | D13: 27.2 | E13: =D13/16 -> 1.7 | F13: Suelo radiante: 16 × 1.70 | H13: COLECTOR SUSPENDIDO PVC 52 mmSuministro e instalación de colector suspendido insonorizado de red horizontal, formado por tubo PVC-U, ABS, ASA y PVC-U con carga mineral de 52 mm de diámetro y 2,8 mm de espesor, unión a presión con junta elástica, con una pendiente mínima del 1,00%, para la evacuación de aguas residuales (a baja y alta temperatura) y/o pluviales en el interior de la estructura de los edificios. Incluso material auxiliar para montaje y sujeción a la obra, accesorios y piezas especiales. | I13: 17.53 | J13: =D13*I13 -> 476.816 | K13: Lo sustituye el módulo: no se pide así
A14: ISS010c | B14: COLECTOR SUSPENDIDO PVC 90 mm | C14: m | D14: 84.8 | E14: =D14/16 -> 5.3 | F14: Pluviales: 16 × 5.30 | H14: COLECTOR SUSPENDIDO PVC 90 mmSuministro e instalación de colector suspendido insonorizado de red horizontal, formado por tubo PVC-U, ABS, ASA y PVC-U con carga mineral de 90 mm de diámetro y 5,1 mm de espesor, unión a presión con junta elástica, con una pendiente mínima del 1,00%, para la evacuación de aguas residuales (a baja y alta temperatura) y/o pluviales en el interior de la estructura de los edificios. Incluso material auxiliar para montaje y sujeción a la obra, accesorios y piezas especiales. | I14: 27.09 | J14: =D14*I14 -> 2297.232 | K14: Lo sustituye el módulo: no se pide así
A15: ISS010cb | B15: COLECTOR SUSPENDIDO PVC 110 mm | C15: m | D15: 408 | E15: =D15/16 -> 25.5 | F15: Fecales Baño 2: 16 × 1.45 Baño principal: 16 × 1.15 Cámara sanitaria (cáviti): 16 × 22.90 | H15: COLECTOR SUSPENDIDO PVC 110 mmSuministro e instalación de colector suspendido insonorizado de red horizontal, formado por tubo PVC-U, ABS, ASA y PVC-U con carga mineral de 110 mm de diámetro y 5,3 mm de espesor, unión a presión con junta elástica, con una pendiente mínima del 1,00%, para la evacuación de aguas residuales (a baja y alta temperatura) y/o pluviales en el interior de la estructura de los edificios. Incluso material auxiliar para montaje y sujeción a la obra, accesorios y piezas especiales. | I15: 30.1 | J15: =D15*I15 -> 12280.8 | K15: Lo sustituye el módulo: no se pide así
A16: ISB010 | B16: BAJANTE RESIDUALES. PVC 110 mm | C16: m | D16: 172 | E16: =D16/16 -> 10.75 | F16: F1-F2: 16 × 2.00 × 3.50 Ventilación cámara sanitaria: 7 × 6.00 × 1.20 1 × 4.00 × 1.20 1 × 4.00 × 1.20 | H16: BAJANTE RESIDUALES. PVC 110 mmBajante interior insonorizada de la red de evacuación de aguas residuales, formada por tubo de PVC-U, ABS, ASA y PVC-U con carga mineral, de 110 mm de diámetro y 5,3 mm de espesor; unión a presión con junta elástica. Incluso material auxiliar para montaje y sujeción a la obra, accesorios y piezas especiales. | I16: 31.02 | J16: =D16*I16 -> 5335.44 | K16: Se pide igual (fábrica u obra)
A17: ISB010b | B17: BAJANTE PLUVIALES. PVC 90 mm | C17: m | D17: 163.2 | E17: =D17/16 -> 10.2 | F17: P1-P2: 16 × 6.50 P3: 16 × 3.50 Caseta aperos: 1 × 3.20 | H17: BAJANTE PLUVIALES. PVC 90 mmBajante interior insonorizada de la red de evacuación de aguas pluviales, formada por tubo de PVC-U, ABS, ASA y PVC-U con carga mineral, de 90 mm de diámetro y 5,1 mm de espesor; unión a presión con junta elástica. Incluso material auxiliar para montaje y sujeción a la obra, accesorios y piezas especiales. | I17: 23.47 | J17: =D17*I17 -> 3830.304 | K17: Se pide igual (fábrica u obra)
A18: 0324SH0204 | B18: CANALETA SUMIDERO PREFABRICADA 25 cm. URBANIZACIÓN | C18: m | D18: 15 | E18: =D18/16 -> 0.9375 | F18: Piscina: 1 × 15.00 | H18: CANALETA SUMIDERO PREFABRICADA 25 cm. URBANIZACIÓNSuministro y montaje de canaleta sumidero sifónica longitudinal de fundición en urbanización, en tramos de 1000 mm de largo, 150 mm de ancho y 170 mm de alto, con rejilla cuadriculada de fundición, en piezas de 1000 mm de longitud, incluso p.p. de conexión a saneamiento con tubería de PVC serie F colocado en parcela recibido con solapes de la lámina impermeabilizante, totalmente enrasado con el pavimento de terminación, instalado y conectado a la red de evacuación, todo ello según especificaciones de proyecto, NTE-ISS, DIT del fabricante, marcado CE y CÓDIGO TÉCNICO DE LA EDIFICACIÓN DB-HS. | I18: 30.24 | J18: =D18*I18 -> 453.6 | K18: Fuera de la vivienda (promotor o Knubo)
A19: 212 | B19: SUMIDERO SIFÓNICO | C19: Ud | D19: 82 | E19: =D19/16 -> 5.125 | F19: Cubierta planta no transitable: 16 × 2.00 Cubierta plana transitable (terrazas): 16 × 2.00 Caseta aperos: 1 × 1.00 Exterior viviendas: 16 × 1.00 Cuarto técnico piscinas: 1 × 1.00 | G19: Medidas: 250x250mm | H19: SUMIDERO SIFÓNICOInstalación de sumidero sifónico de PVC, de salida vertical de 90 mm de diámetro, con rejilla de PVC de 250x250 mm, para recogida de aguas pluviales o de locales húmedos. Incluso accesorios de montaje, piezas especiales y elementos de sujeción. | I19: 21.78 | J19: =D19*I19 -> 1785.96 | K19: Fuera de la vivienda (promotor o Knubo)
A20: HRP060 | B20: REBOSADEROS | C20: Ud | D20: 18 | E20: =D20/16 -> 1.125 | F20: Cubiertas planta primera PAREADO TIPO: 7 × 2.00 AISLADA TIPO 1 (VIVIENDA 5): 1 × 2.00 AISLADA TIPO 2 (VIVIENDA 10): 1 × 2.00 | G20: Medidas: 100x220x58mm · Color: blanco | H20: REBOSADEROSGárgola de hormigón polímero de superficie pulida, de color blanco, de 100x220x58 mm y base rectangular, con goterón, recibida con adhesivo cementoso flexible y sellado de la junta perimetral con masilla de poliuretano, previa aplicación de la imprimación. Incluso nivelación y remate de la impermeabilización en caso necesario. | I20: 10.02 | J20: =D20*I20 -> 180.36 | K20: Fuera de la vivienda (promotor o Knubo)
A21: ISD009 | B21: SUMIDERO SIFÓNICO DUCHA | C21: Ud | D21: 1 | E21: =D21/16 -> 0.0625 | F21: Ducha piscina chapoteo: 1 | G21: Medidas: 100x100mm | H21: SUMIDERO SIFÓNICO DUCHASumidero sifónico de PVC con rejilla de acero inoxidable de 100x100 mm y salidas vertical y horizontal de 50 mm de diámetro, para desagüe de ducha de obra. | I21: 10.41 | J21: =D21*I21 -> 10.41 | K21: Fuera de la vivienda (promotor o Knubo)
A22: IVN110 | B22: REJILLA VENTILACIÓN | C22: Ud | D22: 53 | E22: =D22/16 -> 3.3125 | F22: Ventilación cámara sanitaria PAREADO TIPO: 7 × 6.00 VIVIENDA AISLADA (VIVIENDA 5): 1 × 4.00 VIVIENDA AISLADA (VIVIENDA 10): 1 × 4.00 Caseta aperos: 1 × 1.00 Cuarto técnico piscinas: 1 × 2.00 | G22: Medidas: 15x15cm · Color: con | H22: REJILLA VENTILACIÓNRejilla de ventilación de lamas fijas de aluminio lacado color con 60 micras de espesor mínimo de película seca, de dimensiones 15x15 cm. Incluso tornillos.Incluye: Marcado de los puntos de fijación. Colocación y fijación.Criterio de medición de proyecto: Superficie del hueco a cerrar, medida según documentación gráfica de Proyecto.Criterio de medición de obra: Se medirá, con las dimensiones del hueco, la superficie realmente ejecutada según especificaciones de Proyecto. | I22: 17.83 | J22: =D22*I22 -> 944.99 | K22: Fuera de la vivienda (promotor o Knubo)
B23: Total del capítulo (PEM del proyecto) | J23: =SUM(J5:J22) -> 91944.62

Sheet 04 Cimentación y estructura
A1: Névola · Cimentación y estructura · 16 viviendas
A2: Capítulo C.04 del proyecto de ejecución (BC3 de julio de 2026). Medición de toda la promoción y su desglose tal como viene en el proyecto. Precios del proyecto (CYPE, PEM, sin IVA), solo como referencia.
A4: Código | B4: Partida | C4: Ud | D4: Total 16 viv. | E4: Media por vivienda | F4: Desglose de la medición (proyecto) | G4: Datos clave (medidas, color, marca) | H4: Descripción completa del proyecto | I4: Precio proyecto | J4: Importe PEM | K4: Alcance en el sistema modular
A5: CMP010 | B5: POZO DE CIMENTACIÓN (RELLENO A FIRME) | C5: m³ | D5: 194.83 | E5: =D5/16 -> 12.176875 | F5: ZAPATAS AISLADAS/CIMEN ESCALERAS (demasía 25 %) PAREADO 1-2: 1 × 24.65 × 1.25 × 0.65 PAREADO 3-4: 1 × 30.20 × 1.25 × 0.25 AISLADA 5: 1 × 12.75 × 1.25 × 1.05 PAREADO 6-7: 1 × 24.65 × 1.25 × 0.45 PAREADO 8-9: 1 × 30.20 × 1.25 × 0.80 AISLADA 10: 1 × 12.60 × 1.25 × 0.75 PAREADO 11-12: 1 × 24.65 × 1.25 × 1.05 PAREADO 13-14: 1 × 30.20 × 1.25 × 0.45 PAREADO 15-16: 1 × 30.20 × 1.25 × 1.15 | H5: POZO DE CIMENTACIÓN DE HORMIGÓN CICLÓPEOPozo de cimentación de hormigón HL-150/B/20, fabricado en central y vertido desde camión, en el fondo de la excavación previamente realizada. Incluye: Replanteo. Colocación de toques y/o formación de maestras. Vertido y compactación del hormigón. Coronación y enrase del hormigón.Incluye: Replanteo y trazado de las zapatas y de los pilares u otros elementos estructurales que apoyen en las mismas. Vertido y compactación del hormigón. Colocación de las piedras en el hormigón fresco. Coronación y enrase de cimientos. Curado del hormigón.Criterio de medición de proyecto: Volumen teórico, según documentación gráfica de Proyecto.Criterio de medición de obra: Se medirá el volumen teórico ejecutado según especificaciones de Proyecto, sin incluir los incrementos por excesos de excavación no autorizados. | I5: 70.73 | J5: =D5*I5 -> 13780.326 | K5: Fuera de la vivienda (promotor o Knubo)
A6: 301 | B6: HORMIGÓN DE LIMPIEZA h=10 cm | C6: m² | D6: 1841.22 | E6: =D6/16 -> 115.07625 | F6: VIGAS DE ATADO (demasía 25 %) PAREADO 1-2: 1 × 17.20 × 1.25 PAREADO 3-4: 1 × 16.30 × 1.25 AISLADA 5: 1 × 9.95 × 1.25 PAREADO 6-7: 1 × 17.20 × 1.25 PAREADO 8-9: 1 × 16.30 × 1.25 AISLADA 10: 1 × 10.15 × 1.25 PAREADO 11-12: 1 × 17.20 × 1.25 PAREADO 13-14: 1 × 16.30 × 1.25 × 1.25 PAREADO 15-16: 1 × 16.30 × 1.25 BASE SOLERA CÁVITI PAREADO TIPO: 7 × 150.40 AISLADA TIPO 1 (VIVIENDA 5): 1 × 77.10 AISLADA TIPO 2 (VIVIENDA 10): 1 × 77.95 MUROS BLOQUE H.A. para revestir (demasía 25 %) Vallados a calle Perímetro parcela total: 1 × 289.00 × 0.40 × 1.25 Muros separación pareados VIV 1-VIV 2: 1 × 8.35 × 0.40 × 1.25 VIV 3-VIV 4: 1 × 8.80 × 0.40 × 1.25 VIV 6-VIV 7: 1 × 8.35 × 0.40 × 1.25 VIV 8-VIV 9: 1 × 8.35 × 0.40 × 1.25 VIV 11-VIV 12: 1 × 8.70 × 0.40 × 1.25 VIV 13-VIV 14: 1 × 8.35 × 0.40 × 1.25 VIV 15-VIV 16: 1 × 8.35 × 0.40 × 1.25 MUROS BLOQUE H.A. cara vista (demasía 25 %) Separación entre viviendas VIV 1-VIV 2: 1 × 1.90 × 0.40 × 1.25 VIV 2-VIV 3: 1 × 19.75 × 0.40 × 1.25 VIV 3-VIV 4: 1 × 1.50 × 0.40 × 1.25 VIV 4-VIV 5: 1 × 19.75 × 0.40 × 1.25 VIV 5-VIV 6: 1 × 19.75 × 0.40 × 1.25 VIV 6-VIV 7: 1 × 1.90 × 0.40 × 1.25 VIV 8-VIV 9: 1 × 3.90 × 0.40 × 1.25 VIV 9-VIV 10: 1 × 21.75 × 0.40 × 1.25 VIV 10-VIV 11: 1 × 21.75 × 0.40 × 1.25 VIV 11-VIV 12: 1 × 3.60 × 0.40 × 1.25 VIV 13-VIV 14: 1 × 3.00 × 0.40 × 1.25 VIV 14-VIV 15: 1 × 20.85 × 0.40 × 1.25 VIV 15-VIV 16: 1 × 3.00 × 0.40 × 1.25 VIV 16-PARCELA 17: 1 × 21.10 × 0.40 × 1.25 Separación viviendas-Zona común (demasía 25 %) Contención diferencia de niveles VIV 1-VIV 2: 1 × 30.90 × 0.40 × 1.25 VIV 3-VIV 4: 1 × 28.60 × 0.40 × 1.25 VIV 5: 1 × 15.75 × 0.40 × 1.25 VIV 6-VIV 7: 1 × 28.70 × 0.40 × 1.25 1 × 20.60 × 0.40 × 1.25 VIV 8-VIV 9: 1 × 25.65 × 0.40 × 1.25 VIV 10: 1 × 14.15 × 0.40 × 1.25 VIV 11-VIV 12: 1 × 28.75 × 0.40 × 1.25 VIV 13-VIV 14: 1 × 29.90 × 0.40 × 1.25 1 × 21.00 × 0.40 × 1.25 VIV 15-VIV 16: 1 × 31.50 × 0.40 × 1.25 CASETA APEROS: 1 × 13.45 × 0.40 × 1.25 PERÍMETRO PISCINA: 1 × 71.40 × 0.40 × 1.25 CUARTO TÉCNICO PISCINA: 1 × 21.00 | H6: HORMIGÓN DE LIMPIEZA h=10 cmCapa de hormigón de limpieza y nivelado de fondos de cimentación, de 10 cm de espesor, de hormigón HL-150/B/20, fabricado en central y vertido desde camión, en el fondo de la excavación previamente realizada. Incluye: Replanteo. Colocación de toques y/o formación de maestras. Vertido y compactación del hormigón. Coronación y enrase del hormigón. | I6: 7.31 | J6: =D6*I6 -> 13459.318 | K6: Fuera de la vivienda (promotor o Knubo)
A7: CSZ020 | B7: ENCOFRADO CIMENTACIÓN | C7: m² | D7: 771 | E7: =D7/16 -> 48.1875 | F7: ZAPATAS AISLADAS/CIMEN ESCALERAS/VIGAS DE ATADO PAREADO 1-2: 1 × 155.70 × 0.60 PAREADO 3-4: 1 × 159.80 × 0.60 AISLADA 5: 1 × 88.80 × 0.60 PAREADO 6-7: 1 × 155.70 × 0.60 PAREADO 8-9: 1 × 159.80 × 0.60 AISLADA 10: 1 × 89.90 × 0.60 PAREADO 11-12: 1 × 155.70 × 0.60 PAREADO 13-14: 1 × 159.80 × 0.60 PAREADO 15-16: 1 × 159.80 × 0.60 | H7: ENCOFRADO CIMENTACIÓNMontaje de sistema de encofrado recuperable de madera, para zapata de cimentación, formado por tablones de madera, amortizables en 10 usos, y posterior desmontaje del sistema de encofrado. Incluso elementos de sustentación, fijación y acodalamientos necesarios para su estabilidad y líquido desencofrante para evitar la adherencia del hormigón al encofrado. | I7: 13.83 | J7: =D7*I7 -> 10662.93 | K7: Fuera de la vivienda (promotor o Knubo)
A8: CSZ030 | B8: ZAPATA HORMIGÓN ARMADO HA-25/F/20/XC2 | C8: m³ | D8: 110.07 | E8: =D8/16 -> 6.879375 | F8: ZAPATAS AISLADAS/CIMEN ESCALERAS PAREADO 1-2: 1 × 24.65 × 0.50 PAREADO 3-4: 1 × 30.20 × 0.50 AISLADA 5: 1 × 12.75 × 0.50 PAREADO 6-7: 1 × 24.65 × 0.50 PAREADO 8-9: 1 × 30.20 × 0.50 AISLADA 10: 1 × 12.60 × 0.50 PAREADO 11-12: 1 × 24.65 × 0.50 PAREADO 13-14: 1 × 30.20 × 0.50 PAREADO 15-16: 1 × 30.20 × 0.50 | H8: ZAPATA HORMIGÓN ARMADO HA-25/F/20/XC2Zapata de cimentación de hormigón armado, realizada con hormigón HA-25/F/20/XC2 fabricado en central, y vertido con cubilote, y acero, UNE-EN 10080 B 500 S, con una cuantía aproximada de 35,1 kg/m³. Incluso armaduras de espera del pilar, alambre de atar y separadores.Criterio de valoración económica: El precio incluye la elaboración de la ferralla (corte, doblado y conformado de elementos) en taller industrial y el montaje en el lugar definitivo de su colocación en obra, pero no incluye el encofrado.Incluye: Replanteo y trazado de las zapatas y de los pilares u otros elementos estructurales que apoyen en las mismas. Colocación de separadores y fijación de las armaduras. Vertido y compactación del hormigón. Coronación y enrase de cimientos. Curado del hormigón.Criterio de medición de proyecto: Volumen medido sobre las secciones teóricas de la excavación, según documentación gráfica de Proyecto.Criterio de medición de obra: Se medirá el volumen teórico ejecutado según especificaciones de Proyecto, sin incluir los incrementos por excesos de excavación no autorizados. | I8: 142.04 | J8: =D8*I8 -> 15634.343 | K8: Fuera de la vivienda (promotor o Knubo)
A9: CAV030 | B9: VIGA DE ATADO HA-25/F/20/XC2 | C9: m³ | D9: 54.76 | E9: =D9/16 -> 3.4225 | F9: VIGAS DE ATADO PAREADO 1-2: 1 × 17.20 × 0.40 PAREADO 3-4: 1 × 16.30 × 0.40 AISLADA 5: 1 × 9.95 × 0.40 PAREADO 6-7: 1 × 17.20 × 0.40 PAREADO 8-9: 1 × 16.30 × 0.40 AISLADA 10: 1 × 10.15 × 0.40 PAREADO 11-12: 1 × 17.20 × 0.40 PAREADO 13-14: 1 × 16.30 × 0.40 PAREADO 15-16: 1 × 16.30 × 0.40 | H9: VIGA DE ATADO HA-25/F/20/XC2/VALLADOSViga de atado de hormigón armado, realizada con hormigón HA-25/F/20/XC2 fabricado en central, y vertido con cubilote, y acero, UNE-EN 10080 B 500 S, con una cuantía aproximada de 61,8 kg/m³. Incluso alambre de atar y separadores.Criterio de valoración económica: El precio incluye la elaboración de la ferralla (corte, doblado y conformado de elementos) en taller industrial y el montaje en el lugar definitivo de su colocación en obra, pero no incluye el encofrado.Incluye: Colocación de la armadura con separadores homologados. Vertido y compactación del hormigón. Coronación y enrase. Curado del hormigón.Criterio de medición de proyecto: Volumen medido sobre las secciones teóricas de la excavación, según documentación gráfica de Proyecto.Criterio de medición de obra: Se medirá el volumen teórico ejecutado según especificaciones de Proyecto, sin incluir los incrementos por excesos de excavación no autorizados. | I9: 178.34 | J9: =D9*I9 -> 9765.8984 | K9: Fuera de la vivienda (promotor o Knubo)
A10: CAV030b | B10: ZUNCHO HA-25/F/20/XC2/VALLADOS | C10: m³ | D10: 139.54 | E10: =D10/16 -> 8.72125 | F10: MUROS BLOQUE H.A. para revestir Vallados a calle Perímetro parcela total: 1 × 289.00 × 0.40 × 0.40 Muros separación pareados VIV 1-VIV 2: 1 × 8.35 × 0.40 × 0.40 VIV 3-VIV 4: 1 × 8.80 × 0.40 × 0.40 VIV 6-VIV 7: 1 × 8.35 × 0.40 × 0.40 VIV 8-VIV 9: 1 × 8.35 × 0.40 × 0.40 VIV 11-VIV 12: 1 × 8.70 × 0.40 × 0.40 VIV 13-VIV 14: 1 × 8.35 × 0.40 × 0.40 VIV 15-VIV 16: 1 × 8.35 × 0.40 × 0.40 MUROS BLOQUE H.A. cara vista Separación entre viviendas VIV 1-VIV 2: 1 × 1.90 × 0.40 × 0.40 VIV 2-VIV 3: 1 × 19.75 × 0.40 × 0.40 VIV 3-VIV 4: 1 × 1.50 × 0.40 × 0.40 VIV 4-VIV 5: 1 × 19.75 × 0.40 × 0.40 VIV 5-VIV 6: 1 × 19.75 × 0.40 × 0.40 VIV 6-VIV 7: 1 × 1.90 × 0.40 × 0.40 VIV 8-VIV 9: 1 × 3.90 × 0.40 × 0.40 VIV 9-VIV 10: 1 × 21.75 × 0.40 × 0.40 VIV 10-VIV 11: 1 × 21.75 × 0.40 × 0.40 VIV 11-VIV 12: 1 × 3.60 × 0.40 × 0.40 VIV 13-VIV 14: 1 × 3.00 × 0.40 × 0.40 VIV 14-VIV 15: 1 × 20.85 × 0.40 × 0.40 VIV 15-VIV 16: 1 × 3.00 × 0.40 × 0.40 VIV 16-PARCELA 17: 1 × 21.10 × 0.40 × 0.40 Separación viviendas-Zona común Contención diferencia de niveles VIV 1-VIV 2: 1 × 30.90 × 0.40 × 0.40 VIV 3-VIV 4: 1 × 28.60 × 0.40 × 0.40 VIV 5: 1 × 15.75 × 0.40 × 0.40 VIV 6-VIV 7: 1 × 28.70 × 0.40 × 0.40 1 × 20.60 × 0.40 × 0.40 VIV 8-VIV 9: 1 × 25.65 × 0.40 × 0.40 VIV 10: 1 × 14.15 × 0.40 × 0.40 VIV 11-VIV 12: 1 × 28.75 × 0.40 × 0.40 VIV 13-VIV 14: 1 × 29.90 × 0.40 × 0.40 1 × 21.00 × 0.40 × 0.40 VIV 15-VIV 16: 1 × 31.50 × 0.40 × 0.40 CASETA APEROS: 1 × 13.45 × 0.40 × 0.40 PERÍMETRO PISCINA: 1 × 71.40 × 0.40 × 0.40 | H10: ZUNCHO HA-25/F/20/XC2/VALLADOSZuncho de hormigón armado, realizada con hormigón HA-25/F/20/XC2 fabricado en central, y vertido con cubilote, y acero, UNE-EN 10080 B 500 S, con una cuantía aproximada de 61,8 kg/m³. Incluso alambre de atar y separadores.Criterio de valoración económica: El precio incluye la elaboración de la ferralla (corte, doblado y conformado de elementos) en taller industrial y el montaje en el lugar definitivo de su colocación en obra, pero no incluye el encofrado.Incluye: Colocación de la armadura con separadores homologados. Vertido y compactación del hormigón. Coronación y enrase. Curado del hormigón.Criterio de medición de proyecto: Volumen medido sobre las secciones teóricas de la excavación, según documentación gráfica de Proyecto.Criterio de medición de obra: Se medirá el volumen teórico ejecutado según especificaciones de Proyecto, sin incluir los incrementos por excesos de excavación no autorizados. | I10: 178.34 | J10: =D10*I10 -> 24885.564 | K10: Fuera de la vivienda (promotor o Knubo)
A11: ANS030 | B11: SOLERA VENTILADA C-50 "CÁVITI" 50+5 cm | C11: m² | D11: 1207.85 | E11: =D11/16 -> 75.490625 | F11: PAREADO TIPO: 7 × 150.40 AISLADA TIPO 1 (VIVIENDA 5): 1 × 77.10 AISLADA TIPO 2 (VIVIENDA 10): 1 × 77.95 | G11: Medidas: 750x580x500mm · Color: negro · Marca/serie: CÁVITI | H11: SOLERA VENTILADA C-50 "CÁVITI" 50+5 cmSolera ventilada de hormigón armado de 50+5 cm de canto, sobre encofrado perdido de piezas de polipropileno reciclado, C-50 "CÁVITI", de 750x580x500 mm, color negro, realizada con hormigón HA-25/B/12/IIa fabricado en central, y vertido con cubilote, y malla electrosoldada ME 10x10 Ø 5-5 B 500 T 6x2,20 UNE-EN 10080 como armadura de reparto, colocada sobre separadores homologados en capa de compresión de 5 cm de espesor, incluida tabica perimetral de hormigón armado de ancho máximo 15 cm y encofrado de la misma; con juntas de retracción de 5 mm de espesor, mediante corte con disco de diamante; apoyado todo ello sobre base de hormigón de limpieza (NO INCLUIDO EN ESTE PRECIO). Incluso panel de poliestireno expandido de 3 cm de espesor, para la ejecución de juntas de dilatación. | I11: 39.45 | J11: =D11*I11 -> 47649.683 | K11: Lo sustituye el módulo: no se pide así
A12: EHU030b | B12: FORJADO UNIDIRECCIONAL 30 cm SEMIVIGUETA ARMADA/BOV HORMIGÓN/PILARES Y VIGAS 0,134 m³/m² | C12: m² | D12: 1285.15 | E12: =D12/16 -> 80.321875 | F12: PRIMER FORJADO (Techo de planta baja) PAREADO TIPO: 7 × 160.60 AISLADA TIPO 1 (VIVIENDA 5): 1 × 81.55 AISLADA TIPO 2 (VIVIENDA 10): 1 × 79.40 | H12: FORJADO UNIDIRECCIONAL 30 cm SEMIVIGUETA ARMADA/BOV HORMIGÓN/PILARES Y VIGAS 0,134 m³/m²Estructura de hormigón armado, realizada con hormigón HA-25/F/20/X0 fabricado en central, y vertido con cubilote, con un volumen total de hormigón en forjado y vigas de 0,134 m³/m², y acero, UNE-EN 10080 B 500 S, en zona de paños, vigas y zunchos, cuantía 6,4 kg/m², constituida por: FORJADO UNIDIRECCIONAL: horizontal, de canto 30 cm, intereje de 72 cm; montaje y desmontaje de sistema de encofrado continuo, con acabado tipo industrial para revestir, formado por: superficie encofrante de tableros de madera tratada, reforzados con varillas y perfiles, amortizables en 25 usos, estructura soporte horizontal de sopandas metálicas y accesorios de montaje, amortizables en 150 usos y estructura soporte vertical de puntales metálicos, amortizables en 150 usos; semivigueta armada con zapatilla de hormigón forjado unidireccional; bovedilla de hormigón; capa de compresión de 5 cm de espesor, con armadura de reparto formada por malla electrosoldada ME 20x20 Ø 5-5 B 500 T 6x2,20 UNE-EN 10080; vigas planas/descuelgue; altura libre de planta de entre 3 y 4 m. Incluye pilares de sección rectangular o cuadrada de hormigón armado, realizado con hormigón HA-25/F/20/XC1 fabricado en central, y vertido con cubilote, y acero, UNE-EN 10080 B 500 S, con una cuantía aproximada de 125,1 kg/m³, alambre de atar y separadores. Incluso agente filmógeno, para el curado de hormigones y morteros.Criterio de valoración económica: El precio incluye la elaboración de la ferralla (corte, doblado y conformado de elementos) en taller industrial y el montaje en el lugar definitivo de su colocación en obra.Incluye: Replanteo del sistema de encofrado. Montaje del sistema de encofrado. Replanteo de la geometría de la planta sobre el encofrado. Colocación de viguetas y bovedillas. Colocación de las armaduras con separadores homologados. Vertido y compactación del hormigón. Regleado y nivelación de la capa de compresión. Curado del hormigón. Desmontaje del sistema de encofrado.Criterio de medición de proyecto: Superficie medida en verdadera magnitud desde las caras exteriores de los zunchos del perímetro, según documentación gráfica de Proyecto, deduciendo los huecos de superficie mayor de 6 m².Criterio de medición de obra: Se medirá, en verdadera magnitud, desde las caras exteriores de los zunchos del perímetro, la superficie realmente ejecutada según especificaciones de Proyecto, deduciendo los huecos de superficie mayor de 6 m². Se consideran incluidos todos los elementos integrantes de la estructura señalados en los planos y detalles del Proyecto. | I12: 83.78 | J12: =D12*I12 -> 107669.87 | K12: Lo sustituye el módulo: no se pide así
A13: EHU030 | B13: FORJADO UNIDIRECCIONAL 30 cm SEMIVIGUETA ARMADA/BOV HORMIGÓN/PILARES Y VIGAS 0,147 m³/m² | C13: m² | D13: 1091.6 | E13: =D13/16 -> 68.225 | F13: SEGUNDO FORJADO (Techo de planta primera) PAREADO TIPO: 7 × 135.40 AISLADA TIPO 1 (VIVIENDA 5): 1 × 72.50 AISLADA TIPO 2 (VIVIENDA 10): 1 × 71.30 | H13: FORJADO UNIDIRECCIONAL 30 cm SEMIVIGUETA ARMADA/BOV HORMIGÓN/PILARES Y VIGAS 0,147 m³/m²Estructura de hormigón armado, realizada con hormigón HA-25/F/20/X0 fabricado en central, y vertido con cubilote, con un volumen total de hormigón en forjado y vigas de 0,147 m³/m², y acero, UNE-EN 10080 B 500 S, en zona de paños, vigas y zunchos, cuantía 6,9 kg/m², constituida por: FORJADO UNIDIRECCIONAL: horizontal, de canto 30 cm, intereje de 72 cm; montaje y desmontaje de sistema de encofrado continuo, con acabado tipo industrial para revestir, formado por: superficie encofrante de tableros de madera tratada, reforzados con varillas y perfiles, amortizables en 25 usos, estructura soporte horizontal de sopandas metálicas y accesorios de montaje, amortizables en 150 usos y estructura soporte vertical de puntales metálicos, amortizables en 150 usos; semivigueta armada con zapatilla de hormigón forjado unidireccional; bovedilla de hormigón; capa de compresión de 5 cm de espesor, con armadura de reparto formada por malla electrosoldada ME 20x20 Ø 5-5 B 500 T 6x2,20 UNE-EN 10080; vigas planas/descuelgue; altura libre de planta de entre 3 y 4 m. Incluye pilares de sección rectangular o cuadrada de hormigón armado, realizado con hormigón HA-25/F/20/XC1 fabricado en central, y vertido con cubilote, y acero, UNE-EN 10080 B 500 S, con una cuantía aproximada de 125,1 kg/m³, alambre de atar y separadores. Incluso agente filmógeno, para el curado de hormigones y morteros.Criterio de valoración económica: El precio incluye la elaboración de la ferralla (corte, doblado y conformado de elementos) en taller industrial y el montaje en el lugar definitivo de su colocación en obra.Incluye: Replanteo del sistema de encofrado. Montaje del sistema de encofrado. Replanteo de la geometría de la planta sobre el encofrado. Colocación de viguetas y bovedillas. Colocación de las armaduras con separadores homologados. Vertido y compactación del hormigón. Regleado y nivelación de la capa de compresión. Curado del hormigón. Desmontaje del sistema de encofrado.Criterio de medición de proyecto: Superficie medida en verdadera magnitud desde las caras exteriores de los zunchos del perímetro, según documentación gráfica de Proyecto, deduciendo los huecos de superficie mayor de 6 m².Criterio de medición de obra: Se medirá, en verdadera magnitud, desde las caras exteriores de los zunchos del perímetro, la superficie realmente ejecutada según especificaciones de Proyecto, deduciendo los huecos de superficie mayor de 6 m². Se consideran incluidos todos los elementos integrantes de la estructura señalados en los planos y detalles del Proyecto. | I13: 85.14 | J13: =D13*I13 -> 92938.824 | K13: Lo sustituye el módulo: no se pide así
A14: EHE010 | B14: LOSA DE ESCALERA h=17 cm | C14: m² | D14: 112 | E14: =D14/16 -> 7 | F14: TODA LA OBRA: 16 × 7.00 × 1.00 | H14: LOSA DE ESCALERA h=17 cmLosa de escalera de hormigón armado de 17 cm de espesor, con peldañeado de fábrica (no incluido en este precio), realizada con hormigón HA-25/F/20/XC2 fabricado en central, y vertido con cubilote, y acero UNE-EN 10080 B 500 S, con una cuantía aproximada de 20,5 kg/m²; montaje y desmontaje de sistema de encofrado, con acabado tipo industrial para revestir en su cara inferior y laterales, en planta de hasta 3 m de altura libre, formado por: superficie encofrante de tablones de madera de pino, amortizables en 10 usos, estructura soporte horizontal de tablones de madera de pino, amortizables en 10 usos y estructura soporte vertical de puntales metálicos, amortizables en 150 usos. Incluso alambre de atar, separadores y líquido desencofrante, para evitar la adherencia del hormigón al encofrado. | I14: 69.16 | J14: =D14*I14 -> 7745.92 | K14: Lo sustituye el módulo: no se pide así
A15: CSL010 | B15: LOSA CIMENTACIÓN C. TÉCNICO PISCINAS | C15: m³ | D15: 21 | E15: =D15/16 -> 1.3125 | F15: Base cuarto técnico piscinas: 1 × 21.00 | H15: LOSA CIMENTACIÓN C. TÉCNICO PISCINASLosa de cimentación de hormigón armado, realizada con hormigón HA-25/F/20/XC2 fabricado en central, y vertido con bomba, y acero UNE-EN 10080 B 500 S, con una cuantía aproximada de 85 kg/m³; acabado superficial liso mediante regla vibrante. Incluso armaduras para formación de foso de ascensor, refuerzos, pliegues, encuentros, arranques y esperas en muros, escaleras y rampas, cambios de nivel, alambre de atar, y separadores. | I15: 131.67 | J15: =D15*I15 -> 2765.07 | K15: Fuera de la vivienda (promotor o Knubo)
A16: EHL010 | B16: LOSA h= 20 cm CASETA APEROS/C TÉCNICO PISCINAS | C16: m² | D16: 34.45 | E16: =D16/16 -> 2.153125 | F16: Forjado caseta aperos: 1 × 13.45 Forjado cuarto técnico piscinas: 1 × 21.00 | H16: LOSA h= 20 cm CASETA APEROS/C TÉCNICO PISCINASLosa maciza de hormigón armado, horizontal, con altura libre de planta de hasta 3 m, canto 20 cm, realizada con hormigón HA-25/B/20/IIa fabricado en central, y vertido con cubilote, y acero UNE-EN 10080 B 500 S, con una cuantía aproximada de 25 kg/m²; montaje y desmontaje de sistema de encofrado continuo, con acabado tipo industrial para revestir, formado por: superficie encofrante de tableros de madera tratada, reforzados con varillas y perfiles, amortizables en 25 usos; estructura soporte horizontal de sopandas metálicas y accesorios de montaje, amortizables en 150 usos y estructura soporte vertical de puntales metálicos, amortizables en 150 usos. Incluso nervios y zunchos perimetrales de planta y huecos, alambre de atar, separadores, aplicación de líquido desencofrante y agente filmógeno para el curado de hormigones y morteros. | I16: 136.99 | J16: =D16*I16 -> 4719.3055 | K16: Fuera de la vivienda (promotor o Knubo)
A17: CCS030b | B17: MURO SÓTANO HORMIGÓN ARMADO/2C 25cm HA-25/F/20/XC2 | C17: m³ | D17: 12.95 | E17: =D17/16 -> 0.809375 | F17: Perímetro cuarto técnico piscinas: 1 × 18.50 × 0.25 × 2.80 | H17: MURO SÓTANO HORMIGÓN ARMADO/2C 25cm HA-25/F/20/XC2Muro de sótano de hormigón armado encofrado a 2 caras, realizado con hormigón HA-25/F/20/XC2 fabricado en central, y vertido con bomba, y acero UNE-EN 10080 B 500 S, con una cuantía aproximada de 77,8 kg/m³(incluyendo armadura de pilares a cimentación), ejecutado por bataches, con un grado de complejidad medio, montaje y desmontaje de sistema de encofrado con acabado tipo industrial para revestir, realizado con paneles metálicos modulares, amortizables en 150 usos. Incluso alambre de atar, separadores, pasamuros para paso de los tensores y líquido desencofrante para evitar la adherencia del hormigón al encofrado. Incluso alambre de atar y separadores; cordón de polietileno expandido, para fondo de junta; masilla elastómera tixotrópica, monocomponente, aplicada con pistola desde el fondo de junta hacia fuera; y posterior revestimiento con mortero tixotrópico monocomponente, para sellado impermeabilizante de los huecos pasamuros para paso de los tensores del encofrado.Criterio de valoración económica: El precio incluye la elaboración y el montaje de la ferralla en el lugar definitivo de su colocación en obra, así como el encofrado.Incluye: Colocación de la armadura con separadores homologados. Resolución de juntas de construcción. Limpieza de la base de apoyo del muro en la cimentación. Vertido y compactación del hormigón. Curado del hormigón. Extracción de los pasamuros. Sellado de los huecos pasamuros. Reparación de defectos superficiales, si procede.Criterio de medición de proyecto: Volumen medido sobre la sección teórica de cálculo, según documentación gráfica de Proyecto, deduciendo los huecos de superficie mayor de 2 m².Criterio de medición de obra: Se medirá el volumen teórico ejecutado según especificaciones de Proyecto, deduciendo los huecos de superficie mayor de 2 m².Criterio de valoración económica: El precio incluye la elaboración y el montaje de la ferralla en el lugar definitivo de su colocación en obra, incluyendo armado de pilares y el encofrado. | I17: 334.8 | J17: =D17*I17 -> 4335.66 | K17: Fuera de la vivienda (promotor o Knubo)
A18: D04PS155 | B18: SOLERA HA-25 2#200x200x5 20 cm+ENCACHADO+PVC | C18: m² | D18: 559.45 | E18: =D18/16 -> 34.965625 | F18: PORCHE JARDÍN (pérgola posterior) PAREADO TIPO: 14 × 23.55 AISLADA TIPO 1 (VIVIENDA 5): 1 × 24.70 AISLADA TIPO 2 (VIVIENDA 10): 1 × 22.55 ZONA COMÚN Piscina adultos: 1 × 142.25 Piscina chapoteo: 1 × 40.25 | G18: Medidas: 200x200x5mm | H18: SOLERA HA-25 2#200x200x5 20 cm+ENCACHADO+PVCSolera de 20 cm de espesor, realizada con hormigón HA-25/F/20/XC2 N/mm², tamaño máximo del árido 20 mm elaborado en central, i/vertido, colocación y armado con doble mallazo electrosoldado #200x200x5 mm, incluso p.p. de juntas, aserrado de las mismas, fratasado y encachado de piedra caliza 40/80 de 20 cm de espesor, extendido y compactado con pisón, con lámina intermedia de PVC Danopol HS de 1,5 mm. Según Codigo Estructural. | I18: 26.81 | J18: =D18*I18 -> 14998.854 | K18: Fuera de la vivienda (promotor o Knubo)
B19: Total del capítulo (PEM del proyecto) | J19: =SUM(J5:J18) -> 371011.56

Sheet 05 Cubiertas
A1: Névola · Cubiertas · 16 viviendas
A2: Capítulo C.05 del proyecto de ejecución (BC3 de julio de 2026). Medición de toda la promoción y su desglose tal como viene en el proyecto. Precios del proyecto (CYPE, PEM, sin IVA), solo como referencia.
A4: Código | B4: Partida | C4: Ud | D4: Total 16 viv. | E4: Media por vivienda | F4: Desglose de la medición (proyecto) | G4: Datos clave (medidas, color, marca) | H4: Descripción completa del proyecto | I4: Precio proyecto | J4: Importe PEM | K4: Alcance en el sistema modular
A5: D08PD002 | B5: CUBIERTA PLANA NO TRANSITABLE/GRAVA | C5: m² | D5: 1195.45 | E5: =D5/16 -> 74.715625 | F5: CUBIERTAS PAREADOS: 7 × 147.50 AISLADA TIPO 1 (VIVIENDA 5): 1 × 76.35 AISLADA TIPO 2 (VIVIENDA 10): 1 × 75.40 CASETA APEROS: 1 × 11.20 | G5: Medidas: 1250x600mm | H5: CUBIERTA PLANA NO TRANSITABLE/GRAVACubierta invertida no transitable no ventilada acabada en grava u hormigon regleado, para zonas climáticas D/E, constituida por:1) Barrera de vapor encima de forjado con lámina de LDPE (film de polietileno baja densidad), VAPOR FLAG de SOPREMA2) Capa de hormigón celular de 8 cm de espesor medio, para formación de pendientes (mínima 2%), con tendido de regularización con mortero de cemento M5 de 2 cm de espesor. 3) Membrana impermeabilizante bicapa ADHERIDA al soporte formada por emulsión asfáltica EMUFAL PRIMER con una dotación > 300 g/m², LBM plastomérico APP con armadura de fieltro de fibra de vidrio (FV) con una flexibilidad a bajas tª = -15ºC tipo MORTERPLAS FV 3 kg designación: LBM-30-FV según UNE 104410:2013, lámina superior totalmente adherida a la inferior lámina de betún modificado plastomérico APP con armadura de fieltro de fibra de poliester (FP) con una flexibilidad a bajas tª = -15ºC tipo SOPRALENE ELITE FP 4 kg designación: LBM-40 FP según UNE 104410:2013. 4) Capa separadora de geotextil no tejido de alta tenacidad a base de polipropileno termosoldado con resistencia a la tracción de 6,5 kN/m y de resistencia al punzonamiento estático (CBR) de 1100 N con un gramage de 90 g/m² TEXXAM 700. 5) Capa de aislamiento térmico formada por planchas de poliestireno extruido de dimensiones 1250x600 mm con juntas a media madera de resistencia a la compresión de 300 KPa, conductividad térmica Lambda 0,036 W/mºK y de espesor 100 mm tipo XPS SL 100 instalada encajando las juntas a media madera para evitar puentes térmicos. Cumple para las zonas climáticas D/E. (NO INCLUIDO EN ESTE PRECIO) 6) Capa separadora antipunzonante de geotextil no tejido de alta tenacidad a base de polipropileno termosoldado con resistencia a la tracción de 12,5 kN/m y de resistencia al punzonamiento estático (CBR) de 2250 N con un gramaje de 150 g/m² TEXXAM 1500.7) Capa de gravilla de canto rodado de 6 cm de espesor. | I5: 88.8 | J5: =D5*I5 -> 106155.96 | K5: Lo sustituye el módulo: no se pide así
A6: QAB010b | B6: CUBIERTA PLANA TRANSITABLE/SOLADO FIJO | C6: m² | D6: 143.1 | E6: =D6/16 -> 8.94375 | F6: TERRAZAS P PRIMERA PAREADOS: 14 × 9.00 AISLADA TIPO 1 (VIVIENDA 5): 1 × 9.00 AISLADA TIPO 2 (VIVIENDA 10): 1 × 8.10 | G6: Medidas: 1250x600mm · Color: gris | H6: CUBIERTA PLANA TRANSITABLE/SOLADO FIJOCubierta invertida no transitable no ventilada acabada en grava u hormigon regleado, para zonas climáticas D/E, constituida por:1) Barrera de vapor encima de forjado con lámina de LDPE (film de polietileno baja densidad), VAPOR FLAG de SOPREMA2) Capa de aislamiento térmico formada por planchas de poliestireno extruido de dimensiones 1250x600 mm con juntas a media madera de resistencia a la compresión de 300 KPa, conductividad térmica Lambda 0,036 W/mºK y de espesor 100 mm tipo XPS SL 100 instalada encajando las juntas a media madera para evitar puentes térmicos. Cumple para las zonas climáticas D/E.(NO INCLUIDO EN ESTE PRECIO) 3) Capa de hormigón celular de 8 cm de espesor medio, para formación de pendientes (mínima 2%), con tendido de regularización con mortero de cemento M5 de 2 cm de espesor. 4) Capa separadora de geotextil no tejido de alta tenacidad a base de polipropileno termosoldado con resistencia a la tracción de 6,5 kN/m y de resistencia al punzonamiento estático (CBR) de 1100 N con un gramage de 90 g/m² TEXXAM 700. 5) Impermeabilización bajo revestimiento cerámico o pétreo, en paramento horizontal en terrazas, con lámina impermeabilizante flexible de polietileno, con ambas caras revestidas de geotextil no tejido, kerdi o similar, de 0,5 mm de espesor y 285 g/m², fijada al soporte con adhesivo cementoso mejorado, C2 TE S1, según UNE-EN 12004, deformable, con deslizamiento reducido y tiempo abierto ampliado, color gris, a base de cemento, áridos de granulometría fina, resinas sintéticas y aditivos especiales. Incluso complementos de refuerzo en tratamiento de puntos singulares con banda de refuerzo de polietileno, con ambas caras revestidas de geotextil no tejido, de 120 mm de anchura y de 0,7 mm de espesor; y mortero cementoso impermeabilizante flexible bicomponente, de color gris.6) Capa de protección: baldosas de gres porcelánico en formato comercial colocadas en capa fina con adhesivo cementoso de fraguado normal, C1 gris.(NO INCLUIDO EN ESTE PRECIO) | I6: 97.54 | J6: =D6*I6 -> 13957.974 | K6: Lo sustituye el módulo: no se pide así
A7: QAB010bb | B7: CUBIERTA PLANA TRANSITABLE/SOLADO FIJO | C7: m² | D7: 21 | E7: =D7/16 -> 1.3125 | F7: C TÉCNICO PISCINAS: 1 × 21.00 | G7: Color: gris | H7: CUBIERTA PLANA TRANSITABLE/SOLADO FIJOCubierta invertida no transitable no ventilada acabada en grava u hormigon regleado, para zonas climáticas D/E, constituida por:1) Barrera de vapor encima de forjado con lámina de LDPE (film de polietileno baja densidad), VAPOR FLAG de SOPREMA 2) Capa de hormigón celular de 8 cm de espesor medio, para formación de pendientes (mínima 2%), con tendido de regularización con mortero de cemento M5 de 2 cm de espesor. 3) Capa separadora de geotextil no tejido de alta tenacidad a base de polipropileno termosoldado con resistencia a la tracción de 6,5 kN/m y de resistencia al punzonamiento estático (CBR) de 1100 N con un gramage de 90 g/m² TEXXAM 700. 4) Impermeabilización bajo revestimiento cerámico o pétreo, en paramento horizontal en terrazas, con lámina impermeabilizante flexible de polietileno, con ambas caras revestidas de geotextil no tejido, kerdi o similar, de 0,5 mm de espesor y 285 g/m², fijada al soporte con adhesivo cementoso mejorado, C2 TE S1, según UNE-EN 12004, deformable, con deslizamiento reducido y tiempo abierto ampliado, color gris, a base de cemento, áridos de granulometría fina, resinas sintéticas y aditivos especiales. Incluso complementos de refuerzo en tratamiento de puntos singulares con banda de refuerzo de polietileno, con ambas caras revestidas de geotextil no tejido, de 120 mm de anchura y de 0,7 mm de espesor; y mortero cementoso impermeabilizante flexible bicomponente, de color gris.5) Capa de protección: baldosas de gres porcelánico en formato comercial colocadas en capa fina con adhesivo cementoso de fraguado normal, C1 gris.(NO INCLUIDO EN ESTE PRECIO) | I7: 81.52 | J7: =D7*I7 -> 1711.92 | K7: Lo sustituye el módulo: no se pide así
B8: Total del capítulo (PEM del proyecto) | J8: =SUM(J5:J7) -> 121825.85

Sheet 06 Albañilería
A1: Névola · Albañilería · 16 viviendas
A2: Capítulo C.06 del proyecto de ejecución (BC3 de julio de 2026). Medición de toda la promoción y su desglose tal como viene en el proyecto. Precios del proyecto (CYPE, PEM, sin IVA), solo como referencia.
A4: Código | B4: Partida | C4: Ud | D4: Total 16 viv. | E4: Media por vivienda | F4: Desglose de la medición (proyecto) | G4: Datos clave (medidas, color, marca) | H4: Descripción completa del proyecto | I4: Precio proyecto | J4: Importe PEM | K4: Alcance en el sistema modular
A5: 504 | B5: HOJA EXTERIOR DE FACHADA, 1/2 PIE, DE LADRILLO CERÁMICO PERFORADO TOSCO | C5: m² | D5: 3070.32 | E5: =D5/16 -> 191.895 | F5: PAREADO TIPO Planta baja: 14 × 27.50 × 3.25 Planta primera: 14 × 27.00 × 3.15 Separación viviendas planta baja: 7 × 9.50 × 2.95 Separación viviendas planta primera: 7 × 10.10 × 2.85 -A descontar > 4.00 m² PE2: -14 × 2.80 × 2.20 PE3: -14 × 1.90 × 2.20 PE4: -14 × 2.80 × 2.10 AISLADO TIPO 1 (VIVIENDA 5) Planta baja: 1 × 37.25 × 3.25 Planta primera: 1 × 38.05 × 3.15 -A descontar > 4.00 m² PE2: -1 × 2.80 × 2.20 PE3: -1 × 1.90 × 2.20 PE4: -1 × 2.80 × 2.10 AISLADO TIPO 2 (VIVIENDA 10) Planta baja: 1 × 37.75 × 3.25 Planta primera: 1 × 37.65 × 3.15 -A descontar > 4.00 m² PE2: -1 × 2.80 × 2.20 PE3: -1 × 1.90 × 2.20 PE4: -1 × 2.80 × 2.10 Separación productos químicos piscina: 1 × 3.20 × 2.50 | G5: Medidas: 24x11x5cm · Color: gris | H5: HOJA EXTERIOR DE FACHADA, 1/2 PIE, DE LADRILLO CERÁMICO PERFORADO TOSCOEjecución de hoja exterior de 11 cm de espesor de fábrica, en cerramiento de fachada, de ladrillo cerámico perforado (tosco), para revestir, 24x11x5 cm, recibida con mortero de cemento industrial, color gris, M-5, suministrado a granel. Incluso p/p de replanteo, nivelación y aplomado, mermas y roturas, enjarjes, revestimiento de los frentes de forjado con piezas cerámicas, colocadas con mortero de alta adherencia, formación de dinteles mediante vigueta prefabricada T-18, revestida con piezas cerámicas, colocadas con mortero de alta adherencia, jambas y mochetas, ejecución de encuentros y puntos singulares y limpieza. | I5: 23.49 | J5: =D5*I5 -> 72121.817 | K5: Lo sustituye el módulo: no se pide así
A6: 504b | B6: HOJA EXTERIOR DE FACHADA, 1 PIE, DE LADRILLO CERÁMICO PERFORADO TOSCO | C6: m² | D6: 306.38 | E6: =D6/16 -> 19.14875 | F6: PETOS PAREADO TIPO Petos cubierta: 7 × 54.00 × 0.60 Petos terraza: 14 × 7.15 × 0.30 AISLADO TIPO 1 (VIVIENDA 5) Petos cubierta: 1 × 38.05 × 0.60 Petos terraza: 1 × 7.15 × 0.30 AISLADO TIPO 2 (VIVIENDA 10) Petos cubierta: 1 × 37.65 × 0.60 Petos terraza: 1 × 6.60 × 0.30 | G6: Medidas: 24x11x5cm · Color: gris | H6: HOJA EXTERIOR DE FACHADA, 1 PIE, DE LADRILLO CERÁMICO PERFORADO TOSCOEjecución de hoja exterior de 24 cm de espesor de fábrica, en cerramiento de fachada, de ladrillo cerámico perforado (tosco), para revestir, 24x11x5 cm, recibida con mortero de cemento industrial, color gris, M-5, suministrado a granel. Incluso p/p de replanteo, nivelación y aplomado, mermas y roturas, enjarjes, revestimiento de los frentes de forjado con piezas cerámicas, colocadas con mortero de alta adherencia, formación de dinteles mediante vigueta prefabricada T-18, revestida con piezas cerámicas, colocadas con mortero de alta adherencia, jambas y mochetas, ejecución de encuentros y puntos singulares y limpieza. | I6: 34.06 | J6: =D6*I6 -> 10435.303 | K6: Lo sustituye el módulo: no se pide así
A7: 312 | B7: DINTEL VIGUETA T-18 | C7: m | D7: 358 | E7: =D7/16 -> 22.375 | F7: PAREADO TIPO PE1: 14 × 1.00 × 2.00 PE2: 14 × 1.00 × 3.30 PE3: 14 × 1.00 × 2.40 PE4: 14 × 1.00 × 3.30 V1: 14 × 1.00 × 1.20 V2: 14 × 1.00 × 1.35 V3: 14 × 2.00 × 2.00 V4: 14 × 1.00 × 2.00 V5: 14 × 1.00 × 1.20 V6: 14 × 1.00 × 1.20 AISLADAS (VIVIENDA 5-10) PE1: 2 × 1.00 × 2.00 PE2: 2 × 1.00 × 3.30 PE3: 2 × 1.00 × 2.40 PE4: 2 × 1.00 × 3.30 V1: 2 × 1.00 × 1.20 V2: 2 × 1.00 × 1.35 V3: 2 × 2.00 × 2.00 V4: 2 × 1.00 × 2.00 V5: 2 × 1.00 × 1.20 V6: 2 × 1.00 × 1.20 V7: 2 × 1.00 × 1.25 F1: 2 × 1.00 × 1.40 PUERTA APEROS: 1 × 1.00 × 1.50 | H7: DINTEL VIGUETA T-18Vigueta autorresistente de hormigón pretensado T-18 de hasta 4,00 m de longitud, apoyada sobre capa de mortero de cemento, industrial, M-7,5, de 2 cm de espesor, con revestimiento de ladrillo cerámico en ambas caras; para la formación de dintel en hueco de muro de fábrica. Incluso p/p de replanteo, nivelación y aplomado, y limpieza. | I7: 15.55 | J7: =D7*I7 -> 5566.9 | K7: Lo sustituye el módulo: no se pide así
A8: 505 | B8: ENFOSCADO DE CEMENTO | C8: m² | D8: 3973.66 | E8: =D8/16 -> 248.35375 | F8: -CÁMARAS PAREADO TIPO Planta baja: 14 × 27.50 × 3.25 Planta primera: 14 × 27.00 × 3.15 Separación viviendas planta baja: 14 × 9.50 × 2.95 Separación viviendas planta primera: 14 × 10.10 × 2.85 -A descontar > 4.00 m² PE2: -14 × 2.80 × 2.20 PE3: -14 × 1.90 × 2.20 PE4: -14 × 2.80 × 2.10 AISLADO TIPO 1 (VIVIENDA 5) Planta baja: 1 × 37.25 × 3.25 Planta primera: 1 × 38.05 × 3.15 -A descontar > 4.00 m² PE2: -1 × 2.80 × 2.20 PE3: -1 × 1.90 × 2.20 PE4: -1 × 2.80 × 2.10 AISLADO TIPO 2 (VIVIENDA 10) Planta baja: 1 × 37.75 × 3.25 Planta primera: 1 × 37.65 × 3.15 -A descontar > 4.00 m² PE2: -1 × 2.80 × 2.20 PE3: -1 × 1.90 × 2.20 PE4: -1 × 2.80 × 2.10 APLACADO FACHADAS PAREADO TIPO Fachada principal: 14 × 17.50 Fachada posterior: 14 × 3.80 Fachada lateral: 14 × 2.25 Rodapié fachada p baja: 14 × 28.10 × 0.20 Rodapié fachada terraza p primera: 14 × 7.15 × 0.20 AISLADA TIPO 1 (VIVIENDA 5) Fachada principal: 1 × 16.40 Fachada posterior: 1 × 3.80 Fachada lateral derecha: 1 × 2.25 Fachada lateral izquierda: 1 × 2.25 Rodapié fachada p baja: 1 × 41.10 × 0.20 Rodapié fachada terraza p primera: 1 × 7.15 × 0.20 AISLADA TIPO 2 (VIVIENDA 10) Fachada principal: 1 × 16.40 Fachada posterior: 1 × 4.40 Fachada lateral derecha: 1 × 2.25 Fachada lateral izquierda: 1 × 2.25 Rodapié fachada p baja: 1 × 41.55 × 0.20 Rodapié fachada terraza p primera: 1 × 6.60 × 0.20 Separación cuarto productos químicos: 2 × 3.20 × 2.50 | H8: ENFOSCADO DE CEMENTO Formación de revestimiento continuo de mortero de cemento, tipo GP CSIII W1, a buena vista, de 15 mm de espesor, aplicado sobre un paramento vertical interior, en el trasdós de la hoja exterior de fachada con cámara de aire, hasta 3 m de altura, acabado superficial rugoso. Incluso p/p de preparación de la superficie soporte, formación de juntas, rincones, maestras con separación entre ellas no superior a tres metros, remates en los encuentros con paramentos, revestimientos u otros elementos recibidos en su superficie. | I8: 7.47 | J8: =D8*I8 -> 29683.24 | K8: Lo sustituye el módulo: no se pide así
A9: RQO020 | B9: MORTERO MONOCAPA | C9: m² | D9: 3642.26 | E9: =D9/16 -> 227.64125 | F9: PAREADO TIPO Planta baja: 14 × 27.50 × 3.25 Planta primera: 14 × 27.00 × 3.15 Petos cubierta (int y ext): 7 × 54.00 × 2.00 × 0.60 Petos terraza (int y ext): 14 × 7.15 × 2.00 × 0.30 -A descontar > 4.00 m² (aplacados + huecos) Fachada principal: -14 × 22.55 Fachada posterior: -14 × 12.30 AISLADO TIPO 1 (VIVIENDA 5) Planta baja: 1 × 37.25 × 3.25 Planta primera: 1 × 38.05 × 3.15 Petos cubierta (int y ext): 1 × 38.05 × 2.00 × 0.60 Petos terraza (int y ext): 1 × 7.15 × 2.00 × 0.30 -A descontar > 4.00 m² (aplacados + huecos) Fachada principal: -1 × 22.55 Fachada posterior: -1 × 12.30 AISLADO TIPO 2 (VIVIENDA 10) Planta baja: 1 × 37.75 × 3.25 Planta primera: 1 × 37.65 × 3.15 Petos cubierta (int y ext): 1 × 37.65 × 2.00 × 0.60 Petos terraza (int y ext): 1 × 6.60 × 2.00 × 0.30 -A descontar > 4.00 m² (aplacados + huecos) Fachada principal: -1 × 22.55 Fachada posterior: -1 × 16.20 VALLADOS (a calle y separación pareados) VIV 1: 2 × 4.60 × 2.00 1 × 6.15 × 1.00 VIV 2: 2 × 3.60 × 2.00 1 × 8.45 × 1.00 VIV 3: 2 × 3.60 × 2.00 1 × 9.50 × 1.00 VIV 4: 2 × 3.90 × 2.00 1 × 8.05 × 1.00 VIV 5: 2 × 3.00 × 2.00 1 × 8.20 × 1.00 VIV 6: 2 × 3.00 × 2.00 1 × 8.10 × 1.00 VIV 7: 2 × 4.60 × 2.00 1 × 9.75 × 1.00 VIV 8: 2 × 3.90 × 2.00 1 × 27.25 × 1.00 VIV 9: 2 × 3.60 × 2.00 1 × 5.60 × 1.00 VIV 10: 2 × 3.20 × 2.00 1 × 6.90 × 1.00 VIV 11: 2 × 3.20 × 2.00 1 × 6.40 × 1.00 VIV 12: 2 × 3.90 × 2.00 1 × 23.40 × 1.00 VIV 13: 2 × 3.65 × 2.00 1 × 6.50 × 1.00 VIV 14: 2 × 3.60 × 2.00 1 × 6.60 × 1.00 VIV 15: 2 × 3.60 × 2.00 1 × 6.60 × 1.00 VIV 16: 2 × 3.65 × 2.00 1 × 6.00 × 1.00 Incremento jambas 16 × 0.80 × 2.00 7 × 0.80 × 1.00 9 × 1.20 × 1.00 Muros separación pareados VIV 1-VIV 2: 2 × 8.35 × 2.00 VIV 3-VIV 4: 2 × 8.80 × 2.00 VIV 6-VIV 7: 2 × 8.35 × 2.00 VIV 8-VIV 9: 2 × 8.35 × 2.00 VIV 11-VIV 12: 2 × 8.70 × 2.00 VIV 13-VIV 14: 2 × 8.35 × 2.00 VIV 15-VIV 16: 2 × 8.35 × 2.00 | G9: Color: Blanco | H9: MORTERO MONOCAPAFormación en fachadas de revestimiento continuo de 12 mm de espesor, impermeable al agua de lluvia, con mortero monocapa hidrófobo de red tridimensional, para la impermeabilización y decoración de fachadas, tipo OC CSIII W2, según UNE-EN 998-1, acabado raspado, color Blanco, compuesto de cemento y cargas minerales, aditivado en masa con polímeros. Aplicado manualmente sobre una superficie de ladrillo cerámico, ladrillo o bloque de hormigón o bloque de termoarcilla. Incluso p/p de preparación de la superficie soporte, colocación de malla de fibra de vidrio antiálcalis para refuerzo de encuentros entre materiales diferentes y en los frentes de forjado, en un 20% de la superficie del paramento, formación de juntas, rincones, maestras, aristas, mochetas, jambas y dinteles y remates en los encuentros con paramentos, revestimientos u otros elementos recibidos en su superficie.Incluye: Preparación de la superficie soporte. Despiece de los paños de trabajo. Aristado y realización de juntas. Colocación de malla para armar mortero. Preparación del mortero monocapa. Aplicación del mortero monocapa. Regleado y alisado del revestimiento. Acabado superficial. Repasos y limpieza final.Criterio de medición de proyecto: Superficie medida según documentación gráfica de Proyecto, deduciendo los huecos de superficie mayor de 3 m² e incluyendo el desarrollo de las mochetas.Criterio de medición de obra: Se medirá la superficie realmente ejecutada según especificaciones de Proyecto, deduciendo los huecos de superficie mayor de 3 m² e incluyendo el desarrollo de las mochetas. | I9: 22.36 | J9: =D9*I9 -> 81440.934 | K9: Lo sustituye el módulo: no se pide así
A10: HYO020 | B10: PELDAÑEADO ESCALERAS | C10: m | D10: 336 | E10: =D10/16 -> 21 | F10: ESCALERAS INTERIORES TODA LA OBRA: 16 × 21.00 × 1.00 | H10: PELDAÑEADO ESCALERASFormación de peldañeado de escalera con ladrillo cerámico hueco recibido con mortero de cemento, industrial, M-5, sobre la losa o bóveda de escalera, como base para la posterior colocación del acabado de peldaños. | I10: 16.1 | J10: =D10*I10 -> 5409.6 | K10: Lo sustituye el módulo: no se pide así
A11: HEC030 | B11: PREMARCOS CARPINTERÍA INTERIOR | C11: Ud | D11: 128 | E11: =D11/16 -> 8 | F11: Carpintería interior (TODA LA OBRA): 16 × 8.00 | H11: PREMARCOS CARPINTERÍA INTERIORSuministro, colocación y fijación de precerco de madera de pino, durante la ejecución del tabique y antes de colocar el pavimento, con tornillería al entramado autoportante del tabique de placas, para fijar posteriormente, sobre él, el marco de la carpintería de hasta 2 m² de superficie. | I11: 4.26 | J11: =D11*I11 -> 545.28 | K11: Lo sustituye el módulo: no se pide así
A12: HEC010 | B12: PREMARCOS CARPINTERÍA EXTERIOR | C12: Ud | D12: 181 | E12: =D12/16 -> 11.3125 | F12: PAREADO TIPO: 14 × 11.00 AISLADA TIPO 1(VIVIENDA 5): 1 × 13.00 AISLADA TIPO 2(VIVIENDA 10): 1 × 13.00 CASETA APEROS: 1 × 1.00 | G12: Medidas: 50x20x1,5mm | H12: PREMARCOS CARPINTERÍA EXTERIORSuministro, colocación y fijación de premarco de aluminio, de 50x20x1,5 mm, ensamblado mediante escuadras y con tornillos de fijación, para fijar posteriormente, sobre él, el marco de la carpintería exterior hasta 6 m² de superficie. | I12: 13.61 | J12: =D12*I12 -> 2463.41 | K12: Lo sustituye el módulo: no se pide así
A13: 518 | B13: FORRADO CHIMENEAS | C13: Ud | D13: 16 | E13: =D13/16 -> 1 | F13: Chimeneas: 16 | H13: FORRADO CHIMENEASFormación de fábrica de ladrillo cerámico perforado tosco, de hasta 0,65 m² de sección y 1,5 m de altura dimensiones máximas, recibida con mortero de cemento, industrial, M-5, para forrado de conductos de instalaciones situados en cubierta plana/inclinada. Incluso p/p de mermas y roturas, enjarjes y ejecución de encuentros y puntos singulares. | I13: 380.06 | J13: =D13*I13 -> 6080.96 | K13: Lo sustituye el módulo: no se pide así
A14: 519 | B14: AYUDA ALBAÑILERÍA FONTANERÍA VIV.UNIFAMILIAR | C14: Ud | D14: 16 | E14: =D14/16 -> 1 | F14: 16 | H14: AYUDA ALBAÑILERÍA FONTANERÍA VIV.UNIFAMILIARAyuda, por vivienda unifamiliar, de cualquier trabajo de albañilería, prestada para la correcta ejecución de las instalaciones de fontanería, i/porcentaje estimado para pequeño material, medios auxiliares. | I14: 491.33 | J14: =D14*I14 -> 7861.28 | K14: Lo sustituye el módulo: no se pide así
A15: 520 | B15: AYUDA ALBAÑILERÍA ELECTRICIDAD VIV.UNIFAMILIAR | C15: Ud | D15: 16 | E15: =D15/16 -> 1 | F15: 16 | H15: AYUDA ALBAÑILERÍA ELECTRICIDAD VIV.UNIFAMILIARAyuda, por vivienda unifamiliar, de cualquier trabajo de albañilería, prestada para la correcta ejecución de las instalaciones de electricidad, i/porcentaje estimado para pequeño material, medios auxiliares. | I15: 491.33 | J15: =D15*I15 -> 7861.28 | K15: Lo sustituye el módulo: no se pide así
A16: 521 | B16: AYUDA ALBAÑILERÍA CALEFACCIÓN VIV.UNIFAMILIAR | C16: Ud | D16: 16 | E16: =D16/16 -> 1 | F16: 16 | H16: AYUDA ALBAÑILERÍA CALEFACCIÓN VIV.UNIFAMILIARAyuda, por vivienda unifamiliar, de cualquier trabajo de albañilería, necesaria para la correcta ejecución de las instalaciones de climatización, i/porcentaje estimado para pequeño material, medios auxiliares. | I16: 491.33 | J16: =D16*I16 -> 7861.28 | K16: Lo sustituye el módulo: no se pide así
B17: Total del capítulo (PEM del proyecto) | J17: =SUM(J5:J16) -> 237331.28

Sheet 07 Impermeabilización y aislami
A1: Névola · Impermeabilización y aislamiento · 16 viviendas
A2: Capítulo C.07 del proyecto de ejecución (BC3 de julio de 2026). Medición de toda la promoción y su desglose tal como viene en el proyecto. Precios del proyecto (CYPE, PEM, sin IVA), solo como referencia.
A4: Código | B4: Partida | C4: Ud | D4: Total 16 viv. | E4: Media por vivienda | F4: Desglose de la medición (proyecto) | G4: Datos clave (medidas, color, marca) | H4: Descripción completa del proyecto | I4: Precio proyecto | J4: Importe PEM | K4: Alcance en el sistema modular
A5: NHB020 | B5: BARRERA ANTICAPILARIDAD | C5: m | D5: 525.5 | E5: =D5/16 -> 32.84375 | F5: ARRANQUE MUROS DE FÁBRICA PAREADO TIPO: 7 × 64.35 AISLADA TIPO 1 (VIVIENDA 5): 1 × 37.30 AISLADA TIPO 2 (VIVIENDA 10): 1 × 37.75 | H5: BARRERA ANTICAPILARIDADBarrera anticapilaridad en arranque de muro de fábrica, de 25 cm de espesor, con lámina impermeabilizante autoadhesiva de betún modificado con elastómero (SBS), LBA-15-PE, con armadura de film de polietileno de 95 g/m² que actúa como autoprotección superior y plástico desechable siliconado en la cara inferior, de superficie no protegida, colocada con solapes sobre una capa de regularización de mortero de cemento, industrial, con aditivo hidrófugo, M-5, previa imprimación con emulsión asfáltica de base acuosa y posterior aplicación de capa de protección de mortero de cemento, industrial, con aditivo hidrófugo, M-5. | I5: 9.92 | J5: =D5*I5 -> 5212.96 | K5: Fuera de la vivienda (promotor o Knubo)
A6: 2000b | B6: IMPERMEABILIZACIÓN SUMIDEROS CUBIERTA NO TRANSITABLE | C6: Ud | D6: 33 | E6: =D6/16 -> 2.0625 | F6: CUBIERTAS (Viviendas): 16 × 2.00 CASETA APEROS: 1 × 1.00 | H6: IMPERMEABILIZACIÓN SUMIDEROS CUBIERTA NO TRANSITABLEEjecución de encuentro de cubierta plana no transitable, no ventilada, con grava, tipo convencional con sumidero de salida vertical, realizando un rebaje en el soporte alrededor del sumidero, en el que se recibirá la impermeabilización formada por: pieza de refuerzo de lámina de betún modificado con elastómero SBS, LBM(SBS)-40-FP, con armadura de fieltro de poliéster no tejido de 160 g/m², de superficie no protegida, totalmente adherida al soporte con soplete, previa imprimación con emulsión asfáltica aniónica con cargas tipo EB, y colocación de sumidero de caucho EPDM, de salida vertical, de 90 mm de diámetro, con rejilla alta de polietileno, íntegramente adherido a la pieza de refuerzo anterior con soplete. | I6: 37.44 | J6: =D6*I6 -> 1235.52 | K6: Lo sustituye el módulo: no se pide así
A7: QAF030 | B7: IMPERMEABILIZACIÓN SUMIDEROS CUBIERTA TRANSITABLE | C7: Ud | D7: 32 | E7: =D7/16 -> 2 | F7: TERRAZAS P PRIMERA (Toda la Obra): 16 × 2.00 | H7: IMPERMEABILIZACIÓN SUMIDEROS CUBIERTA TRANSITABLEEjecución de encuentro de cubierta plana transitable, no ventilada, con solado fijo, tipo convencional con sumidero de salida vertical, realizando un rebaje en el soporte alrededor del sumidero, en el que se recibirá la impermeabilización formada por: pieza de refuerzo de lámina de betún modificado con elastómero SBS, LBM(SBS)-40-FP, con armadura de fieltro de poliéster no tejido de 160 g/m², de superficie no protegida, totalmente adherida al soporte con soplete, previa imprimación con emulsión asfáltica aniónica con cargas tipo EB, y colocación de sumidero de caucho EPDM, de salida vertical, de 80 mm de diámetro, con rejilla plana de caucho EPDM, íntegramente adherido a la pieza de refuerzo anterior con soplete. | I7: 34.83 | J7: =D7*I7 -> 1114.56 | K7: Lo sustituye el módulo: no se pide así
A8: QAF020 | B8: ENCUENTRO PETO/CUBIERTA NO TRANSITABLE | C8: m | D8: 467.15 | E8: =D8/16 -> 29.196875 | F8: CUBIERTAS PAREADO TIPO: 7 × 54.00 AISLADA TIPO 1 (VIVIENDA 5): 1 × 38.05 AISLADA TIPO 2 (VIVIENDA 5): 1 × 37.65 CASETA APEROS: 1 × 13.45 | H8: ENCUENTRO PETO/CUBIERTA NO TRANSITABLEEncuentro de paramento vertical con cubierta plana no transitable, no ventilada, con grava, tipo convencional; mediante retranqueo perimetral, para la protección de la impermeabilización formada por: banda de refuerzo de 50 cm de anchura, de lámina de betún modificado con elastómero SBS, LBM(SBS)-40-FP, totalmente adherida al soporte con soplete, previa imprimación con emulsión asfáltica aniónica con cargas tipo EB y banda de terminación de 50 cm de desarrollo con lámina de betún modificado con elastómero SBS, LBM(SBS)-40-FP; acabado con mortero de cemento M-2,5. | I8: 11.92 | J8: =D8*I8 -> 5568.428 | K8: Lo sustituye el módulo: no se pide así
A9: QAF020b | B9: ENCUENTRO PETO/CUBIERTA TRANSITABLE | C9: m | D9: 226.95 | E9: =D9/16 -> 14.184375 | F9: TERRAZAS (incluido en cubierta transitable) PAREADO TIPO: 14 × 14.25 AISLADA TIPO 1 (VIVIENDA 5): 1 × 14.25 AISLADA TIPO 2 (VIVIENDA 10): 1 × 13.20 | H9: ENCUENTRO PETO/CUBIERTA TRANSITABLEEncuentro de paramento vertical con cubierta plana transitable, no ventilada, con solado fijo, tipo convencional; mediante retranqueo perimetral, para la protección de la impermeabilización formada por: banda de refuerzo de 50 cm de anchura, de lámina de betún modificado con elastómero SBS, LBM(SBS)-40-FP, totalmente adherida al soporte con soplete, previa imprimación con emulsión asfáltica aniónica con cargas tipo EB y banda de terminación de 50 cm de desarrollo con lámina de betún modificado con elastómero SBS, LBM(SBS)-40-FP; acabado con mortero de cemento M-2,5 y rodapié (no incluido en este precio). | I9: 11.92 | J9: =D9*I9 -> 2705.244 | K9: Lo sustituye el módulo: no se pide así
A10: 403 | B10: IMP.MUROS LÁM.ASFÁLT.+LAM.DREN. | C10: m² | D10: 64.4 | E10: =D10/16 -> 4.025 | F10: Cuarto técnico piscinas: 1 × 18.40 × 3.50 | H10: IMP.MUROS LÁM.ASFÁLT.+LAM.DREN.Impermeabilización de muros de cimentación por su cara externa, constituida por: imprimación asfáltica, Impridan 100; banda de refuerzo Esterdan 30 P elastómero; lámina asfáltica de betún elastómero Esterdan 30 P elastómero, (tipo LMB-30-FP) de poliéster (fieltro no tejido de 160 gr/m2), totalmente adherida al muro con soplete; geotextil y para protección, lámina drenante nodular de polietileno de alta densidad (PEAD/HDPE), con nódulos de 8 mm de altura, resistencia a la compresión 150 kN/m² según UNE-EN ISO 604, capacidad de drenaje 5 l/(s·m) y masa nominal 0,5 kg/m²; sujeta al paramento vertical mediante fijaciones mecánicas (2 ud/m²), con los nódulos contra el muro previamente impermeabilizado. Incluso p/p de limpieza y preparación de la superficie, solapes horizontales y verticales, remates de esquinas y rincones y colocación de perfil metálico de remate superior (0,3 m/m²). | I10: 14.9 | J10: =D10*I10 -> 959.56 | K10: Fuera de la vivienda (promotor o Knubo)
A11: NIH010 | B11: IMPERMEABILIZACIÓN LOCALES HÚMEDOS/HUECOS EXTERIORES | C11: m² | D11: 367.65 | E11: =D11/16 -> 22.978125 | F11: DUCHAS (TODA LA OBRA) Baño 1: 16 × 7.40 Baño principal: 16 × 8.00 HUECOS EXTERIORES (TODA LA OBRA) PE2: 16 × 1.00 × 2.80 × 0.50 PE3: 16 × 1.00 × 1.90 × 0.50 PE4: 16 × 1.00 × 2.80 × 0.50 V1: 16 × 1.00 × 0.70 × 0.50 V2: 16 × 1.00 × 0.85 × 0.50 V3: 16 × 2.00 × 1.50 × 0.50 V4: 16 × 1.00 × 1.50 × 0.50 V5: 16 × 1.00 × 0.70 × 0.50 V6: 16 × 1.00 × 0.70 × 0.50 V7: 2 × 1.00 × 0.75 × 0.50 F1: 2 × 1.00 × 0.90 × 0.50 | G11: Color: gris | H11: MPERMEABILIZACIÓN LOCALES HÚMEDOS/HUECOS EXTERIORESImpermeabilización bajo revestimiento cerámico o pétreo, en paramentos verticales y horizontales de locales húmedos, con lámina impermeabilizante flexible de polietileno, con ambas caras revestidas de geotextil no tejido, kerdi o similar, de 0,5 mm de espesor y 285 g/m², fijada al soporte con adhesivo cementoso mejorado, C2 TE S1, según UNE-EN 12004, deformable, con deslizamiento reducido y tiempo abierto ampliado, color gris, a base de cemento, áridos de granulometría fina, resinas sintéticas y aditivos especiales. Incluso complementos de refuerzo en tratamiento de puntos singulares con banda de refuerzo de polietileno, con ambas caras revestidas de geotextil no tejido, de 120 mm de anchura y de 0,7 mm de espesor; y mortero cementoso impermeabilizante flexible bicomponente, de color gris. | I11: 24.94 | J11: =D11*I11 -> 9169.191 | K11: Se pide igual (fábrica u obra)
A12: D16ATA015 | B12: AISL FRENTES FORJAD PINTURA TERMOAISLANTE TECNOL TQ-I-TERMIC | C12: m² | D12: 696.4 | E12: =D12/16 -> 43.525 | F12: Tratamiento puente térmico de los forjados PRIMER FORJADO PAREADO TIPO: 7 × 53.25 × 0.80 AISLADA TIPO 1 (VIVIENDA 5): 1 × 37.30 × 0.80 AISLADA TIPO 2 (VIVIENDA 10): 1 × 36.80 × 0.80 SEGUNDO FORJADO PAREADO TIPO: 7 × 49.95 × 0.80 AISLADA TIPO 1 (VIVIENDA 5): 1 × 37.20 × 0.80 AISLADA TIPO 2 (VIVIENDA 10): 1 × 36.80 × 0.80 | H12: AISL FRENTES FORJAD PINTURA TERMOAISLANTE TECNOL TQ-I-TERMICImprimación de lámina acrílica impermeabilizante con propiedades termoacústicas para rotura de puentes térmicos en pilares integrados en fachada (aislados por su cara exterior), tipo I-Termic de Tecnol o similar con microburbujas de vidrio con una conductividad térmica de 0,17 W/m*K. Se aplicará con brocha y rodillo en varias capas según prestaciones deseadas, consumo aproximado de 200 a 250 gr por capa según absorción del soporte. Incluso p.p. de medios auxiliares y limpieza, totalmente terminado. Adecuado principalmente para colocar posteriormente aplacados que no necesiten estar pegados al aislamiento ( cerámica, ladrillos...). Cumpliendo CTE DB HE 1 y apartado 4.6 CEC puentes térmicos. | I12: 7.03 | J12: =D12*I12 -> 4895.692 | K12: Lo sustituye el módulo: no se pide así
A13: D16ATA025 | B13: AISL. PILARES AISLAMIENTO REFLEX. AIR BUR TERMIC S ADHESIVO | C13: m² | D13: 684 | E13: =D13/16 -> 42.75 | F13: Tratamiento puente termico en los pilares PAREADO TIPO PLANTA BAJA: 7 × 14.00 × 1.00 × 3.60 PLANTA SEGUNDA: 7 × 10.00 × 1.00 × 2.80 AISLADA TIPO 1 (VIVIENDA 5) PLANTA BAJA: 1 × 11.00 × 1.00 × 3.60 PLANTA SEGUNDA: 1 × 10.00 × 1.00 × 2.80 AISLADA TIPO 2 (VIVIENDA 10) PLANTA BAJA: 1 × 11.00 × 1.00 × 3.60 PLANTA SEGUNDA: 1 × 10.00 × 1.00 × 2.80 | H13: AISL. PILARES AISLAMIENTO REFLEX. AIR BUR TERMIC S ADHESIVOAislamiento térmico reflectivo para rotura de puente térmico de pilares integrados en fachada (aislamiento por su cara exterior), Air Bur Termic S o similar, formado por una lámina de aluminio puro, una burbuja de aire seco y film adhesivo para su instalación, con una resistencia térmica de 0,98 m²K/W y 4 mm de espesor y una clasificación ante el fuego NDP. Incluso p.p. de cortes, medios auxiliares y limpieza, sellado de juntas con cinta autoadhesiva de polietileno reticulado CintPex 50 o similar, totalmente terminado. Adecuado principalmente para colocar posteriormente aplacados que no necesiten estar pegados al aislamiento ( cerámica, ladrillos...), no recomendado para enfoscar encima. Cumpliendo CTE DB HE 1 y apartado 4.6 CEC puentes térmicos. | I13: 8.6 | J13: =D13*I13 -> 5882.4 | K13: Lo sustituye el módulo: no se pide así
A14: D16DD153 | B14: AISLAMIENTO ACÚSTICO PARA SUELO FLOTANTE PARQUET CHOVAIMPACT 3 S | C14: m² | D14: 1429.65 | E14: =D14/16 -> 89.353125 | F14: SUELO FLOTANTE PAREADO TIPO PLANTA BAJA Vestíbulo: 14 × 5.00 Dormitorio 1: 14 × 9.55 Salón-comedor: 14 × 29.15 PLANTA PRIMERA Distribuidor: 14 × 3.95 Dormitorio principal: 14 × 17.50 Dormitorio 2: 14 × 12.10 Dormitorio 3: 14 × 12.00 AISLADA TIPO 1 (VIVIENDA 5) PLANTA BAJA Vestíbulo: 1 × 5.00 Dormitorio 1: 1 × 9.55 Salón-comedor: 1 × 29.05 PLANTA PRIMERA Distribuidor: 1 × 3.95 Dormitorio principal: 1 × 17.50 Dormitorio 2: 1 × 12.45 Dormitorio 3: 1 × 12.15 AISLADA TIPO 2 (VIVIENDA 10) PLANTA BAJA Vestíbulo: 1 × 5.00 Dormitorio 1: 1 × 9.50 Salón-comedor: 1 × 30.30 PLANTA PRIMERA Distribuidor: 1 × 3.40 Dormitorio principal: 1 × 17.70 Dormitorio 2: 1 × 12.10 Dormitorio 3: 1 × 12.50 | G14: Marca/serie: CHOVA | H14: AISLAMIENTO ACÚSTICO PARA SUELO FLOTANTE PARQUET CHOVAIMPACT 3 SAislamiento acústico a ruido de impacto, colocado sobre capa de nivelación o pavimento existente, lámina ChovAIMPACT 3 "CHOVA" de 3 mm de espesor compuesta por polietileno de alta calidad revestida por una de sus caras con film de polietileno preparada para recibir directamente el suelo de madera o laminado. | I14: 3.09 | J14: =D14*I14 -> 4417.6185 | K14: Se pide igual (fábrica u obra)
A15: D17AA524 | B15: AISLAM. LAMINA ANTIRADON POLYDAN RADON 180-40P ELAST | C15: m² | D15: 1128.8 | E15: =D15/16 -> 70.55 | F15: PAREADO TIPO: 14 × 70.30 AISLADA TIPO 1 (VIVIENDA 5): 1 × 71.90 AISLADA TIPO 2 (VIVIENDA 10): 1 × 72.70 | G15: Marca/serie: Esterdan pendiente cero | H15: AISLAM. LAMINA ANTIRADON POLYDAN RADON 180-40P ELASTImpermeabilización monocapa en cubiertas con pendiente entre el 1% y el 15%, no transitables o transitables para uso peatonal, sistema no adherido, constituida por una lámina asfáltica de betún modificado con elastómeros SBS y peso medio de 4 kg/m² acabada con film de polietileno por ambas caras, ESTERDAN 40 P ELAST, con plegabilidad positiva a 15°C y armadura de fieltro de poliéster (Tipo LBM 40 FP), en posición flotante, adherida sólo en bordes y puntos singulares con soplete, previa imprimación de la base con 0,3 kg/m² de emulsión asfáltica CURIDAN, lista para proteger con protección pesada. Membrana PN 1, s/UNE 104 402/96. Según CTE/DB HS 1. Dispone de DIT. "Esterdan pendiente cero". Nº 550/10. | I15: 12.25 | J15: =D15*I15 -> 13827.8 | K15: Fuera de la vivienda (promotor o Knubo)
A16: NAD010 | B16: AISLAMIENTO LANA MINERAL 100 mm BAJO FORJADO | C16: m² | D16: 156 | E16: =D16/16 -> 9.75 | F16: FALSOS TECHOS EXTERIORES PAREADO TIPO: 14 × 9.80 AISLADA TIPO 1(VIVIENDA 5): 1 × 10.70 AISLADA TIPO 2(VIVIENDA 10): 1 × 8.10 | H16: AISLAMIENTO LANA MINERAL 100 mm BAJO FORJADOSuministro y colocación de aislamiento térmico bajo forjado formado por panel semirrígido de lana mineral, según UNE-EN 13162, no revestido, de 100 mm de espesor, resistencia térmica 2,25 m²K/W, conductividad térmica 0,035 W/(mK), fijado mecánicamente. Incluso p/p de cortes, fijaciones y limpieza. | I16: 12.22 | J16: =D16*I16 -> 1906.32 | K16: Lo sustituye el módulo: no se pide así
A17: 509b | B17: AISLAMIENTO XPS 80 mm SUELO | C17: m² | D17: 1128.8 | E17: =D17/16 -> 70.55 | F17: PAREADO TIPO: 14 × 70.30 AISLADA TIPO 1 (VIVIENDA 5): 1 × 71.90 AISLADA TIPO 2 (VIVIENDA 10): 1 × 72.70 | H17: AISLAMIENTO XPS 80 mm SUELOSuministro y colocación de aislamiento térmico por el interior sobre espacio habitable, formado por panel rígido de poliestireno extruido de superficie lisa y mecanizado lateral a media madera, de 80 mm de espesor, resistencia térmica 2,42 m²K/W, conductividad térmica 0,033 W/(mK), fijado con taco de expansión y clavo de polipropileno, con aro de estanqueidad. Incluso cortes y limpieza. | I17: 12.49 | J17: =D17*I17 -> 14098.712 | K17: Lo sustituye el módulo: no se pide así
A18: 510 | B18: AISLAMIENTO XPS 100 mm FACHADAS | C18: m² | D18: 2664.64 | E18: =D18/16 -> 166.54 | F18: PAREADO TIPO Planta baja: 14 × 27.50 × 3.25 Planta primera: 14 × 27.00 × 3.15 -A descontar > 4.00 m² PE2: -14 × 2.80 × 2.20 PE3: -14 × 1.90 × 2.20 PE4: -14 × 2.80 × 2.10 AISLADO TIPO 1 (VIVIENDA 5) Planta baja: 1 × 37.25 × 3.25 Planta primera: 1 × 38.05 × 3.15 -A descontar > 4.00 m² PE2: -1 × 2.80 × 2.20 PE3: -1 × 1.90 × 2.20 PE4: -1 × 2.80 × 2.10 AISLADO TIPO 2 (VIVIENDA 10) Planta baja: 1 × 37.75 × 3.25 Planta primera: 1 × 37.65 × 3.15 -A descontar > 4.00 m² PE2: -1 × 2.80 × 2.20 PE3: -1 × 1.90 × 2.20 PE4: -1 × 2.80 × 2.10 | H18: AISLAMIENTO XPS 100 mm FACHADASSuministro y colocación de aislamiento térmico por el interior en fachada de doble hoja de fábrica para revestir, formado por panel rígido de poliestireno extruido, de superficie lisa y mecanizado lateral a media madera, de 100 mm de espesor, resistencia térmica 2,75 m²K/W, conductividad térmica 0,029 W/(mK), fijado con taco de expansión y clavo de polipropileno, con aro de estanqueidad. Incluso cortes y limpieza. | I18: 14.8 | J18: =D18*I18 -> 39436.672 | K18: Lo sustituye el módulo: no se pide así
A19: 509 | B19: AISLAMIENTO XPS 100 mm CUBIERTA | C19: m² | D19: 1211.55 | E19: =D19/16 -> 75.721875 | F19: PAREADO TIPO Cubierta primera: 7 × 133.70 Cubierta baja: 14 × 9.00 AISLADA TIPO 1(VIVIENDA 5) Cubierta primera: 1 × 66.70 Cubierta baja: 1 × 9.00 AISLADA TIPO 2(VIVIENDA 10) Cubierta primera: 1 × 65.85 Cubierta baja: 1 × 8.10 | H19: AISLAMIENTO XPS 100 mm CUBIERTASSuministro y colocación de aislamiento térmico por el exterior de cubiertas inclinadas/planas sobre espacio habitable, formado por panel rígido de poliestireno extruido de superficie lisa y mecanizado lateral a media madera, de 100 mm de espesor, resistencia térmica 2,75 m²K/W, conductividad térmica 0,029 W/(mK), fijado con taco de expansión y clavo de polipropileno, con aro de estanqueidad. Incluso cortes y limpieza. | I19: 14.8 | J19: =D19*I19 -> 17930.94 | K19: Lo sustituye el módulo: no se pide así
B20: Total del capítulo (PEM del proyecto) | J20: =SUM(J5:J19) -> 128361.62

Sheet 08 Pladur trasdosados, tabiques
A1: Névola · Pladur: trasdosados, tabiques y techos · 16 viviendas
A2: Capítulo C.08 del proyecto de ejecución (BC3 de julio de 2026). Medición de toda la promoción y su desglose tal como viene en el proyecto. Precios del proyecto (CYPE, PEM, sin IVA), solo como referencia.
A4: Código | B4: Partida | C4: Ud | D4: Total 16 viv. | E4: Media por vivienda | F4: Desglose de la medición (proyecto) | G4: Datos clave (medidas, color, marca) | H4: Descripción completa del proyecto | I4: Precio proyecto | J4: Importe PEM | K4: Alcance en el sistema modular
A5: 507 | B5: TRASDOSADO AUTOPORT. KNAUF W625 (1x15,0+48) C/AISL | C5: m² | D5: 3106.87 | E5: =D5/16 -> 194.17937 | F5: PAREADO TIPO Planta baja: 14 × 36.10 × 2.95 Planta primera: 14 × 36.30 × 2.85 -A descontar > 4.00 m² PE2: -14 × 2.80 × 2.20 PE3: -14 × 1.90 × 2.20 PE4: -14 × 2.80 × 2.10 AISLADO TIPO 1 (VIVIENDA 5) Planta baja: 1 × 36.25 × 2.95 Planta primera: 1 × 37.25 × 2.85 -A descontar > 4.00 m² PE2: -1 × 2.80 × 2.20 PE3: -1 × 1.90 × 2.20 PE4: -1 × 2.80 × 2.10 AISLADO TIPO 2 (VIVIENDA 10) Planta baja: 1 × 36.95 × 2.95 Planta primera: 1 × 36.84 × 2.85 -A descontar > 4.00 m² PE2: -1 × 2.80 × 2.20 PE3: -1 × 1.90 × 2.20 PE4: -1 × 2.80 × 2.10 | H5: TRASDOSADO AUTOPORT. KNAUF W625 (1x15,0+48) C/AISLTrasdosado autoportante W625 formado por una placa Knauf Tipo A Standard o Tipo H1 Hidrófugas en locales húmedos de 15,0 mm de espesor, atornilladas a una estructura metálica de acero galvanizado de canales horizontales y montantes verticales de 48x30 y 0,6 mm de espesor, con una modulación de 400 mm e/e y fijadas al muro portante con anclajes directos cada 1,00 m, incluso aislamiento acústico mediante panel semirrígido de lana mineral, espesor 45 mm, en el alma, y p.p. de pasta y cinta para juntas, tornillos fijaciones, banda acústica bajo los perfiles perimetrales, totalmente terminado y listo para imprimar y decorar. | I5: 31.85 | J5: =D5*I5 -> 98953.81 | K5: Lo sustituye el módulo: no se pide así
A6: FBY015 | B6: TABIQUE MÚLTIPLE KNAUF W112 (2x12,5+48+2x12,5) C/AISL | C6: m² | D6: 2089.54 | E6: =D6/16 -> 130.59625 | F6: PAREADO TIPO Planta baja: 14 × 15.10 × 2.95 Planta primera: 14 × 30.20 × 2.85 AISLADO TIPO 1 (VIVIENDA 5) Planta baja: 1 × 15.10 × 2.95 Planta primera: 1 × 30.20 × 2.85 AISLADO TIPO 2 (VIVIENDA 10) Planta baja: 1 × 14.85 × 2.95 Planta primera: 1 × 30.35 × 2.85 | G6: Marca/serie: KNAUF | H6: TABIQUE MÚLTIPLE KNAUF W112 (2x12,5+48+2x12,5) C/AISLTabique múltiple sistema W112.es "KNAUF", de 98 mm de espesor total, con nivel de calidad del acabado Q2, sobre banda acústica de dilatación autoadhesiva "KNAUF", formado por una estructura simple de perfiles de chapa de acero galvanizado de 48 mm de anchura, a base de montantes (elementos verticales) separados 400 mm entre sí, con disposición normal "N" y canales (elementos horizontales), a la que se atornillan cuatro placas en total (Tipo A Standard o Tipo H1 Hidrófugas en locales húmedos en cada cara, de 12,5 mm de espesor cada placa); aislamiento acústico mediante panel semirrígido de lana mineral, espesor 45 mm, en el alma. Incluso banda acústica de dilatación autoadhesiva "KNAUF"; tornillería para la fijación de las placas y pasta y cinta para el tratamiento de juntas. | I6: 29.94 | J6: =D6*I6 -> 62560.828 | K6: Se pide igual (fábrica u obra)
A7: FBY015b | B7: TABIQUE MÚLTIPLE KNAUF W112 (2x12,5+70+2x12,5) C/AISL | C7: m² | D7: 359.2 | E7: =D7/16 -> 22.45 | F7: COLECTORES CLIMA/CUADRO ELÉCTRICO PAREADO TIPO Planta baja: 14 × 5.50 × 2.95 Planta primera: 14 × 1.65 × 2.85 Escalera (barandilla): 14 × 1.65 × 1.00 AISLADO TIPO 1 (VIVIENDA 5) Planta baja: 1 × 5.50 × 2.95 Planta primera: 1 × 1.65 × 2.85 Escalera (barandilla): 1 × 1.65 × 1.00 AISLADO TIPO 2 (VIVIENDA 10) Planta baja: 1 × 5.00 × 2.95 Planta primera: 1 × 1.45 × 2.85 Escalera (barandilla): 1 × 1.65 × 1.00 | G7: Marca/serie: KNAUF | H7: TABIQUE MÚLTIPLE KNAUF W112 (2x12,5+70+2x12,5) C/AISLTabique múltiple sistema W112.es "KNAUF", de 120 mm de espesor total, con nivel de calidad del acabado Q2, sobre banda acústica de dilatación autoadhesiva "KNAUF", formado por una estructura simple de perfiles de chapa de acero galvanizado de 70 mm de anchura, a base de montantes (elementos verticales) separados 400 mm entre sí, con disposición normal "N" y canales (elementos horizontales), a la que se atornillan cuatro placas en total (Tipo A Standard o Tipo H1 Hidrófugas en locales húmedos en cada cara, de 12,5 mm de espesor cada placa); aislamiento acústico mediante panel semirrígido de lana mineral, espesor 65 mm, en el alma. Incluso banda acústica de dilatación autoadhesiva "KNAUF"; tornillería para la fijación de las placas y pasta y cinta para el tratamiento de juntas. | I7: 31.34 | J7: =D7*I7 -> 11257.328 | K7: Se pide igual (fábrica u obra)
A8: D14DAC005-2 | B8: INCREMENTO PLACA ALTA RESISTENCIA MUEBLES DE COCINA/LAVABOS/ESCALERAS | C8: m² | D8: 202.55 | E8: =D8/16 -> 12.659375 | F8: COCINAS PAREADO TIPO: 14 × 3.00 × 1.50 AISLADO TIPO 1 (VIVIENDA 5): 1 × 3.00 × 1.50 AISLADO TIPO 2 (VIVIENDA 10): 1 × 3.10 × 1.50 ESCALERAS: 16 × 1.65 × 1.00 BAÑOS PAREADO TIPO: 14 × 3.25 × 2.00 AISLADO TIPO 1 (VIVIENDA 5): 1 × 3.25 × 2.00 AISLADA TIPO 2 (VIVIENDA 10): 1 × 3.25 × 2.00 | I8: 8.2 | J8: =D8*I8 -> 1660.91 | K8: Se pide igual (fábrica u obra)
A9: 511 | B9: FALSO TECHO CONTINUO CUARTOS SECOS | C9: m² | D9: 1504.05 | E9: =D9/16 -> 94.003125 | F9: PAREADO TIPO PLANTA BAJA Vestíbulo: 14 × 5.00 Dormitorio 1: 14 × 9.55 Salón-comedor: 14 × 29.15 PLANTA PRIMERA Escalera: 14 × 4.65 Distribuidor: 14 × 3.95 Dormitorio principal: 14 × 17.50 Dormitorio 2: 14 × 12.10 Dormitorio 3: 14 × 12.00 AISLADA TIPO 1 (VIVIENDA 5) PLANTA BAJA Vestíbulo: 1 × 5.00 Dormitorio 1: 1 × 9.55 Salón-comedor: 1 × 29.05 PLANTA PRIMERA Escalera: 1 × 4.65 Distribuidor: 1 × 3.95 Dormitorio principal: 1 × 17.50 Dormitorio 2: 1 × 12.45 Dormitorio 3: 1 × 12.15 AISLADA TIPO 2 (VIVIENDA 10) PLANTA BAJA Vestíbulo: 1 × 5.00 Dormitorio 1: 1 × 9.50 Salón-comedor: 1 × 30.30 PLANTA PRIMERA Escalera: 1 × 4.65 Distribuidor: 1 × 3.40 Dormitorio principal: 1 × 17.70 Dormitorio 2: 1 × 12.10 Dormitorio 3: 1 × 12.50 | G9: Marca/serie: KNAUF | H9: FALSO TECHO CONTINUO CUARTOS SECOSFalso techo continuo suspendido, situado a una altura menor de 4 m, con nivel de calidad del acabado Q2, liso, sistema D47.es "KNAUF" (12,5+17), formado por una placa de yeso laminado A/UNE-EN 520-1200/longitud/12,5/ con los bordes longitudinales afinados, Standard "KNAUF" atornillada a una estructura metálica de acero galvanizado de maestras primarias 47/17 mm separadas cada 500 mm entre ejes y suspendidas del forjado o elemento soporte mediante cuelgues Pivot F-47, para maestra 47/17, "KNAUF", y varillas cada 1200 mm, aislamiento acústico mediante panel semirrígido de lana mineral, espesor 45 mm. Incluso banda acústica, fijaciones para el anclaje de los perfiles, tornillería para la fijación de las placas, pasta y cinta para el tratamiento de juntas y accesorios de montaje. | I9: 27.74 | J9: =D9*I9 -> 41722.347 | K9: Se pide igual (fábrica u obra)
A10: 512 | B10: FALSO TECHO CONTINUO CUARTOS HÚMEDOS | C10: m² | D10: 432.7 | E10: =D10/16 -> 27.04375 | F10: PAREADO TIPO PLANTA BAJA Baño 1: 14 × 3.75 Lavadero: 14 × 4.00 Cocina: 14 × 8.45 PLANTA PRIMERA Baño Principal: 14 × 7.10 Baño 2: 14 × 3.85 AISLADA TIPO 1 (VIVIENDA 5) PLANTA BAJA Baño 1: 1 × 3.75 Lavadero: 1 × 4.00 Cocina: 1 × 8.45 PLANTA PRIMERA Baño Principal: 1 × 6.75 Baño 2: 1 × 3.75 AISLADA TIPO 2 (VIVIENDA 10) PLANTA BAJA Baño 1: 1 × 3.65 Lavadero: 1 × 4.30 Cocina: 1 × 7.85 PLANTA PRIMERA Baño Principal: 1 × 6.80 Baño 2: 1 × 3.30 | G10: Marca/serie: KNAUF | H10: FALSO TECHO CONTINUO CUARTOS HÚMEDOSFalso techo continuo suspendido, situado a una altura menor de 4 m, con nivel de calidad del acabado Q2, liso, sistema D47.es "KNAUF" (12,5+17), formado por una placa de yeso laminado A/UNE-EN 520-1200/longitud/12,5/ con los bordes longitudinales afinados, Tipo H1 Hidrófugas para locales húmedos "KNAUF" atornillada a una estructura metálica de acero galvanizado de maestras primarias 47/17 mm separadas cada 500 mm entre ejes y suspendidas del forjado o elemento soporte mediante cuelgues Pivot F-47, para maestra 47/17, "KNAUF", y varillas cada 1200 mm, aislamiento acústico mediante panel semirrígido de lana mineral, espesor 45 mm. Incluso banda acústica, fijaciones para el anclaje de los perfiles, tornillería para la fijación de las placas, pasta y cinta para el tratamiento de juntas y accesorios de montaje. | I10: 31.01 | J10: =D10*I10 -> 13418.027 | K10: Se pide igual (fábrica u obra)
A11: RTC020b | B11: TABICA VERTICAL FALSO TECHO CONTINUO | C11: m | D11: 116.5 | E11: =D11/16 -> 7.28125 | F11: PAREADO TIPO Planta baja: 14 × 6.25 Planta primera: 14 × 1.00 AISLADA TIPO 1 (VIVIENDA 5) Planta baja: 1 × 6.25 Planta primera: 1 × 1.00 AISLADA TIPO 2 (VIVIENDA 10) Planta baja: 1 × 6.50 Planta primera: 1 × 1.25 | G11: Marca/serie: KNAUF | H11: TABICA VERTICAL FALSO TECHO CONTINUO Formación de tabica vertical en cambio de nivel de falso techo continuo, formado por una placa de yeso laminado A/UNE-EN 520-1200/longitud/12,5/ con los bordes longitudinales afinados, Tipo A Standard o Tipo H1 Hidrófugas en locales húmedos "KNAUF", atornillada a una estructura metálica de acero galvanizadorecibidas con pasta de agarre, para cerrar un espacio de 30 cm de altura. Incluso corte, fijación con pasta de agarre, pasta de juntas y cinta de juntas.Incluye: Replanteo y trazado en los paramentos de la situación de la tabica. Presentación y corte de las piezas. Extendido de la pasta de agarre. Fijación de las placas. Tratamiento de juntas.Criterio de medición de proyecto: Longitud medida según documentación gráfica de Proyecto.Criterio de medición de obra: Se medirá la longitud realmente ejecutada según especificaciones de Proyecto.Criterio de valoración económica: El precio incluye la resolución de encuentros y puntos singulares. | I11: 20.41 | J11: =D11*I11 -> 2377.765 | K11: Se pide igual (fábrica u obra)
A12: 513 | B12: FALSO TECHO CONTINUO PLACAS DE CEMENTO | C12: m² | D12: 156 | E12: =D12/16 -> 9.75 | F12: VUELOS EXTERIORES PAREADO TIPO: 14 × 9.80 AISLADA TIPO 1(VIVIENDA 5): 1 × 10.70 AISLADA TIPO 2(VIVIENDA 10): 1 × 8.10 | G12: Marca/serie: KNAUF | H12: FALSO TECHO CONTINUO PLACAS DE CEMENTOSuministro y montaje de falso techo continuo, situado a una altura de hasta 4 m, liso D282a.es "KNAUF" o similar (12,5+27+27), formado por una placa de cemento Portland Aquapanel Outdoor "KNAUF" 12,5x1200x2400, revestida con una capa de fibra de vidrio embebida en ambas caras, atornillada a una estructura metálica de acero galvanizado de maestras primarias 60/27 mm separadas cada 50 mm entre ejes y suspendidas del forjado o elemento soporte mediante cuelgues Nonius cada 750 mm (incluidos en este precio), y maestras secundarias fijadas perpendicularmente a las primarias mediante caballetes y colocadas con una modulación máxima de 400 mm entre ejes, incluso p/p de fijaciones, tornillería, resolución del perímetro y puntos singulares, mortero de juntas, cinta de juntas y accesorios de montaje. Totalmente terminado con pasta Aquapanel Q4 Finish. | I12: 101.73 | J12: =D12*I12 -> 15869.88 | K12: Se pide igual (fábrica u obra)
A13: FUF010 | B13: MAMPARA DUCHA | C13: m² | D13: 34.56 | E13: =D13/16 -> 2.16 | F13: MAMPARAS BAÑO PRINCIPAL TODA LA OBRA: 16 × 0.60 × 2.40 16 × 0.60 × 1.20 | G13: Color: plata | H13: MAMPARA DUCHAPared fija de vidrio, formada por: perfiles de aluminio anodizado color plata mate y vidrio laminar de seguridad, 6+6 mm, incoloro, clasificación de prestaciones 2B2, según UNE-EN 12600. | I13: 77.61 | J13: =D13*I13 -> 2682.2016 | K13: Se pide igual (fábrica u obra)
B14: Total del capítulo (PEM del proyecto) | J14: =SUM(J5:J13) -> 250503.1

Sheet 09 Alicatados y solados
A1: Névola · Alicatados y solados · 16 viviendas
A2: Capítulo C.09 del proyecto de ejecución (BC3 de julio de 2026). Medición de toda la promoción y su desglose tal como viene en el proyecto. Precios del proyecto (CYPE, PEM, sin IVA), solo como referencia.
A4: Código | B4: Partida | C4: Ud | D4: Total 16 viv. | E4: Media por vivienda | F4: Desglose de la medición (proyecto) | G4: Datos clave (medidas, color, marca) | H4: Descripción completa del proyecto | I4: Precio proyecto | J4: Importe PEM | K4: Alcance en el sistema modular
A5: RAG012 | B5: ALICATADO GRES PORCELÁNICO (20 /m²) | C5: m² | D5: 1416.19 | E5: =D5/16 -> 88.511875 | F5: PAREADO TIPO Cocina: 14 × 3.00 × 2.40 Lavadero: 14 × 10.45 × 2.10 Baño 1: 14 × 8.00 × 2.40 Baño 2: 14 × 8.25 × 2.40 Baño principal: 14 × 8.65 × 2.40 AISLADA TIPO 1 (VIVIENDA 5) Cocina: 1 × 3.00 × 2.40 Lavadero: 1 × 10.45 × 2.10 Baño 1: 1 × 8.00 × 2.40 Baño 2: 1 × 8.25 × 2.40 Baño principal: 1 × 8.35 × 2.40 AISLADA TIPO 2 (VIVIENDA 10) Cocina: 1 × 3.10 × 2.40 Lavadero: 1 × 8.65 × 2.10 Baño 1: 1 × 8.00 × 2.40 Baño 2: 1 × 7.55 × 2.40 Baño principal: 1 × 8.50 × 2.40 | G5: Color: gris | H5: ALICATADO GRES PORCELÁNICO (20 /m²)Suministro y colocación de alicatado con gres porcelánico acabado mate o natural, en formato comercial,(precio del material 20 euros/m²), capacidad de absorción de agua E<0,5%, grupo BIa, según UNE-EN 14411, con resistencia al deslizamiento Rd<=15 según UNE-ENV 12633 y resbaladicidad clase 0 según CTE, recibido con adhesivo cementoso de fraguado normal, C1 sin ninguna característica adicional, color gris. Incluso p/p de preparación de la superficie soporte de placas de yeso laminado; replanteo, cortes, cantoneras de PVC, y juntas; rejuntado con lechada de cemento blanco, L, BL-V 22,5, para junta mínima (entre 1,5 y 3 mm), coloreada con la misma tonalidad de las piezas; acabado y limpieza final. | I5: 26.61 | J5: =D5*I5 -> 37684.816 | K5: Se pide igual (fábrica u obra)
A6: D19RA002 | B6: PAVIMENTO LAMINADO TERHÜRNE 8,5 mm | C6: m² | D6: 1429.65 | E6: =D6/16 -> 89.353125 | F6: PAREADO TIPO PLANTA BAJA Vestíbulo: 14 × 5.00 Dormitorio 1: 14 × 9.55 Salón-comedor: 14 × 29.15 PLANTA PRIMERA Distribuidor: 14 × 3.95 Dormitorio principal: 14 × 17.50 Dormitorio 2: 14 × 12.10 Dormitorio 3: 14 × 12.00 AISLADA TIPO 1 (VIVIENDA 5) PLANTA BAJA Vestíbulo: 1 × 5.00 Dormitorio 1: 1 × 9.55 Salón-comedor: 1 × 29.05 PLANTA PRIMERA Distribuidor: 1 × 3.95 Dormitorio principal: 1 × 17.50 Dormitorio 2: 1 × 12.45 Dormitorio 3: 1 × 12.15 AISLADA TIPO 2 (VIVIENDA 10) PLANTA BAJA Vestíbulo: 1 × 5.00 Dormitorio 1: 1 × 9.50 Salón-comedor: 1 × 30.30 PLANTA PRIMERA Distribuidor: 1 × 3.40 Dormitorio principal: 1 × 17.70 Dormitorio 2: 1 × 12.10 Dormitorio 3: 1 × 12.50 | G6: Medidas: 1285x191x8,5mm | H6: PAVIMENTO LAMINADO TERHÜRNE 8,5 mmPavimento laminado Comfloor ( AC5/32 ) Akustec de Terhürne o similar, con tablero base DPL de alta densidad de medidas 1285x191x8,5 mm dotado de junta de cierre ClikTec en los cuatro cantos de la tabla. Compuesto por tres elementos: A, capa de desgaste compuesta de una capa protectora fábricada a partir de resinas melamínicas y papel decorado con acabado de superficie similar a la madera (arce natural, haya, roble...). B, tablero base HDF dotado de sistema anti humedad WaterproTec y unión ClickTec. C, contracapa de papel Krahf para mayor estabilidad del conjunto y sistema de reducción del sonido de la pisada AkusTec.(INCLUYE PLASTON) | I6: 36.32 | J6: =D6*I6 -> 51924.888 | K6: Se pide igual (fábrica u obra)
A7: FDD150 | B7: TAPETA MADERA EN ESCALERA | C7: m | D7: 26.4 | E7: =D7/16 -> 1.65 | F7: Escaleras: 16 × 1.65 | H7: TAPETA MADERA EN ESCALERATapeta recta de madera de roble, de 100 mm de ancho máximo, barnizado en taller con barniz sintético con acabado satinado, con soportes metálicos fijados al paramento mediante anclaje mecánico con tacos de nylon y tornillos de acero. Incluso p/p de replanteo de los soportes, fijación de los soportes al paramento y fijación del pasamanos a los soportes. Elaborado en taller y montado en obra. | I7: 47.92 | J7: =D7*I7 -> 1265.088 | K7: Se pide igual (fábrica u obra)
A8: FDD140 | B8: PASAMANOS ALUMINIO | C8: m | D8: 60.8 | E8: =D8/16 -> 3.8 | F8: Escaleras: 16 × 3.80 | G8: Medidas: 60x40mm · Color: natural | H8: PASAMANOS ALUMINIOPasamanos curvo de aluminio anodizado color natural, de 60x40 mm de sección, con soportes de aluminio fijados al paramento mediante anclaje mecánico con tacos de nylon y tornillos de acero. Incluso p/p de replanteo de los soportes, fijación de los soportes al paramento, fijación del pasamanos a los soportes y colocación de tapas de remate. Elaborado en taller y montado en obra. | I8: 31.88 | J8: =D8*I8 -> 1938.304 | K8: Se pide igual (fábrica u obra)
A9: D19DD003D | B9: SOLADO DE GRES PORCELÁNICO (20 /m²) INTERIOR C2 | C9: m² | D9: 432.7 | E9: =D9/16 -> 27.04375 | F9: PAREADO TIPO PLANTA BAJA Baño 1: 14 × 3.75 Lavadero: 14 × 4.00 Cocina: 14 × 8.45 PLANTA PRIMERA Baño Principal: 14 × 7.10 Baño 2: 14 × 3.85 AISLADA TIPO 1 (VIVIENDA 5) PLANTA BAJA Baño 1: 1 × 3.75 Lavadero: 1 × 4.00 Cocina: 1 × 8.45 PLANTA PRIMERA Baño Principal: 1 × 6.75 Baño 2: 1 × 3.75 AISLADA TIPO 2 (VIVIENDA 10) PLANTA BAJA Baño 1: 1 × 3.65 Lavadero: 1 × 4.30 Cocina: 1 × 7.85 PLANTA PRIMERA Baño Principal: 1 × 6.80 Baño 2: 1 × 3.30 | H9: SOLADO DE GRES PORCELÁNICO (20 /m²) INTERIOR C2Solado con baldosas de gres porcelánico acabado mate o natural, en formato comercial,(precio del material 20 euros/m²) para interiores (resistencia al deslizamiento Rd s/ UNE-ENV 12633 para: a) zonas secas, CLASE 1 para pendientes menores al 6% y CLASE 2 para pendientes superiores al 6% y escaleras, b) zonas húmedas, CLASE 2 para pendientes menores al 6% y CLASE 3 para pendientes superiores al 6% y escaleras y piscinas), recibido con cemento cola Weber.col classic blanco, sobre base de mortero de cemento y arena de río 1/6 (incluido), i/piezas especiales, ejecución de cortes, rejuntado con mortero decorativo Weber col junta fina (< 3mm) y limpieza, s/ CTE BD SU y NTE-RSB-7. | I9: 35.97 | J9: =D9*I9 -> 15564.219 | K9: Se pide igual (fábrica u obra)
A10: D19DD004 | B10: SOLADO DE GRES PORCELÁNICO (20 /m²) EXTERIOR C3 | C10: m² | D10: 749.65 | E10: =D10/16 -> 46.853125 | F10: ZAGUÁN ACCESO: 16 × 1.50 PÉRGOLA-TERRAZA PAREADO TIPO: 14 × 23.55 AISLADA TIPO 1 (VIVIENDA 5): 1 × 24.10 AISLADA TIPO 2 (VIVIENDA 10): 1 × 22.55 TERRAZA PLANTA PRIMERA PAREADO TIPO: 14 × 9.00 AISLADA TIPO 1 (VIVIENDA 5): 1 × 9.00 AISLADA TIPO 2 (VIVIENDA 10): 1 × 8.10 ZONA COMÚN PISCINA ADULTOS: 1 × 131.75 CUARTO TÉCNICO PISCINAS: 1 × 20.75 CASETA APEROS: 1 × 13.45 PISCINA CHAPOTEO: 1 × 40.25 | H10: SOLADO DE GRES PORCELÁNICO (20 /m²) EXTERIOR C3Solado con baldosas de gres porcelánico acabado mate o natural, en formato comercial,(precio del material 20 euros/m²), para exteriores y piscinas (resistencia al deslizamiento Rd>45 s/ UNE-ENV 12633 CLASE 3), recibido con mortero de cemento y arena de río M5 según UNE-EN 998-2, i/cama de 2 cm de arena de río, p.p. de rodapié del mismo material de 7 cm, rejuntado y limpieza, s/ CTE BD SU y NTE-RSB-7. | I10: 42.95 | J10: =D10*I10 -> 32197.467 | K10: Fuera de la vivienda (promotor o Knubo)
A11: UXC020 | B11: HORMIGÓN PULIDO | C11: m² | D11: 16 | E11: =D11/16 -> 1 | F11: Cuarto técnico piscinas: 1 × 16.00 | H11: HORMIGÓN PULIDOPavimento continuo exterior de hormigón en masa, con juntas, de 10 cm de espesor medio, realizado con hormigón HM-15/B/20/I fabricado en central y vertido desde camión; con lámina de polietileno como capa separadora bajo el pavimento; tratado superficialmente con capa de rodadura de con un rendimiento aproximado de 3 kg/m², espolvoreado manualmente sobre el hormigón aún fresco y posterior fratasado mecánico de toda la superficie hasta conseguir que el mortero quede totalmente integrado en el hormigón. Incluso p/p de colocación y retirada de encofrados, ejecución de juntas de construcción; emboquillado o conexión de los elementos exteriores (cercos de arquetas, sumideros, botes sifónicos, etc.) de las redes de instalaciones ejecutadas bajo el pavimento; extendido, regleado y aplicación de aditivos. Sin incluir la ejecución de la base de apoyo ni la de las juntas de dilatación y de retracción. | I11: 19.4 | J11: =D11*I11 -> 310.4 | K11: Fuera de la vivienda (promotor o Knubo)
A12: 0604 | B12: HORMIGÓN IMPRESO-SOLERA HA-25 #150x150x5 15 cm+ENCACHADO+PVC | C12: m² | D12: 1777.6 | E12: =D12/16 -> 111.1 | F12: VIVIENDAS (ACERADO) VIVIENDA 1: 1 × 69.20 VIVIENDA 2: 1 × 68.65 VIVIENDA 3: 1 × 67.90 VIVIENDA 4: 1 × 71.65 VIVIENDA 5: 1 × 67.20 VIVIENDA 6: 1 × 74.65 VIVIENDA 7: 1 × 86.65 VIVIENDA 8: 1 × 64.50 VIVIENDA 9: 1 × 67.10 VIVIENDA 10: 1 × 69.95 VIVIENDA 11: 1 × 69.20 VIVIENDA 12: 1 × 61.40 VIVIENDA 13: 1 × 71.00 VIVIENDA 14: 1 × 69.15 VIVIENDA 15: 1 × 69.15 VIVIENDA 16: 1 × 74.00 ZONA COMÚN: 1 × 656.25 | G12: Medidas: 150x150x5mm | H12: HORMIGÓN IMPRESO-SOLERA HA-25 #150x150x5 15 cm+ENCACHADO+PVCSolera de 15 cm de espesor, realizada con hormigón HA-25/B/20/IIa N/mm², tamaño máximo del árido 20 mm elaborado en central, i/vertido, colocación y armado con mallazo electrosoldado #150x150x5 mm, incluso p.p. de juntas, aserrado de las mismas, fratasado y encachado de piedra caliza 40/80 de 15 cm de espesor, extendido y compactado con pisón, con lámina intermedia de PVC Danopol HS de 1,5 mm, junta de perímetro mediante EPS de 1 cm de espesor y sellado de juntas con masilla de poliuretano de elasticidad permanente. Según EHE-08. Acabado impreso en relieve y tratado superficialmente con mortero decorativo de rodadura para pavimento de hormigón; desmoldeante en polvo y capa de sellado final con resina impermeabilizante. Incluso colocación y retirada de encofrados, ejecución de juntas de construcción; emboquillado o conexión de los elementos exteriores (cercos de arquetas, sumideros, botes sifónicos, etc.) de las redes de instalaciones ejecutadas bajo el pavimento; extendido, regleado y aplicación de aditivos. | I12: 34.5 | J12: =D12*I12 -> 61327.2 | K12: Fuera de la vivienda (promotor o Knubo)
A13: D19DD505 | B13: PELDAÑO DE GRES PORCELÁNICO (20 /m²) ESCALERA INTERIOR C2 | C13: m | D13: 336 | E13: =D13/16 -> 21 | F13: ESCALERAS INTERIORES TODA LA OBRA: 16 × 21.00 × 1.00 | G13: Color: blanco | H13: PELDAÑO DE GRES PORCELÁNICO (20 /m²) ESCALERA INTERIOR C2Revestimiento de peldaño de escalera interior de anchura 1,00 m máximo, con baldosas de gres porcelánico acabado mate o natural, en formato comercial,(precio del material 20 euros/m²)formado por huella con canto redondeado,tabica y rodapié, gama media, capacidad de absorción de agua E<3%, grupo BIb, según UNE-EN 14411, con resistencia al deslizamiento 35<Rd<=45 según UNE-EN 16165 y resbaladicidad clase 2 según CTE. COLOCACIÓN: en capa fina y mediante encolado simple con adhesivo cementoso mejorado, C2 TE, según UNE-EN 12004, con deslizamiento reducido y tiempo abierto ampliado. REJUNTADO: con mortero de juntas cementoso mejorado, con absorción de agua reducida y resistencia elevada a la abrasión tipo CG 2 W A, color blanco, en juntas de 2 mm de espesor. | I13: 28.08 | J13: =D13*I13 -> 9434.88 | K13: Se pide igual (fábrica u obra)
A14: HRC030 | B14: VIERTEAGUAS GRES PORCELÁNICO | C14: m | D14: 120 | E14: =D14/16 -> 7.5 | F14: TODA LA OBRA PE2: 16 × 2.80 PE3: 16 × 1.90 PE4: 16 × 2.80 | H14: VIERTEAGUAS GRES PORCELÁNICOFormación de vierteaguas con piezas de gres porcelánico, en formato comercial,con goterón y empotrado en las jambas, cubriendo los alféizares, los salientes de los paramentos, las cornisas de fachada, etc., recibido con mortero de cemento, industrial, con aditivo hidrófugo, M-10, creando una pendiente suficiente para evacuar el agua y rejuntado entre piezas y de las uniones con los muros con mortero de juntas cementoso con absorción de agua reducida, CG2, para juntas entre 3 y 15 mm. Incluso p/p de replanteo, cortes y limpieza final.Incluye: Replanteo de las piezas en el hueco o remate. Preparación y regularización del soporte. Colocación con mortero de las piezas. Relleno de juntas y limpieza del vierteaguas.Criterio de medición de proyecto: Longitud del ancho del hueco, medida según documentación gráfica de Proyecto, incrementada en 5 cm a cada lado.Criterio de medición de obra: Se medirá la longitud realmente ejecutada según especificaciones de Proyecto, incluyendo los empotramientos en las jambas. | I14: 31.86 | J14: =D14*I14 -> 3823.2 | K14: Se pide igual (fábrica u obra)
A15: HRL010 | B15: ALBARDILLA ALUMINIO | C15: m | D15: 467.15 | E15: =D15/16 -> 29.196875 | F15: PETOS CUBIERTA PAREADO TIPO: 7 × 54.00 AISLADA TIPO 1 (VIVIENDA 5): 1 × 38.05 AISLADA TIPO 2 (VIVIENDA 10): 1 × 37.65 CASETA APEROS: 1 × 13.45 | H15: ALBARDILLA ALUMINIOAlbardilla metálica, de chapa plegada de aluminio lacado en color, con un ángulo de inclinación de 10°, con 60 micras de espesor mínimo de película seca, espesor 1,5 mm, desarrollo 300 mm y 5 pliegues, con goterón, para cubrición de muros; colocación con adhesivo bituminoso de aplicación en frío, sobre tablero estructural contrachapado atornillado a rastreles de madera; y sellado de las juntas entre piezas y, en su caso, de las uniones con los muros con sellador adhesivo monocomponente.Incluye: Preparación de la superficie de apoyo. Preparación de la base y de los medios de fijación. Replanteo de las piezas. Corte de las piezas. Colocación y fijación de las piezas metálicas niveladas y aplomadas. Sellado de juntas y limpieza.Criterio de medición de proyecto: Longitud medida a ejes, según documentación gráfica de Proyecto.Criterio de medición de obra: Se medirá, a ejes, la longitud realmente ejecutada según especificaciones de Proyecto.Incluye: Preparación de la superficie de apoyo. Preparación de la base y de los medios de fijación. Replanteo de las piezas. Corte de las piezas. Colocación y fijación de las piezas metálicas niveladas y aplomadas. Sellado de juntas y limpieza.Criterio de medición de proyecto: Longitud medida a ejes, según documentación gráfica de Proyecto.Criterio de medición de obra: Se medirá, a ejes, la longitud realmente ejecutada según especificaciones de Proyecto. | I15: 22.99 | J15: =D15*I15 -> 10739.779 | K15: Se pide igual (fábrica u obra)
A16: RCG010 | B16: APLACADO GRES EXTERIOR EN FACHADA | C16: m² | D16: 497.68 | E16: =D16/16 -> 31.105 | F16: PAREADO TIPO Fachada principal: 14 × 17.50 Fachada posterior: 14 × 3.80 Fachada lateral: 14 × 2.25 Rodapié fachada p baja: 14 × 28.10 × 0.20 Rodapié fachada terraza p primera: 14 × 7.15 × 0.20 AISLADA TIPO 1 (VIVIENDA 5) Fachada principal: 1 × 16.40 Fachada posterior: 1 × 3.80 Fachada lateral derecha: 1 × 2.25 Fachada lateral izquierda: 1 × 2.25 Rodapié fachada p baja: 1 × 41.10 × 0.20 Rodapié fachada terraza p primera: 1 × 7.15 × 0.20 AISLADA TIPO 2 (VIVIENDA 10) Fachada principal: 1 × 16.40 Fachada posterior: 1 × 4.40 Fachada lateral derecha: 1 × 2.25 Fachada lateral izquierda: 1 × 2.25 Rodapié fachada p baja: 1 × 41.55 × 0.20 Rodapié fachada terraza p primera: 1 × 6.60 × 0.20 | H16: APLACADO GRES EXTERIOR EN FACHADAAplacado mixto, con baldosa de gres porcelánico, en formato comercial, con un coeficiente de absorción de agua del 0,4% y un PEI IV, colocadas en capa fina, aplicando adhesivo cementoso mejorado, C2 TE, con deslizamiento reducido y tiempo abierto ampliado, blanco, utilizando la técnica de doble encolado, sobre una capa previa de mortero de regularización debidamente maestreada, (no incluida en este precio), utilizando además elementos mecánicos de refuerzo, enclavados en las juntas de separación entre baldosas y fijados mecánicamente al paramento. Rejuntado con mortero de juntas cementoso con resistencia elevada a la abrasión y absorción de agua reducida, CG2, para junta abierta (entre 3 y 15 mm), con la misma tonalidad de las piezas. Incluso p/p de preparación de la superficie soporte, replanteo, apertura de cajas en muros, cortes, piezas especiales, formación y sellado de juntas de movimiento, resolución de puntos singulares y encuentros con huecos de carpintería, elementos de fijación mecánica, acabado y limpieza final.Incluye: Replanteo de niveles y disposición de baldosas. Replanteo de taladros. Realización de taladros. Colocación de tacos. Atornillado de los elementos metálicos. Colocación de las piezas, extendiendo el material adhesivo de agarre. Formación de juntas de movimiento. Resolución de puntos singulares. Rejuntado de baldosas. Acabado y limpieza final.Criterio de medición de proyecto: Superficie medida según documentación gráfica de Proyecto, deduciendo los huecos de superficie mayor de 1 m², añadiendo a cambio la superficie de la parte interior del hueco, correspondiente al desarrollo de jambas y dinteles. No se ha incrementado la medición por roturas y recortes, ya que en la descomposición se ha considerado un 5% más de piezas.Criterio de medición de obra: Se medirá la superficie realmente ejecutada según especificaciones de Proyecto, deduciendo los huecos de superficie mayor de 1 m², añadiendo a cambio la superficie de la parte interior del hueco, correspondiente al desarrollo de jambas y dinteles. | I16: 48.34 | J16: =D16*I16 -> 24057.851 | K16: Se pide igual (fábrica u obra)
B17: Total del capítulo (PEM del proyecto) | J17: =SUM(J5:J16) -> 250268.09

Sheet 10 Carpintería interior
A1: Névola · Carpintería interior · 16 viviendas
A2: Capítulo C.10 del proyecto de ejecución (BC3 de julio de 2026). Medición de toda la promoción y su desglose tal como viene en el proyecto. Precios del proyecto (CYPE, PEM, sin IVA), solo como referencia.
A4: Código | B4: Partida | C4: Ud | D4: Total 16 viv. | E4: Media por vivienda | F4: Desglose de la medición (proyecto) | G4: Datos clave (medidas, color, marca) | H4: Descripción completa del proyecto | I4: Precio proyecto | J4: Importe PEM | K4: Alcance en el sistema modular
A5: LPM010 | B5: PUERTA INTERIOR ABATIBLE MDF | C5: Ud | D5: 112 | E5: =D5/16 -> 7 | F5: 16 × 7.00 | G5: Medidas: 725x2100x35mm, 70x35mm, 70x30mm, 70x12mm | H5: PUERTA INTERIOR ABATIBLE MDFPuerta de paso interior abatible ciega en Block con hoja lisa sin molduras y acanaladuras en forma de pico de pájaro, lacada en blanco de medidas de hoja 725x2100x35 mm, de tablero de MDF. Precerco en madera de pino de 70x35 mm, cerco visto de 70x30 mm, tapajuntas de 70x12 mm. Con 4 pernios de latón con remate, picaporte 6137/BC/50/HL y manivela con placa. Totalmente montada, mecanizada y lacada, incluso en p.p. de medios auxiliares. | I5: 221.56 | J5: =D5*I5 -> 24814.72 | K5: Se pide igual (fábrica u obra)
A6: LAF010 | B6: ARMARIO MODULAR PUERTAS ABATIBLES | C6: m² | D6: 47.4 | E6: =D6/16 -> 2.9625 | F6: AE1: 15 × 1.25 × 2.40 (Vivienda 10): 1 × 1.00 × 2.40 | G6: Color: cromado | H6: ARMARIO MODULAR PUERTAS ABATIBLESBlock de armario para empotrar de dos hojas abatibles, de tablero aglomerado melamínico, de 16 mm de espesor, en costados, techo, suelo y división de maletero, y de 10 mm de espesor en el fondo; hoja de 19 mm de espesor y canto de 1,4 mm en PVC; barras de colgar en aluminio dorado, estriado y antidoblante, con soportes laterales de igual color; bisagras rectas de color cromado (4 unidades por puerta) y tiradores de color cromado para puertas abatibles. Incluso precerco, módulos columna y baldas de división en maletero, molduras en MDF plastificadas, tapajuntas, zócalo y demás herrajes. Elaborado en taller, con ajuste y fijación en obra. Totalmente montado. | I6: 143.1 | J6: =D6*I6 -> 6782.94 | K6: Se pide igual (fábrica u obra)
A7: LAF010b | B7: ARMARIO MODULAR/SIN PUERTAS | C7: m² | D7: 188.28 | E7: =D7/16 -> 11.7675 | F7: AE2: 15 × 3.30 × 2.40 (Vivienda 5): 1 × 3.35 × 2.40 AE3: 16 × 1.60 × 2.40 | H7: ARMARIO MODULAR/SIN PUERTASBlock de armario para empotrar, de tablero aglomerado melamínico, de 16 mm de espesor, en costados, techo, suelo y división de maletero, y de 10 mm de espesor en el fondo; hoja de 19 mm de espesor y canto de 1,4 mm en PVC; barras de colgar en aluminio dorado, estriado y antidoblante, con soportes laterales de igual color. Incluso módulos columna y baldas de división en maletero, molduras en MDF plastificadas, tapajuntas, zócalo y demás herrajes. Elaborado en taller, con ajuste y fijación en obra. Totalmente montado. | I7: 105.8 | J7: =D7*I7 -> 19920.024 | K7: Se pide igual (fábrica u obra)
A8: RSL020b | B8: RODAPIÉ MDF | C8: m | D8: 1621.25 | E8: =D8/16 -> 101.32812 | F8: PAREADO TIPO PLANTA BAJA Vestíbulo: 14 × 7.00 Dormitorio 1: 14 × 12.55 Salón-comedor-cocina: 14 × 18.20 PLANTA PRIMERA Distribuidor: 14 × 9.00 Dormitorio principal: 14 × 21.70 Baño Principal: 14 × 2.95 Dormitorio 2: 14 × 14.30 Dormitorio 3: 14 × 15.60 AISLADA TIPO 1 (VIVIENDA 5) PLANTA BAJA Vestíbulo: 1 × 7.00 Dormitorio 1: 1 × 12.55 Salón-comedor-cocina: 1 × 18.20 PLANTA PRIMERA Distribuidor: 1 × 9.00 Dormitorio principal: 1 × 21.70 Baño Principal: 1 × 2.95 Dormitorio 2: 1 × 14.55 Dormitorio 3: 1 × 16.15 AISLADA TIPO 2 (VIVIENDA 10) PLANTA BAJA Vestíbulo: 1 × 7.20 Dormitorio 1: 1 × 12.50 Salón-comedor-cocina: 1 × 18.80 PLANTA PRIMERA Distribuidor: 1 × 7.90 Dormitorio principal: 1 × 21.20 Baño Principal: 1 × 2.85 Dormitorio 2: 1 × 14.30 Dormitorio 3: 1 × 16.20 | G8: Medidas: 90x18mm · Color: blanco | H8: RODAPIÉ MDFRodapié de MDF, de 90x18 mm, recubierto con una lámina plástica color blanco, fijado al paramento mediante adhesivo de montaje. Incluso replanteo, cortes, resolución de esquinas, uniones y encuentros, pequeño material auxiliar y limpieza final. | I8: 6.95 | J8: =D8*I8 -> 11267.688 | K8: Se pide igual (fábrica u obra)
B9: Total del capítulo (PEM del proyecto) | J9: =SUM(J5:J8) -> 62785.372

Sheet 11 Carpintería exterior y cerra
A1: Névola · Carpintería exterior y cerrajería · 16 viviendas
A2: Capítulo C.11 del proyecto de ejecución (BC3 de julio de 2026). Medición de toda la promoción y su desglose tal como viene en el proyecto. Precios del proyecto (CYPE, PEM, sin IVA), solo como referencia.
A4: Código | B4: Partida | C4: Ud | D4: Total 16 viv. | E4: Media por vivienda | F4: Desglose de la medición (proyecto) | G4: Datos clave (medidas, color, marca) | H4: Descripción completa del proyecto | I4: Precio proyecto | J4: Importe PEM | K4: Alcance en el sistema modular
A5: 0804 | B5: PUERTA ENTRADA ALUMINIO/BLOCK DE SEGURIDAD | C5: Ud | D5: 16 | E5: =D5/16 -> 1 | F5: PE1: 16 × 1.00 | G5: Medidas: 82,5x210cm · Color: RAL 7016 | H5: PUERTA ENTRADA ALUMINIO/BLOCK DE SEGURIDADSuministro y montaje de puerta de entrada de aluminio termolacado en polvo a 210°C, block de seguridad, de 82,5x210 cm. Compuesta de: hoja de 50 mm de espesor total, construida con dos chapas de aluminio de 1,2 mm de espesor, con alma de madera blindada con chapa de hierro acerado de 1 mm y macizo especial en todo el perímetro de la hoja y herraje, estampación con embutición profunda en doble relieve a dos caras, acabado en color RAL 7016; marcos especiales de extrusión de aluminio reforzado de 1,6 mm de espesor, de igual terminación que las hojas, con burlete perimétrico. Incluso premarco de acero galvanizado con garras de anclaje a obra, cerradura especial con tres puntos de cierre con bombín de seguridad, tres bisagras de seguridad antipalanca, burlete cortavientos, mirilla gran angular, manivela interior, pomo, tirador y aldaba exteriores, espuma de poliuretano para relleno de la holgura entre marco y muro, sellado perimetral de juntas por medio de un cordón de silicona neutra y ajuste final en obra. Elaborada en taller, con clasificación a la permeabilidad al aire según UNE-EN 12207, a la estanqueidad al agua según UNE-EN 12208 y a la resistencia a la carga del viento según UNE-EN 12210. Totalmente montada y probada. | I5: 1140.81 | J5: =D5*I5 -> 18252.96 | K5: Se pide igual (fábrica u obra)
A6: LCV015 | B6: PE1/FIJO (sin persiana) | C6: Ud | D6: 16 | E6: =D6/16 -> 1 | F6: PE1: 16 × 1.00 | G6: Medidas: 500x2200mm · Color: RAL 7016; WSWS Blanco · Marca/serie: KÖMMERLING, SAINT GOBAIN, SIKA | H6: PE1/FIJO (sin persiana)Ventanal fijo de PVC, serie Eurofutur 70 "KÖMMERLING", dimensiones 500x2200 mm, acabado estándar en la cara interior en color WSWS Blanco y acabado foliado en la cara exterior, color RAL 7016, perfiles de 70 mm de anchura, fabricados bajo formulación Greenline®, sin plomo ni estabilizantes pesados, soldados a inglete, que incorporan cinco cámaras interiores, tanto en la sección de la hoja como en la del marco, para mejora del aislamiento térmico; galce con pendiente del 5% para facilitar el desagüe; con refuerzos interiores, según UNE-EN 14351-1; transmitancia térmica del marco: Uh,m = desde 1,3 W/(m²K); espesor máximo del acristalamiento: 40 mm; compuesta por marco, hojas, herrajes de colgar y apertura, elementos de estanqueidad y accesorios homologados, con clasificación a la permeabilidad al aire clase 4, según UNE-EN 12207, clasificación a la estanqueidad al agua clase E1650, según UNE-EN 12208, y clasificación a la resistencia a la carga del viento clase C5, según UNE-EN 12210, con premarco y sin persiana. Incluso limpieza del premarco ya instalado, alojamiento y calzado del marco en el premarco, fijación del marco al premarco con tornillos de acero galvanizado.Incluido doble acristalamiento SGG CLIMALIT PLUS PLANITHERM XN F2 4/12 argón 90%/55.2 "SAINT GOBAIN", conjunto formado por vidrio exterior PLANITHERM XN de 4 mm, con capa de baja emisividad térmica incorporada en la cara interior, cámara de gas deshidratada con perfil separador de aluminio y doble sellado perimetral, de 12 mm, rellena de gas argón y vidrio interior STADIP PROTECT de 5+5 mm, compuesto por dos lunas de vidrio laminar de 5 mm unidas mediante dos láminas incoloras de butiral de polivinilo, para hojas de vidrio de superficie entre 3 y 4 m²; 26 mm de espesor total, fijado sobre carpintería con acuñado mediante calzos de apoyo perimetrales y laterales, sellado en frío con silicona Sikasil WS-305-N "SIKA", compatible con el material soporte, para hojas de vidrio de superficie entre 3 y 4 m².Incluye: Colocación, calzado, montaje y ajuste en la carpintería. Sellado final de estanqueidad. Señalización de las hojas.Criterio de medición de proyecto: Superficie de carpintería a acristalar, según documentación gráfica de Proyecto, incluyendo en cada hoja vidriera las dimensiones del bastidor.Criterio de medición de obra: Se medirá la superficie realmente ejecutada según especificaciones de Proyecto, sumando, para cada una de las piezas, la superficie resultante de redondear por exceso cada una de sus aristas a múltiplos de 30 mm.Criterio de valoración económica: El precio incluye el sistema de triple barrera.Incluye: Colocación del premarco. Colocación de la carpintería sobre el premarco. Ajuste final de la hoja.Criterio de medición de proyecto: Número de unidades previstas, según documentación gráfica de Proyecto.Criterio de medición de obra: Se medirá el número de unidades realmente ejecutadas según especificaciones de Proyecto. | I6: 240.87 | J6: =D6*I6 -> 3853.92 | K6: Se pide igual (fábrica u obra)
A7: LCV015j | B7: PE2/PUERTA 1 HOJA + FIJO LATERAL (con persiana) | C7: Ud | D7: 16 | E7: =D7/16 -> 1 | F7: PE2: 16 × 1.00 | G7: Medidas: 2800x2200mm · Color: RAL 7016; WSWS Blanco; a · Marca/serie: KÖMMERLING, SAINT GOBAIN, SIKA | H7: PE2/PUERTA 1 HOJA + FIJO LATERAL (con persiana)Puerta de PVC, serie Eurofutur 70 "KÖMMERLING", una hoja practicable con apertura hacia el interior y fijo lateral, dimensiones 2800x2200 mm, anchura del fijo 1800 mm, compuesta de marco, hoja y junquillos, acabado estándar en la cara interior en color WSWS Blanco y acabado foliado en la cara exterior, color RAL 7016, perfiles de 70 mm de anchura, fabricados bajo formulación Greenline®, sin plomo ni estabilizantes pesados, soldados a inglete, que incorporan cinco cámaras interiores, tanto en la sección de la hoja como en la del marco, para mejora del aislamiento térmico; galce con pendiente del 5% para facilitar el desagüe; con refuerzos interiores, juntas de estanqueidad de EPDM manilla y herrajes, según UNE-EN 14351-1; transmitancia térmica del marco: Uh,m = desde 1,3 W/(m²K); espesor máximo del acristalamiento: 40 mm; compuesta por marco, hojas, herrajes de colgar y apertura, elementos de estanqueidad y accesorios homologados, con clasificación a la permeabilidad al aire clase 4, según UNE-EN 12207, clasificación a la estanqueidad al agua clase E1650, según UNE-EN 12208, y clasificación a la resistencia a la carga del viento clase C2, según UNE-EN 12210, con premarco y cajón de persiana Rolaplus incorporado, acabado foliado en la cara exterior, color a elegir, persiana enrollable de lamas de aluminio inyectado, con aislamiento térmico, con accionamiento manual con cinta y recogedor. Incluso limpieza del premarco ya instalado, alojamiento y calzado del marco en el premarco, fijación del marco al premarco con tornillos de acero galvanizado.Incluido doble acristalamiento SGG CLIMALIT PLUS PLANITHERM XN F2 4/12 argón 90%/55.2 "SAINT GOBAIN", conjunto formado por vidrio exterior PLANITHERM XN de 4 mm, con capa de baja emisividad térmica incorporada en la cara interior, cámara de gas deshidratada con perfil separador de aluminio y doble sellado perimetral, de 12 mm, rellena de gas argón y vidrio interior STADIP PROTECT de 5+5 mm, compuesto por dos lunas de vidrio laminar de 5 mm unidas mediante dos láminas incoloras de butiral de polivinilo, para hojas de vidrio de superficie entre 3 y 4 m²; 26 mm de espesor total, fijado sobre carpintería con acuñado mediante calzos de apoyo perimetrales y laterales, sellado en frío con silicona Sikasil WS-305-N "SIKA", compatible con el material soporte, para hojas de vidrio de superficie entre 3 y 4 m².Incluye: Colocación, calzado, montaje y ajuste en la carpintería. Sellado final de estanqueidad. Señalización de las hojas.Criterio de medición de proyecto: Superficie de carpintería a acristalar, según documentación gráfica de Proyecto, incluyendo en cada hoja vidriera las dimensiones del bastidor.Criterio de medición de obra: Se medirá la superficie realmente ejecutada según especificaciones de Proyecto, sumando, para cada una de las piezas, la superficie resultante de redondear por exceso cada una de sus aristas a múltiplos de 30 mm.Criterio de valoración económica: El precio incluye el sistema de triple barrera.Incluye: Colocación del premarco. Colocación de la carpintería sobre el premarco. Ajuste final de la hoja. Realización de pruebas de servicio.Criterio de medición de proyecto: Número de unidades previstas, según documentación gráfica de Proyecto.Criterio de medición de obra: Se medirá el número de unidades realmente ejecutadas según especificaciones de Proyecto. | I7: 1335.55 | J7: =D7*I7 -> 21368.8 | K7: Se pide igual (fábrica u obra)
A8: LCV015i | B8: PE3/PUERTA 1 HOJA + FIJO LATERAL (con persiana) | C8: Ud | D8: 16 | E8: =D8/16 -> 1 | F8: PE3: 16 × 1.00 | G8: Medidas: 1900x2200mm · Color: RAL 7016; WSWS Blanco; a · Marca/serie: KÖMMERLING, SAINT GOBAIN, SIKA | H8: PE3/PUERTA 1 HOJA + FIJO LATERAL (con persiana)Puerta de PVC, serie Eurofutur 70 "KÖMMERLING", una hoja practicable con apertura hacia el interior y fijo lateral, dimensiones 1900x2200 mm, anchura del fijo 900 mm, compuesta de marco, hoja y junquillos, acabado estándar en la cara interior en color WSWS Blanco y acabado foliado en la cara exterior, color RAL 7016, perfiles de 70 mm de anchura, fabricados bajo formulación Greenline®, sin plomo ni estabilizantes pesados, soldados a inglete, que incorporan cinco cámaras interiores, tanto en la sección de la hoja como en la del marco, para mejora del aislamiento térmico; galce con pendiente del 5% para facilitar el desagüe; con refuerzos interiores, juntas de estanqueidad de EPDM manilla y herrajes, según UNE-EN 14351-1; transmitancia térmica del marco: Uh,m = desde 1,3 W/(m²K); espesor máximo del acristalamiento: 40 mm; compuesta por marco, hojas, herrajes de colgar y apertura, elementos de estanqueidad y accesorios homologados, con clasificación a la permeabilidad al aire clase 4, según UNE-EN 12207, clasificación a la estanqueidad al agua clase E1650, según UNE-EN 12208, y clasificación a la resistencia a la carga del viento clase C2, según UNE-EN 12210, con premarco y cajón de persiana Rolaplus incorporado, acabado foliado en la cara exterior, color a elegir, persiana enrollable de lamas de aluminio inyectado, con aislamiento térmico, con accionamiento manual con cinta y recogedor. Incluso limpieza del premarco ya instalado, alojamiento y calzado del marco en el premarco, fijación del marco al premarco con tornillos de acero galvanizado.Incluido doble acristalamiento SGG CLIMALIT PLUS PLANITHERM XN F2 4/12 argón 90%/55.2 "SAINT GOBAIN", conjunto formado por vidrio exterior PLANITHERM XN de 4 mm, con capa de baja emisividad térmica incorporada en la cara interior, cámara de gas deshidratada con perfil separador de aluminio y doble sellado perimetral, de 12 mm, rellena de gas argón y vidrio interior STADIP PROTECT de 5+5 mm, compuesto por dos lunas de vidrio laminar de 5 mm unidas mediante dos láminas incoloras de butiral de polivinilo, para hojas de vidrio de superficie entre 3 y 4 m²; 26 mm de espesor total, fijado sobre carpintería con acuñado mediante calzos de apoyo perimetrales y laterales, sellado en frío con silicona Sikasil WS-305-N "SIKA", compatible con el material soporte, para hojas de vidrio de superficie entre 3 y 4 m².Incluye: Colocación, calzado, montaje y ajuste en la carpintería. Sellado final de estanqueidad. Señalización de las hojas.Criterio de medición de proyecto: Superficie de carpintería a acristalar, según documentación gráfica de Proyecto, incluyendo en cada hoja vidriera las dimensiones del bastidor.Criterio de medición de obra: Se medirá la superficie realmente ejecutada según especificaciones de Proyecto, sumando, para cada una de las piezas, la superficie resultante de redondear por exceso cada una de sus aristas a múltiplos de 30 mm.Criterio de valoración económica: El precio incluye el sistema de triple barrera.Incluye: Colocación del premarco. Colocación de la carpintería sobre el premarco. Ajuste final de la hoja. Realización de pruebas de servicio.Criterio de medición de proyecto: Número de unidades previstas, según documentación gráfica de Proyecto.Criterio de medición de obra: Se medirá el número de unidades realmente ejecutadas según especificaciones de Proyecto. | I8: 1266.9 | J8: =D8*I8 -> 20270.4 | K8: Se pide igual (fábrica u obra)
A9: LCV015h | B9: PE4/PUERTA 1 HOJA + FIJO LATERAL (con persiana) | C9: Ud | D9: 16 | E9: =D9/16 -> 1 | F9: PE4: 16 × 1.00 | G9: Medidas: 2800x2100mm · Color: RAL 7016; WSWS Blanco; a · Marca/serie: KÖMMERLING, SAINT GOBAIN, SIKA | H9: PE4/PUERTA 1 HOJA + FIJO LATERAL (con persiana)Puerta de PVC, serie Eurofutur 70 "KÖMMERLING", una hoja practicable con apertura hacia el interior y fijo lateral, dimensiones 2800x2100 mm, anchura del fijo 1800 mm, compuesta de marco, hoja y junquillos, acabado estándar en la cara interior en color WSWS Blanco y acabado foliado en la cara exterior, color RAL 7016, perfiles de 70 mm de anchura, fabricados bajo formulación Greenline®, sin plomo ni estabilizantes pesados, soldados a inglete, que incorporan cinco cámaras interiores, tanto en la sección de la hoja como en la del marco, para mejora del aislamiento térmico; galce con pendiente del 5% para facilitar el desagüe; con refuerzos interiores, juntas de estanqueidad de EPDM manilla y herrajes, según UNE-EN 14351-1; transmitancia térmica del marco: Uh,m = desde 1,3 W/(m²K); espesor máximo del acristalamiento: 40 mm; compuesta por marco, hojas, herrajes de colgar y apertura, elementos de estanqueidad y accesorios homologados, con clasificación a la permeabilidad al aire clase 4, según UNE-EN 12207, clasificación a la estanqueidad al agua clase E1650, según UNE-EN 12208, y clasificación a la resistencia a la carga del viento clase C2, según UNE-EN 12210, con premarco y cajón de persiana Rolaplus incorporado, acabado foliado en la cara exterior, color a elegir, persiana enrollable de lamas de aluminio inyectado, con aislamiento térmico, con accionamiento manual con cinta y recogedor. Incluso limpieza del premarco ya instalado, alojamiento y calzado del marco en el premarco, fijación del marco al premarco con tornillos de acero galvanizado.Incluido doble acristalamiento SGG CLIMALIT PLUS PLANITHERM XN F2 4/12 argón 90%/55.2 "SAINT GOBAIN", conjunto formado por vidrio exterior PLANITHERM XN de 4 mm, con capa de baja emisividad térmica incorporada en la cara interior, cámara de gas deshidratada con perfil separador de aluminio y doble sellado perimetral, de 12 mm, rellena de gas argón y vidrio interior STADIP PROTECT de 5+5 mm, compuesto por dos lunas de vidrio laminar de 5 mm unidas mediante dos láminas incoloras de butiral de polivinilo, para hojas de vidrio de superficie entre 3 y 4 m²; 26 mm de espesor total, fijado sobre carpintería con acuñado mediante calzos de apoyo perimetrales y laterales, sellado en frío con silicona Sikasil WS-305-N "SIKA", compatible con el material soporte, para hojas de vidrio de superficie entre 3 y 4 m².Incluye: Colocación, calzado, montaje y ajuste en la carpintería. Sellado final de estanqueidad. Señalización de las hojas.Criterio de medición de proyecto: Superficie de carpintería a acristalar, según documentación gráfica de Proyecto, incluyendo en cada hoja vidriera las dimensiones del bastidor.Criterio de medición de obra: Se medirá la superficie realmente ejecutada según especificaciones de Proyecto, sumando, para cada una de las piezas, la superficie resultante de redondear por exceso cada una de sus aristas a múltiplos de 30 mm.Criterio de valoración económica: El precio incluye el sistema de triple barrera.Incluye: Colocación del premarco. Colocación de la carpintería sobre el premarco. Ajuste final de la hoja. Realización de pruebas de servicio.Criterio de medición de proyecto: Número de unidades previstas, según documentación gráfica de Proyecto.Criterio de medición de obra: Se medirá el número de unidades realmente ejecutadas según especificaciones de Proyecto. | I9: 1300.09 | J9: =D9*I9 -> 20801.44 | K9: Se pide igual (fábrica u obra)
A10: LCV015b | B10: V1/VENTANA 1 HOJA (sin persiana) | C10: Ud | D10: 16 | E10: =D10/16 -> 1 | F10: V1: 16 | G10: Medidas: 700x1200mm · Color: RAL 7016; WSWS Blanco · Marca/serie: KÖMMERLING, SAINT GOBAIN, SIKA | H10: V1/VENTANA 1 HOJA (sin persiana)Ventana de PVC, serie Eurofutur 70 "KÖMMERLING", una hoja oscilobatiente con apertura hacia el interior, dimensiones 700x1200 mm, compuesta de marco, hoja y junquillos, acabado estándar en la cara interior en color WSWS Blanco y acabado foliado en la cara exterior, color RAL 7016, perfiles de 70 mm de anchura, fabricados bajo formulación Greenline®, sin plomo ni estabilizantes pesados, soldados a inglete, que incorporan cinco cámaras interiores, tanto en la sección de la hoja como en la del marco, para mejora del aislamiento térmico; galce con pendiente del 5% para facilitar el desagüe; con refuerzos interiores, juntas de estanqueidad de EPDM, manilla y herrajes, según UNE-EN 14351-1; transmitancia térmica del marco: Uh,m = desde 1,3 W/(m²K); espesor máximo del acristalamiento: 40 mm; compuesta por marco, hojas, herrajes de colgar y apertura, elementos de estanqueidad y accesorios homologados, con clasificación a la permeabilidad al aire clase 4, según UNE-EN 12207, clasificación a la estanqueidad al agua clase E1650, según UNE-EN 12208, y clasificación a la resistencia a la carga del viento clase C5, según UNE-EN 12210, con premarco y sin persiana. Incluso limpieza del premarco ya instalado, alojamiento y calzado del marco en el premarco, fijación del marco al premarco con tornillos de acero galvanizado.Incluido doble acristalamiento SGG CLIMALIT PLUS PLANITHERM XN F2 4/12 argón 90%/55.2 "SAINT GOBAIN", conjunto formado por vidrio exterior PLANITHERM XN de 4 mm, con capa de baja emisividad térmica incorporada en la cara interior, cámara de gas deshidratada con perfil separador de aluminio y doble sellado perimetral, de 12 mm, rellena de gas argón y vidrio interior STADIP PROTECT de 5+5 mm, compuesto por dos lunas de vidrio laminar de 5 mm unidas mediante dos láminas incoloras de butiral de polivinilo, para hojas de vidrio de superficie entre 3 y 4 m²; 26 mm de espesor total, fijado sobre carpintería con acuñado mediante calzos de apoyo perimetrales y laterales, sellado en frío con silicona Sikasil WS-305-N "SIKA", compatible con el material soporte, para hojas de vidrio de superficie entre 3 y 4 m².Incluye: Colocación, calzado, montaje y ajuste en la carpintería. Sellado final de estanqueidad. Señalización de las hojas.Criterio de medición de proyecto: Superficie de carpintería a acristalar, según documentación gráfica de Proyecto, incluyendo en cada hoja vidriera las dimensiones del bastidor.Criterio de medición de obra: Se medirá la superficie realmente ejecutada según especificaciones de Proyecto, sumando, para cada una de las piezas, la superficie resultante de redondear por exceso cada una de sus aristas a múltiplos de 30 mm.Criterio de valoración económica: El precio incluye el sistema de triple barrera.Incluye: Colocación del premarco. Colocación de la carpintería sobre el premarco. Ajuste final de la hoja. Realización de pruebas de servicio.Criterio de medición de proyecto: Número de unidades previstas, según documentación gráfica de Proyecto.Criterio de medición de obra: Se medirá el número de unidades realmente ejecutadas según especificaciones de Proyecto. | I10: 315.83 | J10: =D10*I10 -> 5053.28 | K10: Se pide igual (fábrica u obra)
A11: LCV015f | B11: V2/VENTANA 1 HOJA + FIJO INFERIOR (con persiana) | C11: Ud | D11: 16 | E11: =D11/16 -> 1 | F11: V2: 16 | G11: Medidas: 850x2000mm · Color: RAL 7016; WSWS Blanco; a · Marca/serie: KÖMMERLING, SAINT GOBAIN, SIKA | H11: V2/VENTANA 1 HOJA + FIJO INFERIOR (con persiana)Ventana de PVC, serie Eurofutur 70 "KÖMMERLING", una hoja oscilobatiente con apertura hacia el interior y fijo inferior, dimensiones 850x2000 mm, altura del fijo 800 mm, compuesta de marco, hoja y junquillos, acabado estándar en la cara interior en color WSWS Blanco y acabado foliado en la cara exterior, color RAL 7016, perfiles de 70 mm de anchura, fabricados bajo formulación Greenline®, sin plomo ni estabilizantes pesados, soldados a inglete, que incorporan cinco cámaras interiores, tanto en la sección de la hoja como en la del marco, para mejora del aislamiento térmico; galce con pendiente del 5% para facilitar el desagüe; con refuerzos interiores, juntas de estanqueidad de EPDM manilla y herrajes, según UNE-EN 14351-1; transmitancia térmica del marco: Uh,m = desde 1,3 W/(m²K); espesor máximo del acristalamiento: 40 mm; compuesta por marco, hojas, herrajes de colgar y apertura, elementos de estanqueidad y accesorios homologados, con clasificación a la permeabilidad al aire clase 4, según UNE-EN 12207, clasificación a la estanqueidad al agua clase E1650, según UNE-EN 12208, y clasificación a la resistencia a la carga del viento clase C5, según UNE-EN 12210, con premarco y cajón de persiana Rolaplus incorporado, acabado foliado en la cara exterior, color a elegir, persiana enrollable de lamas de aluminio inyectado, con aislamiento térmico, con accionamiento manual con cinta y recogedor. Incluso limpieza del premarco ya instalado, alojamiento y calzado del marco en el premarco, fijación del marco al premarco con tornillos de acero galvanizado.Incluido doble acristalamiento SGG CLIMALIT PLUS PLANITHERM XN F2 4/12 argón 90%/55.2 "SAINT GOBAIN", conjunto formado por vidrio exterior PLANITHERM XN de 4 mm, con capa de baja emisividad térmica incorporada en la cara interior, cámara de gas deshidratada con perfil separador de aluminio y doble sellado perimetral, de 12 mm, rellena de gas argón y vidrio interior STADIP PROTECT de 5+5 mm, compuesto por dos lunas de vidrio laminar de 5 mm unidas mediante dos láminas incoloras de butiral de polivinilo, para hojas de vidrio de superficie entre 3 y 4 m²; 26 mm de espesor total, fijado sobre carpintería con acuñado mediante calzos de apoyo perimetrales y laterales, sellado en frío con silicona Sikasil WS-305-N "SIKA", compatible con el material soporte, para hojas de vidrio de superficie entre 3 y 4 m².Incluye: Colocación, calzado, montaje y ajuste en la carpintería. Sellado final de estanqueidad. Señalización de las hojas.Criterio de medición de proyecto: Superficie de carpintería a acristalar, según documentación gráfica de Proyecto, incluyendo en cada hoja vidriera las dimensiones del bastidor.Criterio de medición de obra: Se medirá la superficie realmente ejecutada según especificaciones de Proyecto, sumando, para cada una de las piezas, la superficie resultante de redondear por exceso cada una de sus aristas a múltiplos de 30 mm.Criterio de valoración económica: El precio incluye el sistema de triple barrera.Incluye: Colocación del premarco. Colocación de la carpintería sobre el premarco. Ajuste final de la hoja. Realización de pruebas de servicio.Criterio de medición de proyecto: Número de unidades previstas, según documentación gráfica de Proyecto.Criterio de medición de obra: Se medirá el número de unidades realmente ejecutadas según especificaciones de Proyecto. | I11: 597.76 | J11: =D11*I11 -> 9564.16 | K11: Se pide igual (fábrica u obra)
A12: LCV015g | B12: V3-V4/VENTANA 2 HOJAS + FIJO INFERIOR (con persiana) | C12: Ud | D12: 48 | E12: =D12/16 -> 3 | F12: V3: 16 × 2.00 V4: 16 × 1.00 | G12: Medidas: 1500x1500mm · Color: RAL 7016; WSWS Blanco; a · Marca/serie: KÖMMERLING, SAINT GOBAIN, SIKA | H12: V3-V4/VENTANA 2 HOJAS + FIJO INFERIOR (con persiana)Ventana de PVC, serie Eurofutur 70 "KÖMMERLING", una hoja oscilobatiente y otra hoja practicable con apertura hacia el interior y fijo inferior, dimensiones 1500x1500 mm, altura del fijo 300 mm, compuesta de marco, hoja y junquillos, acabado estándar en la cara interior en color WSWS Blanco y acabado foliado en la cara exterior, color RAL 7016, perfiles de 70 mm de anchura, fabricados bajo formulación Greenline®, sin plomo ni estabilizantes pesados, soldados a inglete, que incorporan cinco cámaras interiores, tanto en la sección de la hoja como en la del marco, para mejora del aislamiento térmico; galce con pendiente del 5% para facilitar el desagüe; con refuerzos interiores, juntas de estanqueidad de EPDM, manilla y herrajes, según UNE-EN 14351-1; transmitancia térmica del marco: Uh,m = desde 1,3 W/(m²K); espesor máximo del acristalamiento: 40 mm; compuesta por marco, hojas, herrajes de colgar y apertura, elementos de estanqueidad y accesorios homologados, con clasificación a la permeabilidad al aire clase 4, según UNE-EN 12207, clasificación a la estanqueidad al agua clase E1650, según UNE-EN 12208, y clasificación a la resistencia a la carga del viento clase C5, según UNE-EN 12210, con premarco y cajón de persiana Rolaplus incorporado, acabado foliado en la cara exterior, color a elegir, persiana enrollable de lamas de aluminio inyectado, con aislamiento térmico, con accionamiento manual con cinta y recogedor. Incluso limpieza del premarco ya instalado, alojamiento y calzado del marco en el premarco, fijación del marco al premarco con tornillos de acero galvanizado.Incluido doble acristalamiento SGG CLIMALIT PLUS PLANITHERM XN F2 4/12 argón 90%/55.2 "SAINT GOBAIN", conjunto formado por vidrio exterior PLANITHERM XN de 4 mm, con capa de baja emisividad térmica incorporada en la cara interior, cámara de gas deshidratada con perfil separador de aluminio y doble sellado perimetral, de 12 mm, rellena de gas argón y vidrio interior STADIP PROTECT de 5+5 mm, compuesto por dos lunas de vidrio laminar de 5 mm unidas mediante dos láminas incoloras de butiral de polivinilo, para hojas de vidrio de superficie entre 3 y 4 m²; 26 mm de espesor total, fijado sobre carpintería con acuñado mediante calzos de apoyo perimetrales y laterales, sellado en frío con silicona Sikasil WS-305-N "SIKA", compatible con el material soporte, para hojas de vidrio de superficie entre 3 y 4 m².Incluye: Colocación, calzado, montaje y ajuste en la carpintería. Sellado final de estanqueidad. Señalización de las hojas.Criterio de medición de proyecto: Superficie de carpintería a acristalar, según documentación gráfica de Proyecto, incluyendo en cada hoja vidriera las dimensiones del bastidor.Criterio de medición de obra: Se medirá la superficie realmente ejecutada según especificaciones de Proyecto, sumando, para cada una de las piezas, la superficie resultante de redondear por exceso cada una de sus aristas a múltiplos de 30 mm.Criterio de valoración económica: El precio incluye el sistema de triple barrera.Incluye: Colocación del premarco. Colocación de la carpintería sobre el premarco. Ajuste final de las hojas. Realización de pruebas de servicio.Criterio de medición de proyecto: Número de unidades previstas, según documentación gráfica de Proyecto.Criterio de medición de obra: Se medirá el número de unidades realmente ejecutadas según especificaciones de Proyecto. | I12: 737.34 | J12: =D12*I12 -> 35392.32 | K12: Se pide igual (fábrica u obra)
A13: LCV015c | B13: V5-V6 VENTANA 1 HOJA + FIJO INFERIOR (sin persiana) | C13: Ud | D13: 32 | E13: =D13/16 -> 2 | F13: V5: 16 × 1.00 V6: 16 × 1.00 | G13: Medidas: 700x1500mm · Color: RAL 7016; WSWS Blanco · Marca/serie: KÖMMERLING, SAINT GOBAIN, SIKA | H13: V5-V6 VENTANA 1 HOJA + FIJO INFERIOR (sin persiana)Ventana de PVC, serie Eurofutur 70 "KÖMMERLING", una hoja oscilobatiente con apertura hacia el interior y fijo inferior, dimensiones 700x1500 mm, altura del fijo 300 mm, compuesta de marco, hoja y junquillos, acabado estándar en la cara interior en color WSWS Blanco y acabado foliado en la cara exterior, color RAL 7016, perfiles de 70 mm de anchura, fabricados bajo formulación Greenline®, sin plomo ni estabilizantes pesados, soldados a inglete, que incorporan cinco cámaras interiores, tanto en la sección de la hoja como en la del marco, para mejora del aislamiento térmico; galce con pendiente del 5% para facilitar el desagüe; con refuerzos interiores, juntas de estanqueidad de EPDM manilla y herrajes, según UNE-EN 14351-1; transmitancia térmica del marco: Uh,m = desde 1,3 W/(m²K); espesor máximo del acristalamiento: 40 mm; compuesta por marco, hojas, herrajes de colgar y apertura, elementos de estanqueidad y accesorios homologados, con clasificación a la permeabilidad al aire clase 4, según UNE-EN 12207, clasificación a la estanqueidad al agua clase E1650, según UNE-EN 12208, y clasificación a la resistencia a la carga del viento clase C5, según UNE-EN 12210, con premarco y sin persiana. Incluso limpieza del premarco ya instalado, alojamiento y calzado del marco en el premarco, fijación del marco al premarco con tornillos de acero galvanizado.Incluido doble acristalamiento SGG CLIMALIT PLUS PLANITHERM XN F2 4/12 argón 90%/55.2 "SAINT GOBAIN", conjunto formado por vidrio exterior PLANITHERM XN de 4 mm, con capa de baja emisividad térmica incorporada en la cara interior, cámara de gas deshidratada con perfil separador de aluminio y doble sellado perimetral, de 12 mm, rellena de gas argón y vidrio interior STADIP PROTECT de 5+5 mm, compuesto por dos lunas de vidrio laminar de 5 mm unidas mediante dos láminas incoloras de butiral de polivinilo, para hojas de vidrio de superficie entre 3 y 4 m²; 26 mm de espesor total, fijado sobre carpintería con acuñado mediante calzos de apoyo perimetrales y laterales, sellado en frío con silicona Sikasil WS-305-N "SIKA", compatible con el material soporte, para hojas de vidrio de superficie entre 3 y 4 m².Incluye: Colocación, calzado, montaje y ajuste en la carpintería. Sellado final de estanqueidad. Señalización de las hojas.Criterio de medición de proyecto: Superficie de carpintería a acristalar, según documentación gráfica de Proyecto, incluyendo en cada hoja vidriera las dimensiones del bastidor.Criterio de medición de obra: Se medirá la superficie realmente ejecutada según especificaciones de Proyecto, sumando, para cada una de las piezas, la superficie resultante de redondear por exceso cada una de sus aristas a múltiplos de 30 mm.Criterio de valoración económica: El precio incluye el sistema de triple barrera.Incluye: Colocación del premarco. Colocación de la carpintería sobre el premarco. Ajuste final de la hoja. Realización de pruebas de servicio.Criterio de medición de proyecto: Número de unidades previstas, según documentación gráfica de Proyecto.Criterio de medición de obra: Se medirá el número de unidades realmente ejecutadas según especificaciones de Proyecto. | I13: 323.91 | J13: =D13*I13 -> 10365.12 | K13: Se pide igual (fábrica u obra)
A14: LCV015e | B14: V7/VENTANA 1 HOJA (con persiana) | C14: Ud | D14: 2 | E14: =D14/16 -> 0.125 | F14: AISLADA TIPO 1 (VIVIENDA 5): 1 AISLADA TIPO 1 (VIVIENDA 5): 1 | G14: Medidas: 750x750mm · Color: RAL 7016; WSWS Blanco; a · Marca/serie: KÖMMERLING, SAINT GOBAIN, SIKA | H14: V7/VENTANA 1 HOJA (con persiana)Ventana de PVC, serie Eurofutur 70 "KÖMMERLING", una hoja practicable con apertura hacia el interior, dimensiones 750x750 mm, compuesta de marco, hoja y junquillos, acabado estándar en la cara interior en color WSWS Blanco y acabado foliado en la cara exterior, color RAL 7016, perfiles de 70 mm de anchura, fabricados bajo formulación Greenline®, sin plomo ni estabilizantes pesados, soldados a inglete, que incorporan cinco cámaras interiores, tanto en la sección de la hoja como en la del marco, para mejora del aislamiento térmico; galce con pendiente del 5% para facilitar el desagüe; con refuerzos interiores, juntas de estanqueidad de EPDM, manilla y herrajes, según UNE-EN 14351-1; transmitancia térmica del marco: Uh,m = desde 1,3 W/(m²K); espesor máximo del acristalamiento: 40 mm; compuesta por marco, hojas, herrajes de colgar y apertura, elementos de estanqueidad y accesorios homologados, con clasificación a la permeabilidad al aire clase 4, según UNE-EN 12207, clasificación a la estanqueidad al agua clase E1650, según UNE-EN 12208, y clasificación a la resistencia a la carga del viento clase C5, según UNE-EN 12210, con premarco y cajón de persiana Rolaplus incorporado, acabado foliado en la cara exterior, color a elegir, persiana enrollable de lamas de aluminio inyectado, con aislamiento térmico, con accionamiento manual con cinta y recogedor. Incluso limpieza del premarco ya instalado, alojamiento y calzado del marco en el premarco, fijación del marco al premarco con tornillos de acero galvanizado.Incluido doble acristalamiento SGG CLIMALIT PLUS PLANITHERM XN F2 4/12 argón 90%/55.2 "SAINT GOBAIN", conjunto formado por vidrio exterior PLANITHERM XN de 4 mm, con capa de baja emisividad térmica incorporada en la cara interior, cámara de gas deshidratada con perfil separador de aluminio y doble sellado perimetral, de 12 mm, rellena de gas argón y vidrio interior STADIP PROTECT de 5+5 mm, compuesto por dos lunas de vidrio laminar de 5 mm unidas mediante dos láminas incoloras de butiral de polivinilo, para hojas de vidrio de superficie entre 3 y 4 m²; 26 mm de espesor total, fijado sobre carpintería con acuñado mediante calzos de apoyo perimetrales y laterales, sellado en frío con silicona Sikasil WS-305-N "SIKA", compatible con el material soporte, para hojas de vidrio de superficie entre 3 y 4 m².Incluye: Colocación, calzado, montaje y ajuste en la carpintería. Sellado final de estanqueidad. Señalización de las hojas.Criterio de medición de proyecto: Superficie de carpintería a acristalar, según documentación gráfica de Proyecto, incluyendo en cada hoja vidriera las dimensiones del bastidor.Criterio de medición de obra: Se medirá la superficie realmente ejecutada según especificaciones de Proyecto, sumando, para cada una de las piezas, la superficie resultante de redondear por exceso cada una de sus aristas a múltiplos de 30 mm.Criterio de valoración económica: El precio incluye el sistema de triple barrera.Incluye: Colocación del premarco. Colocación de la carpintería sobre el premarco. Ajuste final de la hoja. Realización de pruebas de servicio.Criterio de medición de proyecto: Número de unidades previstas, según documentación gráfica de Proyecto.Criterio de medición de obra: Se medirá el número de unidades realmente ejecutadas según especificaciones de Proyecto. | I14: 351.65 | J14: =D14*I14 -> 703.3 | K14: Se pide igual (fábrica u obra)
A15: LCV015d | B15: F1/FIJO (con persiana) | C15: Ud | D15: 2 | E15: =D15/16 -> 0.125 | F15: AISLADA TIPO 1 (VIVIENDA 5): 1 AISLADA TIPO 1 (VIVIENDA 5): 1 | G15: Medidas: 900x2000mm · Color: RAL 7016; WSWS Blanco; a · Marca/serie: KÖMMERLING, SAINT GOBAIN, SIKA | H15: F1/FIJO (con persiana)Ventanal fijo de PVC, serie Eurofutur 70 "KÖMMERLING", dimensiones 900x2000 mm, acabado estándar en la cara interior en color WSWS Blanco y acabado foliado en la cara exterior, color RAL 7016, perfiles de 70 mm de anchura, fabricados bajo formulación Greenline®, sin plomo ni estabilizantes pesados, soldados a inglete, que incorporan cinco cámaras interiores, tanto en la sección de la hoja como en la del marco, para mejora del aislamiento térmico; galce con pendiente del 5% para facilitar el desagüe; con refuerzos interiores, según UNE-EN 14351-1; transmitancia térmica del marco: Uh,m = desde 1,3 W/(m²K); espesor máximo del acristalamiento: 40 mm; compuesta por marco, hojas, herrajes de colgar y apertura, elementos de estanqueidad y accesorios homologados, con clasificación a la permeabilidad al aire clase 4, según UNE-EN 12207, clasificación a la estanqueidad al agua clase E1650, según UNE-EN 12208, y clasificación a la resistencia a la carga del viento clase C5, según UNE-EN 12210, con premarco y cajón de persiana Rolaplus incorporado, acabado foliado en la cara exterior, color a elegir, persiana enrollable de lamas de aluminio inyectado, con aislamiento térmico, con accionamiento manual con cinta y recogedor. Incluso limpieza del premarco ya instalado, alojamiento y calzado del marco en el premarco, fijación del marco al premarco con tornillos de acero galvanizado.Incluido doble acristalamiento SGG CLIMALIT PLUS PLANITHERM XN F2 4/12 argón 90%/55.2 "SAINT GOBAIN", conjunto formado por vidrio exterior PLANITHERM XN de 4 mm, con capa de baja emisividad térmica incorporada en la cara interior, cámara de gas deshidratada con perfil separador de aluminio y doble sellado perimetral, de 12 mm, rellena de gas argón y vidrio interior STADIP PROTECT de 5+5 mm, compuesto por dos lunas de vidrio laminar de 5 mm unidas mediante dos láminas incoloras de butiral de polivinilo, para hojas de vidrio de superficie entre 3 y 4 m²; 26 mm de espesor total, fijado sobre carpintería con acuñado mediante calzos de apoyo perimetrales y laterales, sellado en frío con silicona Sikasil WS-305-N "SIKA", compatible con el material soporte, para hojas de vidrio de superficie entre 3 y 4 m².Incluye: Colocación, calzado, montaje y ajuste en la carpintería. Sellado final de estanqueidad. Señalización de las hojas.Criterio de medición de proyecto: Superficie de carpintería a acristalar, según documentación gráfica de Proyecto, incluyendo en cada hoja vidriera las dimensiones del bastidor.Criterio de medición de obra: Se medirá la superficie realmente ejecutada según especificaciones de Proyecto, sumando, para cada una de las piezas, la superficie resultante de redondear por exceso cada una de sus aristas a múltiplos de 30 mm.Criterio de valoración económica: El precio incluye el sistema de triple barrera.Incluye: Colocación del premarco. Colocación de la carpintería sobre el premarco. Ajuste final de la hoja.Criterio de medición de proyecto: Número de unidades previstas, según documentación gráfica de Proyecto.Criterio de medición de obra: Se medirá el número de unidades realmente ejecutadas según especificaciones de Proyecto. | I15: 408.37 | J15: =D15*I15 -> 816.74 | K15: Se pide igual (fábrica u obra)
A16: HRL040 | B16: RECERCADO ALUMINIO | C16: m | D16: 926.4 | E16: =D16/16 -> 57.9 | F16: PE2: 16 × 1.00 × 7.20 PE3: 16 × 1.00 × 6.30 PE4: 16 × 1.00 × 7.00 V1: 16 × 1.00 × 3.80 V2: 16 × 1.00 × 5.70 V3: 16 × 2.00 × 6.00 V4: 16 × 1.00 × 6.00 V5: 16 × 1.00 × 4.40 V6: 16 × 1.00 × 4.40 V7 (AISLADAS): 2 × 1.00 × 3.00 F1 (AISLADAS): 2 × 1.00 × 5.80 | G16: Color: RAL 7016 | H16: RECERCADO ALUMINIORecercado en ventanas y puertas de aluminio formado por vierteaguas, jambas y dintel de chapa plegada de aluminio lacado en color RAL 7016, con 60 micras de espesor mínimo de película seca, espesor 1,2 mm, desarrollo 400 mm y 3 pliegues, con goterón, empotrado en las jambas; colocación con adhesivo bituminoso de aplicación en frío; y sellado de las juntas entre piezas y de las uniones con los muros con sellador adhesivo monocomponente. | I16: 29.03 | J16: =D16*I16 -> 26893.392 | K16: Se pide igual (fábrica u obra)
... A22: SEE010 | B22: ESCALERA ESCAMOTEABLE DE ACERO | C22: Ud | D22: 1 | E22: =D22/16 -> 0.0625 | F22: Cuarto técnico piscinas: 1 | G22: Medidas: 120x60cm | H22: ESCALERA ESCAMOTEABLE DE ACEROEscalera escamoteable de acero lacado, de 3 tramos para salvar una altura entre plantas de 220 a 280 cm y para un hueco de 120x60 cm, con tapa interior, barra de apertura y cajón, recibido con mortero de cemento, industrial, M-5. Totalmente montada. | I22: 436.14 | J22: =D22*I22 -> 436.14 | K22: Fuera de la vivienda (promotor o Knubo)
A23: RTC021 | B23: TRAMPILLA METÁLICA | C23: Ud | D23: 1 | E23: =D23/16 -> 0.0625 | F23: Cuarto técnico piscinas: 1 Cuart | H23: TRAMPILLA METÁLICATrampilla de registro de acero lacado, abatible, para acceso a cuarto de instalaciones, en hueco de losa de hormigón armado, incluídas fijaciones y accesorios,totalmente montada. | I23: 105.83 | J23: =D23*I23 -> 105.83 | K23: Fuera de la vivienda (promotor o Knubo)
A24: LFA010 | B24: PUERTA RF CUARTO PRODUCTOS QUÍMICOS | C24: Ud | D24: 1 | E24: =D24/16 -> 0.0625 | F24: PRF (cuarto productos químicos piscina): 1 | G24: Medidas: 800x2000mm, 300x150mm · Color: blanco | H24: PUERTA RF CUARTO PRODUCTOS QUÍMICOS Puerta cortafuegos pivotante homologada, EI2 60-C5, de una hoja de 63 mm de espesor, 800x2000 mm de luz y altura de paso, acabado lacado en color blanco formada por 2 chapas de acero galvanizado de 0,8 mm de espesor, plegadas, ensambladas y montadas, con cámara intermedia de lana de roca de alta densidad y placas de cartón yeso, sobre cerco de acero galvanizado de 1,5 mm de espesor con junta intumescente y garras de anclaje a obra, incluso cierrapuertas para uso moderado, rejilla cortafuegos de material intumescente de 300x150 mm. Elaborada en taller, con ajuste y fijación en obra. Totalmente montada y probada. | I24: 740.47 | J24: =D24*I24 -> 740.47 | K24: Fuera de la vivienda (promotor o Knubo)
B25: Total del capítulo (PEM del proyecto) | J25: =SUM(J5:J24) -> 258815.76

Sheet 12 Pintura
A1: Névola · Pintura · 16 viviendas
A2: Capítulo C.12 del proyecto de ejecución (BC3 de julio de 2026). Medición de toda la promoción y su desglose tal como viene en el proyecto. Precios del proyecto (CYPE, PEM, sin IVA), solo como referencia.
A4: Código | B4: Partida | C4: Ud | D4: Total 16 viv. | E4: Media por vivienda | F4: Desglose de la medición (proyecto) | G4: Datos clave (medidas, color, marca) | H4: Descripción completa del proyecto | I4: Precio proyecto | J4: Importe PEM | K4: Alcance en el sistema modular
A5: 0901 | B5: PINTURA PLÁSTICA MATE BLANCA VERTICAL | C5: m² | D5: 4697.94 | E5: =D5/16 -> 293.62125 | F5: PAREADO TIPO PLANTA BAJA Vestíbulo: 14 × 9.25 × 2.60 Dormitorio 1: 14 × 12.55 × 2.60 Escalera: 14 × 6.00 × 2.60 Salón-comedor-cocina: 14 × 21.20 × 2.60 PLANTA PRIMERA Escalera: 14 × 7.70 × 2.40 Distribuidor: 14 × 9.00 × 2.40 Dormitorio principal: 14 × 21.70 × 2.60 Baño Principal: 14 × 2.95 × 2.40 Dormitorio 2: 14 × 14.30 × 2.60 Dormitorio 3: 14 × 15.60 × 2.60 -A descontar > 4.00 m² PE2: -14 × 2.80 × 2.20 PE3: -14 × 1.90 × 2.20 PE4: -14 × 2.80 × 2.10 AISLADA TIPO 1 (VIVIENDA 5) PLANTA BAJA Vestíbulo: 1 × 9.25 × 2.60 Dormitorio 1: 1 × 12.55 × 2.60 Escalera: 1 × 6.00 × 2.60 Salón-comedor-cocina: 1 × 21.20 × 2.60 PLANTA PRIMERA Escalera: 1 × 7.70 × 2.40 Distribuidor: 1 × 9.00 × 2.40 Dormitorio principal: 1 × 21.70 × 2.60 Baño Principal: 1 × 2.95 × 2.40 Dormitorio 2: 1 × 14.55 × 2.60 Dormitorio 3: 1 × 16.15 × 2.60 -A descontar > 4.00 m² PE2: -1 × 2.80 × 2.20 PE3: -1 × 1.90 × 2.20 PE4: -1 × 2.80 × 2.10 AISLADA TIPO 2 (VIVIENDA 10) PLANTA BAJA Vestíbulo: 1 × 9.20 × 2.60 Dormitorio 1: 1 × 12.50 × 2.60 Escalera: 1 × 6.00 × 2.60 Salón-comedor-cocina: 1 × 22.30 × 2.60 PLANTA PRIMERA Escalera: 1 × 7.65 × 2.40 Distribuidor: 1 × 7.90 × 2.40 Dormitorio principal: 1 × 21.20 × 2.60 Baño Principal: 1 × 2.85 × 2.40 Dormitorio 2: 1 × 14.30 × 2.60 Dormitorio 3: 1 × 16.20 × 2.60 -A descontar > 4.00 m² PE2: -1 × 2.80 × 2.20 PE3: -1 × 1.90 × 2.20 PE4: -1 × 2.80 × 2.10 Separación cuarto productos químicos: 2 × 3.20 × 2.50 | H5: PINTURA PLÁSTICA MATE BLANCA VERTICALPintura plástica blanca mate para interior, en superficies verticales, ALPHALUX SF de SIKKENS de alta calidad, al agua 100% libre de disolvente, microporosa, lavable y resistente al frote húmedo según DIN 53778. Sobre superficies muy porosas se aplicará una mano de imprimación transparente y no peliculante al agua ALPHA AQUAFIX de SIKKENS.Criterio de medición: A cinta corrida, descontando huecos mayores de 4,00 m2 | I5: 8.11 | J5: =D5*I5 -> 38100.293 | K5: Se pide igual (fábrica u obra)
A6: 0902 | B6: PINTURA PLÁSTICA MATE BLANCA HORIZONTAL | C6: m² | D6: 2092.75 | E6: =D6/16 -> 130.79688 | F6: PAREADO TIPO PLANTA BAJA Vestíbulo: 14 × 5.00 Dormitorio 1: 14 × 9.55 Baño 1: 14 × 3.75 Lavadero: 14 × 4.00 Salón-comedor-cocina: 14 × 37.60 PLANTA PRIMERA Escalera: 14 × 4.65 Distribuidor: 14 × 3.95 Dormitorio principal: 14 × 17.50 Baño Principal: 14 × 7.10 Dormitorio 2: 14 × 12.10 Dormitorio 3: 14 × 12.00 Baño 2: 14 × 3.85 AISLADA TIPO 1 (VIVIENDA 5) PLANTA BAJA Vestíbulo: 1 × 5.00 Dormitorio 1: 1 × 9.55 Baño 1: 1 × 3.75 Lavadero: 1 × 4.00 Salón-comedor-cocina: 1 × 37.50 PLANTA PRIMERA Escalera: 1 × 4.65 Distribuidor: 1 × 3.95 Dormitorio principal: 1 × 17.50 Baño Principal: 1 × 6.75 Dormitorio 2: 1 × 12.45 Dormitorio 3: 1 × 12.15 Baño 2: 1 × 3.75 AISLADA TIPO 2 (VIVIENDA 10) PLANTA BAJA Vestíbulo: 1 × 5.00 Dormitorio 1: 1 × 9.50 Baño 1: 1 × 3.65 Lavadero: 1 × 4.30 Salón-comedor-cocina: 1 × 38.15 PLANTA PRIMERA Escalera: 1 × 4.65 Distribuidor: 1 × 3.40 Dormitorio principal: 1 × 17.70 Baño Principal: 1 × 6.80 Dormitorio 2: 1 × 12.10 Dormitorio 3: 1 × 12.50 Baño 2: 1 × 3.30 FALSOS TECHOS EXTERIORES PAREADO TIPO: 14 × 9.80 AISLADA TIPO 1(VIVIENDA 5): 1 × 10.70 AISLADA TIPO 2(VIVIENDA 10): 1 × 8.10 | H6: PINTURA PLÁSTICA MATE BLANCA HORIZONTALPintura plástica blanca mate para interior/exterior, en superficies horizontales, ALPHALUX SF de SIKKENS de alta calidad, al agua 100% libre de disolvente, microporosa, lavable y resistente al frote húmedo según DIN 53778. Sobre superficies muy porosas se aplicará una mano de imprimación transparente y no peliculante al agua ALPHA AQUAFIX de SIKKENS. | I6: 10.45 | J6: =D6*I6 -> 21869.237 | K6: Se pide igual (fábrica u obra)
B7: Total del capítulo (PEM del proyecto) | J7: =SUM(J5:J6) -> 59969.531

Sheet 13 Electricidad y telecomunicac
A1: Névola · Electricidad y telecomunicaciones · 16 viviendas
A2: Capítulo C.13 del proyecto de ejecución (BC3 de julio de 2026). Medición de toda la promoción y su desglose tal como viene en el proyecto. Precios del proyecto (CYPE, PEM, sin IVA), solo como referencia.
A4: Código | B4: Partida | C4: Ud | D4: Total 16 viv. | E4: Media por vivienda | F4: Desglose de la medición (proyecto) | G4: Datos clave (medidas, color, marca) | H4: Descripción completa del proyecto | I4: Precio proyecto | J4: Importe PEM | K4: Alcance en el sistema modular
A5: 1001 | B5: TRAMITACIÓN DOCUMENTACIÓN/BOLETÍN | C5: Ud | D5: 34 | E5: =D5/16 -> 2.125 | F5: Viviendas: 16 × 1.00 Punto recarga vehículos: 16 × 1.00 Zona común: 1 × 1.00 Puesta a tierra piscina adultos: 1 × 1.00 | H5: TRAMITACIÓN DOCUMENTACIÓN/BOLETÍNPresentación, tramitación y entrega de certificados, boletines y cualquier otra documentación exigida por los organismos y/o empresas competentes y por la normativa vigente, i/ tramitación y presentación en industria de la instalación eléctrica hasta consecución del Boletín Eléctrico, aportando a la D.F. copia del mismo y esquema unifilar de la instalación. | I5: 101.61 | J5: =D5*I5 -> 3454.74 | K5: Se pide igual (fábrica u obra)
A6: E17BCD010 | B6: MÓDULO CONTADOR | C6: Ud | D6: 17 | E6: =D6/16 -> 1.0625 | F6: Viviendas: 16 × 1.00 Zona común: 1 × 1.00 | G6: Medidas: 360x630mm | H6: MÓDULO CONTADORMódulo para contador electrónico monofásico hasta 41,5 kW, de 360x630 mm de dimensiones, homologada por la compañía suministradora, formada por: 4 bornes de conexión abonado de 25 mm2 y conexión para reloj de 2,5 mm2, Bases BUC de 100/160 A, cableado con conductores de cobre rígido clase 2 tipo H07Z-R de 10 mm2 de sección, dispositivos de ventilación en la tapa, conos entrada y salida de cables, dispositivos de precinto en la tapa y ventanilla practicable para acceso al contador, totalmente instalado y conexionado, incluyendo cableado y accesorios para formar parte de la centralización de contadores; según REBT, ITC-16. | I6: 174.34 | J6: =D6*I6 -> 2963.78 | K6: Fuera de la vivienda (promotor o Knubo)
A7: E17AB030 | B7: ACOMETIDA MONOFÁSICA 2(1x16) mm2 Cu | C7: m | D7: 139 | E7: =D7/16 -> 8.6875 | F7: Viviendas 12 × 6.00 2 × 14.00 2 × 19.50 | G7: Medidas: 2x16mm, 50x85cm | H7: ACOMETIDA MONOFÁSICA 2(1x16) mm2 CuAcometida enterrada monofásica tendida directamente en zanja formada por conductores unipolares aislados de cobre con polietileno reticulado (XLEP) y cubierta de PVC, RV-K 2x16 mm², para una tensión nominal de 0,6/1 kV, incluido zanja de 50x85 cm, cama de 5 cm y capa de protección de 10 cm ambas de arena de río, protección mecánica por placa y cinta señalización de PVC. Totalmente instalado y conexionado; según REBT, ITC-BT-11 e ITC-BT-07. | I7: 23.07 | J7: =D7*I7 -> 3206.73 | K7: Fuera de la vivienda (promotor o Knubo)
A8: E17AB040 | B8: ACOMETIDA MONOFÁSICA 4(1x25) mm2 Cu | C8: m | D8: 45 | E8: =D8/16 -> 2.8125 | F8: Zona común: 45 | G8: Medidas: 4x25mm, 50x85cm | H8: ACOMETIDA MONOFÁSICA 4(1x25) mm2 CuAcometida enterrada monofásica tendida directamente en zanja formada por conductores unipolares aislados de cobre con polietileno reticulado (XLEP) y cubierta de PVC, RV-K 4x25 mm², para una tensión nominal de 0,6/1 kV, incluido zanja de 50x85 cm, cama de 5 cm y capa de protección de 10 cm ambas de arena de río, protección mecánica por placa y cinta señalización de PVC. Totalmente instalado y conexionado; según REBT, ITC-BT-11 e ITC-BT-07. | I8: 44.31 | J8: =D8*I8 -> 1993.95 | K8: Fuera de la vivienda (promotor o Knubo)
A9: E17BB020 | B9: LÍNEA GENERAL ALIMENTACIÓN 2(1x16) mm2 Cu | C9: m | D9: 160 | E9: =D9/16 -> 10 | F9: Viviendas: 16 × 10.00 | H9: LÍNEA GENERAL ALIMENTACIÓN 2(1x16) mm2 CuLínea general de alimentación (LGA) en canalización entubada formada por conductores unipolares de cobre aislados, RZ1-K (AS) 2x16 mm2, para una tensión nominal 0,6/1 kV, no propagadores del incendio y con emisión de humos y opacidad reducida, bajo tubo de PVC reforzado M25/gp7. Instalación incluyendo conexionado; según REBT, ITC-BT-14. | I9: 18.13 | J9: =D9*I9 -> 2900.8 | K9: Fuera de la vivienda (promotor o Knubo)
A10: E17BD030 | B10: DERIVACIÓN INDIVIDUAL MONOFÁSICA 3x16 mm2 | C10: m | D10: 160 | E10: =D10/16 -> 10 | F10: Viviendas: 16 × 10.00 | G10: Color: rojo | H10: DERIVACIÓN INDIVIDUAL MONOFÁSICA 3x16 mm2Derivación individual monofásica (DI) en canalización entubada formada por conductores unipolares de cobre, H07Z1-K (AS) 3x16 mm2 + 1x1,5 mm2 de hilo de mando color rojo, para una tensión nominal de 450/750 V, no propagadores del incendio y con emisión de humos y opacidad reducida, bajo tubo de PVC reforzado M32/gp7 instalada en patinillo incluyendo elementos de fijación y conexionado; según REBT, ITC-BT-15. | I10: 12.71 | J10: =D10*I10 -> 2033.6 | K10: Fuera de la vivienda (promotor o Knubo)
A11: E17BD070 | B11: DERIVACIÓN INDIVIDUAL TRIFÁSICA 5x16 mm2 | C11: m | D11: 40 | E11: =D11/16 -> 2.5 | F11: Zona común: 1 × 40.00 | G11: Color: rojo | H11: DERIVACIÓN INDIVIDUAL MONOFÁSICA 5x16 mm2Derivación individual monofásica (DI) en canalización entubada formada por conductores unipolares de cobre, H07Z1-K (AS) 5x16 mm2 + 1x1,5 mm2 de hilo de mando color rojo, para una tensión nominal de 450/750 V, no propagadores del incendio y con emisión de humos y opacidad reducida, bajo tubo de PVC reforzado M32/gp7, instalada en patinillo incluyendo elementos de fijación y conexionado; según REBT, ITC-BT-15. | I11: 18.11 | J11: =D11*I11 -> 724.4 | K11: Fuera de la vivienda (promotor o Knubo)
A12: E17BD020 | B12: DERIVACIÓN INDIVIDUAL MONOFÁSICA 3x10 mm2 | C12: m | D12: 45 | E12: =D12/16 -> 2.8125 | F12: Subcuadro Generales: 20 Subcuadro Piscina: 25 | G12: Color: rojo | H12: DERIVACIÓN INDIVIDUAL MONOFÁSICA 3x10 mm2Derivación individual monofásica (DI) en canalización entubada formada por conductores unipolares de cobre, H07Z1-K (AS) 3x10 mm2 + 1x1,5 mm2 de hilo de mando color rojo, para una tensión nominal de 450/750 V, no propagadores del incendio y con emisión de humos y opacidad reducida, bajo tubo de PVC reforzado M32/gp7, instalada en patinillo incluyendo elementos de fijación y conexionado; según REBT, ITC-BT-15. | I12: 9.83 | J12: =D12*I12 -> 442.35 | K12: Fuera de la vivienda (promotor o Knubo)
A13: E17CB04122 | B13: CUADRO GENERAL MANDO Y PROTEC. VIVIENDA ELECTR. ELEVADA 12 C | C13: Ud | D13: 16 | E13: =D13/16 -> 1 | F13: Viviendas: 16 × 1.00 | H13: CUADRO GENERAL MANDO Y PROTEC. VIVIENDA ELECTR. ELEVADA 12 CCuadro general de mando y protección de vivienda, electrificación elevada, formado por caja empotrable de doble aislamiento con puerta con grado de protección IP40-IK08, de 24 elementos, perfil omega, embarrado de proteción, alojamiento del interruptor de control de potencia (no incluido) independiente y precintable, 1 IGA de corte omnipolar de 40 A (2P), 3 interruptores diferenciales 40 A/2 P/30 mA, 2 interruptores diferenciales 25 A/2 P/30 mAy 8 PIAS (I+N) de corte omnipolar: 2 de 10 A para alumbrado; 7 de 16 A para tomas de uso general, auxiliar en cocina y baños y para recarga de vehículo eléctrico; 2 de 20 A para lavadora, lavavajillas y extractor; y 2 de 25 A para cocina y horno y aerotermia. Instalado, conexionado y rotulado; según REBT, ITC-BT-10, ICT-BT-17, ITC-BT-25 e ITC-BT-52. | I13: 1170.53 | J13: =D13*I13 -> 18728.48 | K13: Se pide igual (fábrica u obra)
A14: E17CB0601925 | B14: CUADRO GENERAL DE MANDO Y PROTECCIÓN PISCINA | C14: Ud | D14: 1 | E14: =D14/16 -> 0.0625 | F14: 1 | H14: CUADRO GENERAL DE MANDO Y PROTECCIÓN PISCINACuadro general de mando y protección de piscina, formado por caja empotrable de doble aislamiento con puerta con grado de protección IP40-IK08, de 24 elementos, perfil omega, embarrado de proteción, segun esquema unifilar. Instalado, conexionado y rotulado; según REBT. | I14: 454.37 | J14: =D14*I14 -> 454.37 | K14: Fuera de la vivienda (promotor o Knubo)
A15: E17CB0601919 | B15: CUADRO GENERAL DE MANDO Y PROTECCIÓN SERVICIOS COMUNES | C15: Ud | D15: 1 | E15: =D15/16 -> 0.0625 | F15: 1 | H15: Cuadro general de mando y protección de servicios comunes, formado por caja empotrable de doble aislamiento con puerta con grado de protección IP40-IK08, de 24 elementos, perfil omega, embarrado de proteción, segun esquema unifilar. Instalado, conexionado y rotulado; según REBT. | I15: 826.57 | J15: =D15*I15 -> 826.57 | K15: Fuera de la vivienda (promotor o Knubo)
A16: E17CM040 | B16: CIRCUITO MONOFÁSICO 3x4 mm2 (AS) | C16: m | D16: 420 | E16: =D16/16 -> 26.25 | F16: Alumbrado Balizas: 150 × 2.00 Alumbrado Farolas: 120 | H16: CIRCUITO MONOFÁSICO 3x4 mm2 (AS)Circuito eléctrico formado por conductores unipolares de cobre aislados H07Z1-K (AS) 3x4 mm2, para una tensión nominal de 450/750 V, no propagadores del incendio y con emisión de humos y opacidad reducida, realizado con tubo PVC corrugado M20/gp5 empotrado, en sistema monofásico (fase, neutro y protección), incluido p.p./ de cajas de registro y regletas de conexión. Instalación y conexionado; según REBT. | I16: 5.74 | J16: =D16*I16 -> 2410.8 | K16: Fuera de la vivienda (promotor o Knubo)
A17: E17CM010 | B17: CIRCUITO MONOFASICO 3x2,5 mm2 | C17: m | D17: 20 | E17: =D17/16 -> 1.25 | F17: TC Prevision: 20 | H17: Circuito electrico formado por conductores unipolares de cobre aislados H07V-K 3x2,5 mm2, para una tensión nominal de 450/750 V, realizado con tubo PVC corrugado M 20/gp5 empotrado, en sistema monofásico (fase, neutro y protección), incluido p.p./ de cajas de registro y regletas de conexión. Instalación y conexionado; según REBT, ITC-BT-25. | I17: 5.71 | J17: =D17*I17 -> 114.2 | K17: Fuera de la vivienda (promotor o Knubo)
A18: E17CDP035 | B18: CANALIZACIÓN TUBO RÍGIDO M32/gp7 | C18: m | D18: 420 | E18: =D18/16 -> 26.25 | F18: Alumbrado Exterior: 420 | G18: Color: gris | H18: CANALIZACIÓN TUBO RÍGIDO M32/gp7Canalización de tubo rígido de PVC color gris M32/gp7, fijado al paramento mediante abrazaderas separadas 50 cm como máximo, con p.p. de piezas especiales y accesorios. Totalmente colocado. Según REBT, ITC-BT-21. | I18: 4.92 | J18: =D18*I18 -> 2066.4 | K18: Fuera de la vivienda (promotor o Knubo)
A19: IEI015b | B19: RED ELÉCTRICA DE DISTRIBUCIÓN INTERIOR DE VIVIENDA UNIFAMILIAR 12 CIRCUITOS | C19: Ud | D19: 16 | E19: =D19/16 -> 1 | F19: 16 × 1.00 | H19: Red eléctrica de distribución interior de una vivienda unifamiliar con electrificación elevada (9.200 W), de superficie útil aproximada 125,00 m², con las siguientes estancias: acceso, vestíbulo, pasillo, escalera, salón-comedor, 3 dormitorios dobles, 3 baños, cocina, lavadero y 2 terrazas, compuesta de: cuadro general de mando y protección; 12 circuitos interiores con cableado bajo tubo protector:C1: AlumbradoC2: FuerzaC3: Horno y vitroC4: Lavadora y lavavajillasC5: SecadoraC6: Alumbrado exteriorC7: Fuerza exteriorC8: Fuerza cocinaC9: ExtractoresC10: Aerotermia (Incluye líneas repartidoras para Unidad Interior y Exterior, Colectores y Termostatos)C11: Bomba ACSC12: Punto de recarga vehículo eléctricoNo incluye mecanismos gama media (tecla o tapa: blanco; marco: blanco; embellecedor: blanco).No incluye cuadro general de mando y protección de vivienda, electrificación elevada (9.200 W), formado por caja empotrable de doble aislamiento con puerta con grado de protección IP40-IK08, segun esquema unifilar. Instalado, conexionado y rotulado; según REBT, ITC-BT-10, ICT-BT-17 e ITC-BT-25.Incluye canalización de tubo curvable de PVC, y cable unipolar H07V-K | I19: 2937.18 | J19: =D19*I19 -> 46994.88 | K19: Se pide igual (fábrica u obra)
A20: 1017 | B20: RED DE EQUIPOTENCIALIDAD EN CUARTO HÚMEDO | C20: Ud | D20: 48 | E20: =D20/16 -> 3 | F20: Cuartos húmedos (baños): 16 × 3.00 | H20: RED DE EQUIPOTENCIALIDAD EN CUARTO HÚMEDOSuministro e instalación de red de equipotencialidad en cuarto húmedo mediante conductor rígido de cobre de 4 mm² de sección, conectando a tierra todas las canalizaciones metálicas existentes y todos los elementos conductores que resulten accesibles mediante abrazaderas de latón. Incluso cajas de empalmes y regletas. Totalmente montada, conexionada y probada.Incluye: Replanteo. Conexionado del electrodo y la línea de enlace. Montaje del punto de puesta a tierra. Trazado de la línea principal de tierra. Sujeción. Trazado de derivaciones de tierra. Conexionado de las derivaciones. Conexionado a masa de la red.Criterio de medición de proyecto: Número de unidades previstas, según documentación gráfica de Proyecto.Criterio de medición de obra: Se medirá el número de unidades realmente ejecutadas según especificaciones de Proyecto. | I20: 38.34 | J20: =D20*I20 -> 1840.32 | K20: Se pide igual (fábrica u obra)
A21: 1018 | B21: TOMA DE TIERRA INDEPENDIENTE CON PICA | C21: Ud | D21: 17 | E21: =D21/16 -> 1.0625 | F21: Viviendas: 16 × 1.00 Piscinas: 1 × 1.00 | H21: TOMA DE TIERRA INDEPENDIENTE CON PICAToma de tierra independiente con con pica de acero cobrizado de D=14,3 mm y 2 m de longitud, cable de cobre de 35 mm2 hasta una longitud de 20 metros, uniones mediante soldadura aluminotérmica, incluyendo registro de comprobación y puente de prueba. Según REBT, ITC-BT-18 e ITC-BT-26. | I21: 118.37 | J21: =D21*I21 -> 2012.29 | K21: Se pide igual (fábrica u obra)
A22: 1019 | B22: RED TOMA DE TIERRA ESTRUCTURA | C22: m | D22: 650.35 | E22: =D22/16 -> 40.646875 | F22: PAREADO TIPO: 7 × 72.60 AISLADA TIPO 1 (VIVIENDA 5): 1 × 40.55 AISLADA TIPO 2 (VIVIENDA 10): 1 × 40.60 ZONA COMÚN (Piscinas): 1 × 61.00 | H22: RED TOMA DE TIERRA ESTRUCTURARed de toma de tierra de estructura, realizada con cable de cobre desnudo de 35 mm2, electrodos cobrizados de D=14,3 mm. y 2 m. de longitud con conexión mediante soldadura aluminotérmica a la armadura de cada zapata, incluyendo parte proporcional de pica, soldadura, registro de comprobación y puente de prueba. Según REBT, ITC-BT-18 e ITC-BT-26. | I22: 50.71 | J22: =D22*I22 -> 32979.249 | K22: Se pide igual (fábrica u obra)
A23: diE17V040 | B23: SOLDADURA ALUMINOTÉRMICA CABLE/CABLE | C23: Ud | D23: 150 | E23: =D23/16 -> 9.375 | F23: PAREADO TIPO: 7 × 18.00 AISLADA TIPO 1 (VIVIENDA 5): 1 × 12.00 AISLADA TIPO 2 (VIVIENDA 10): 1 × 12.00 | H23: SOLDADURA ALUMINOTÉRMICA CABLE/CABLERealización de soldadura aluminotérmica entre cables desnudo de cobre, ejecutada por medio de molde de grafíto. Se incluye en el precio el cartucho y material axiliar necesario para que la unidad quede totalmente terminada. | I23: 23.94 | J23: =D23*I23 -> 3591 | K23: Se pide igual (fábrica u obra)
A24: E17MN010 | B24: PUNTO LUZ SENCILLO UNIPOLAR BLANCO | C24: Ud | D24: 192 | E24: =D24/16 -> 12 | F24: 16 × 12.00 | G24: Marca/serie: Schuko | H24: Punto de luz sencillo realizado con tubo PVC corrugado de M16/gp5 y conductor de cobre unipolar aislado para una tensión nominal de 750 V y sección de 1,5 mm2 (activo, neutro y protección), incluido caja de registro, caja de mecanismo universal con tornillo, interruptor unipolar con tecla gama estándar, marco respectivo y casquillo, totalmente montado e instalado. Sistema "Schuko" gama estándar o similar. | I24: 18.32 | J24: =D24*I24 -> 3517.44 | K24: Se pide igual (fábrica u obra)
A25: E17MN050 | B25: PUNTO LUZ DOBLE INTERRUPTOR BLANCO | C25: Ud | D25: 33 | E25: =D25/16 -> 2.0625 | F25: Viviendas: 16 × 2.00 Caseta de aperos: 1 × 1.00 | G25: Marca/serie: Schuko | H25: Punto de luz doble interruptor realizado en tubo PVC corrugado M16/gp5 y conductor de cobre unipolar aislados para una tensión nominal de 750 V y sección 1,5 mm2 (activo, neutro y protección), incluido caja registro, caja mecanismo universal con tornillo, doble interruptor con tecla gama estándar, marco respectivo y casquillo, totalmente montado e instalado. Sistema "Schuko" gama estándar o similar. | I25: 38.18 | J25: =D25*I25 -> 1259.94 | K25: Se pide igual (fábrica u obra)
A26: E17MJB020 | B26: PUNTO DE LUZ SENCILLO CONMUTADO BLANCO | C26: Ud | D26: 224 | E26: =D26/16 -> 14 | F26: 16 × 14.00 | G26: Marca/serie: Schuko | H26: PUNTO DE LUZ SENCILLO CONMUTADO Punto de luz conmutado realizado con tubo PVC corrugado M16/gp5 y conductor de cobre unipolar aislados para una tensión nominal de 750 V y sección 1,5 mm2 (activo, neutro y protección), incluido caja registro, caja mecanismo universal con tornillo, mecanismos conmutadores con teclas gama estándar, marco respectivo y casquillo, totalmente montado e instalado. Sistema "Schuko" gama estándar o similar. | I26: 34.89 | J26: =D26*I26 -> 7815.36 | K26: Se pide igual (fábrica u obra)
A27: E17MN040 | B27: PUNTO LUZ CRUZAMIENTO BLANCO | C27: Ud | D27: 32 | E27: =D27/16 -> 2 | F27: 16 × 2.00 | G27: Marca/serie: Schuko | H27: PUNTO LUZ CRUZAMIENTO BLANCOPunto cruzamiento realizado en tubo PVC corrugado M16/gp5 y conductor de cobre unipolar aislados para una tensión nominal de 750 V y sección 1,5 mm2 (activo, neutro y protección), incluido caja registro, caja mecanismo universal con tornillo, mecanismo conmutadores y cruzamiento con tecla gama estándar, marcos respectivos y casquillo, totalmente montados e instalados. Sistema "Schuko" gama estándar o similar. | I27: 50.17 | J27: =D27*I27 -> 1605.44 | K27: Se pide igual (fábrica u obra)
A28: IIC020 | B28: DETECTOR DE MOVIMIENTO | C28: Ud | D28: 16 | E28: =D28/16 -> 1 | F28: Zona aparcamiento: 16 × 1.00 | G28: Medidas: 80x72x100mm | H28: DETECTOR DE MOVIMIENTOSuministro e instalación a la intemperie de detector de movimiento por infrarrojos para automatización del sistema de alumbrado, ángulo de detección de 140°, alcance frontal de 12 m y lateral de 8 m, regulable en tiempo y en sensibilidad lumínica, alimentación a 230 V y 50 Hz, poder de ruptura de 10 A a 250 V, cargas máximas recomendadas: 2000 W para lámparas incandescentes, 600 VA para lámparas fluorescentes, 600 VA para lámparas halógenas de bajo voltaje, 2000 W para lámparas halógenas, 600 VA para lámparas de bajo consumo, 600 VA para luminarias tipo Downlight, 60 VA para lámparas LED, temporización regulable de 3 s a 30 min, sensibilidad lumínica regulable de 5 a 2000 lux, temperatura de trabajo entre -20°C y 40°C, grado de protección IP55, de 80x72x100 mm. Incluso sujeciones.Incluye: Replanteo. Montaje, conexionado y comprobación de su correcto funcionamiento.Criterio de medición de proyecto: Número de unidades previstas, según documentación gráfica de Proyecto.Criterio de medición de obra: Se medirá el número de unidades realmente ejecutadas según especificaciones de Proyecto. | I28: 38.28 | J28: =D28*I28 -> 612.48 | K28: Se pide igual (fábrica u obra)
A29: 1025 | B29: BASE DE ENCHUFE T.T. BLANCO | C29: Ud | D29: 336 | E29: =D29/16 -> 21 | F29: 16 × 21.00 | G29: Marca/serie: Schuko | H29: BASE DE ENCHUFE 16A BLANCOBase enchufe con toma de tierra lateral realizado en tubo PVC corrugado M 20/gp5 y conductor de cobre unipolar, aislados para una tensión nominal de 750 V y sección 2,5 mm2, (activo, neutro y protección). Incluido caja de registro, caja mecanismo universal con tornillo, base enchufe, de ejecución empotrada, f+n+t, de 16A 250V, sistema "Schuko" gama estándar o similar, así como marco respectivo, totalmente montado e instalado. | I29: 20.93 | J29: =D29*I29 -> 7032.48 | K29: Se pide igual (fábrica u obra)
A30: 1026 | B30: BASE DOBLE ENCHUFE T.T. BLANCO | C30: Ud | D30: 112 | E30: =D30/16 -> 7 | F30: 16 × 7.00 | G30: Marca/serie: Schuko | H30: BASE DOBLE ENCHUFE T.T. BLANCOBase doble enchufe con toma de tierra lateral realizado en tubo PVC corrugado M20/gp5 y conductor de cobre unipolar, aislados para una tensión nominal de 750 V y sección 2,5 mm2 (activo, neutro y protección), incluido caja de registro, caja mecanismo universal con tornillo, base enchufe 10/16 A (II+T.T.), sistema "Schuko" gama estándar o similar, así como marco respectivo, totalmente montado e instalado. | I30: 26.91 | J30: =D30*I30 -> 3013.92 | K30: Se pide igual (fábrica u obra)
A31: 1027 | B31: BASE ENCHUFE 25A (II+T.T) COCINA BLANCO | C31: Ud | D31: 64 | E31: =D31/16 -> 4 | F31: Cocina: 16 × 2.00 Lavado: 16 × 2.00 | G31: Marca/serie: Schuko | H31: BASE ENCHUFE 25A (II+T.T) COCINA BLANCOBase enchufe con toma de tierra lateral, realizado en tubo PVC corrugado M25/gp5 y conductor de cobre unipolar, aislados para una tensión nominal de 750 V y sección 6 mm2 (activo, neutro y protección), incluido caja de registro, caja mecanismo universal con tornillo, base enchufe 25A (II+T.T.), sistema "Schuko" gama estándar, así como marco respectivo, totalmente montado e instalado. | I31: 37.39 | J31: =D31*I31 -> 2392.96 | K31: Se pide igual (fábrica u obra)
A32: E17MN190 | B32: BASE SEGURIDAD 20A | C32: Ud | D32: 80 | E32: =D32/16 -> 5 | F32: Baños: 16 × 5.00 | G32: Marca/serie: Schuko | H32: Base de seguridad para baño, con toma de tierra lateral realizado en tubo PVC corrugado M20/gp5 y conductor de cobre unipolar, aislados para una tensión nominal de 750 V y sección 4 mm2 (activo, neutro y protección), incluido caja de registro, caja mecanismo universal con tornillo, base enchufe 20 A (II+T.T.), sistema "Schuko" gama estándar, así como marco respectivo, totalmente montado e instalado. | I32: 26.49 | J32: =D32*I32 -> 2119.2 | K32: Se pide igual (fábrica u obra)
A33: 1028 | B33: BASE ENCHUFE 10-16 A ESTANCO IP44 | C33: Ud | D33: 33 | E33: =D33/16 -> 2.0625 | F33: Exterior viviendas: 16 × 2.00 Caseta de aperos: 1 × 1.00 | H33: BASE ENCHUFE 10-16 A ESTANCO IP44Base de enchufe estanca con toma de tierra lateral realizada con tubo PVC corrugado de M 20/gp5 y conductor rígido de 2,5 mm2 de Cu, y aislamiento VV 750 V, en sistema monofásico con toma de tierra (fase, neutro y tierra), incluyendo caja de registro, caja de mecanismo universal con tornillos, base de enchufe sistema schuko 10-16 A (II+t.) Estanco IP44 , instalada. | I33: 24.13 | J33: =D33*I33 -> 796.29 | K33: Se pide igual (fábrica u obra)
A34: E19PV015 | B34: VIDEOPORTERO DIGITAL VIVIENDA UNIFAMILIAR | C34: Ud | D34: 16 | E34: =D34/16 -> 1 | F34: 16 × 1.00 | H34: VIDEOPORTERO DIGITAL VIVIENDA UNIFAMILIARVideoportero blanco y negro digital para una vivienda unifamiliar, sistema digital de 3 hilos mas coaxial, pulsador de autoencendido de cámara, llamada y ganancia regulables, confirmación de apertura mediante mensaje de puerta abierta, incluyendo placa de calle, telecámara b/n, alimentador, abrepuertas y monitor b/n 4". Montado incluyendo cableado (2 hilos para la conexión de la placa de calle con el abrepuertas) y conexionado completo. | I34: 729.6 | J34: =D34*I34 -> 11673.6 | K34: Se pide igual (fábrica u obra)
A35: IEB010 | B35: PUNTO RECARGA VEHÍCULOS | C35: Ud | D35: 16 | E35: =D35/16 -> 1 | F35: 16 × 1.00 | H35: PUNTO RECARGA VEHÍCULOSEstación de recarga de vehículos eléctricos para modo de carga 1 compuesta por caja de recarga de vehículo eléctrico, metálica, para alimentación monofásica a 230 V y 50 Hz de frecuencia, de 2,3 kW de potencia, con una toma Schuko de 16 A. | I35: 1242.13 | J35: =D35*I35 -> 19874.08 | K35: Se pide igual (fábrica u obra)
A36: E19TCT010 | B36: EQUIPO CAPTACIÓN RTV C/ MÁSTIL h=3 m | C36: Ud | D36: 16 | E36: =D36/16 -> 1 | F36: 16 × 1.00 | H36: EQUIPO CAPTACIÓN RTV C/ MÁSTIL h=3 mEquipo de captación de señales de TV terrenal, analógicas y digitales, radio digital (DAB) y FM formado por antenas para UHF, DAB y FM, con mástil de tubo de acero galvanizado de 3 m, incluido soporte y anclajes mástil, cable coaxial hasta equipos de cabecera, y conductor de tierra de 25 mm2. Totalmente instalado y conexionado, según RD 346/2011. | I36: 268.51 | J36: =D36*I36 -> 4296.16 | K36: Se pide igual (fábrica u obra)
A37: ILA010 | B37: ARQUETA DE ENTRADA | C37: Ud | D37: 16 | E37: =D37/16 -> 1 | F37: 16 × 1.00 | G37: Medidas: 40x40x60cm | H37: ARQUETA DE ENTRADAArqueta de entrada prefabricada de hormigón de dimensiones interiores 40x40x60 cm (UNE 133100-2:2002), en instalaciónes de hasta 20 PAU, para unión entre las redes de alimentación de los distintos operadores y la infraestructura común de telecomunicaciones del edificio, con ventanas para entrada de conductos, dotada de cercos, tapa de hormigón con cierre de seguridad y ganchos para tracción y tendido de cables, incluso excavación en terreno compacto, solera de hormigón en masa HM-20 de 10 cm y p.p. de medios auxiliares, embocadura de conductos, relleno lateral de tierras y transporte de tierras sobrantes a vertedero. Totalmente instalado, según RD 346/2011. | I37: 207.6 | J37: =D37*I37 -> 3321.6 | K37: Fuera de la vivienda (promotor o Knubo)
A38: ILE021 | B38: REGISTRO DE ENLACE INFERIOR | C38: Ud | D38: 16 | E38: =D38/16 -> 1 | F38: 16 × 1.00 | G38: Medidas: 450x450x120mm | H38: REGISTRO DE ENLACE INFERIORRegistro de enlace inferior para paso y distribución de instalaciones de ICT, formado por armario con cuerpo y puerta de poliéster reforzado con fibra de vidrio de 450x450x120 mm. Instalación en superficie. Incluso cierre con llave, accesorios, piezas especiales y fijaciones.Incluye: Replanteo. Colocación y fijación del armario.Criterio de medición de proyecto: Número de unidades previstas, según documentación gráfica de Proyecto.Criterio de medición de obra: Se medirá el número de unidades realmente ejecutadas según especificaciones de Proyecto. | I38: 136.77 | J38: =D38*I38 -> 2188.32 | K38: Fuera de la vivienda (promotor o Knubo)
A39: ILE031 | B39: REGISTRO DE ENLACE SUPERIOR | C39: Ud | D39: 16 | E39: =D39/16 -> 1 | F39: 16 × 1.00 | G39: Medidas: 360x360x120mm | H39: REGISTRO DE ENLACE SUPERIORRegistro de enlace superior para paso y distribución de instalaciones de ICT, formado por armario con cuerpo y puerta de plancha de acero lacado con aislamiento interior de 360x360x120 mm. Instalación en superficie. Incluso cierre con llave, accesorios, piezas especiales y fijaciones.Incluye: Replanteo. Colocación y fijación del armario.Criterio de medición de proyecto: Número de unidades previstas, según documentación gráfica de Proyecto.Criterio de medición de obra: Se medirá el número de unidades realmente ejecutadas según especificaciones de Proyecto. | I39: 108.96 | J39: =D39*I39 -> 1743.36 | K39: Se pide igual (fábrica u obra)
A40: ILA020 | B40: CANALIZACIÓN EXTERNA ENTERRADA | C40: m | D40: 94.4 | E40: =D40/16 -> 5.9 | F40: 16 × 5.90 | G40: Medidas: 45x75cm | H40: CANALIZACIÓN EXTERNA ENTERRADACanalización externa, entre la arqueta de entrada y el registro de enlace inferior en el interior de la vivienda, formada por 1 tubo (TBA+STDP) de polietileno de 63 mm de diámetro, suministrado en rollo, resistencia a la compresión 450 N, resistencia al impacto 20 julios, ejecutada en zanja de 45x75 cm, con el tubo embebido en un prisma de hormigón en masa HM-20/B/20/X0 con 6 cm de recubrimiento superior e inferior y 5,5 cm de recubrimiento lateral. Instalación enterrada. Incluso hilo guía.Criterio de valoración económica: El precio no incluye la excavación ni el relleno perimetral posterior.Incluye: Replanteo del recorrido de la canalización. Refinado de fondos y laterales a mano, con extracción de las tierras. Vertido y compactación del hormigón en formación de solera. Presentación en seco de los tubos. Vertido y compactación del hormigón para formación del prisma.Criterio de medición de proyecto: Longitud medida en proyección horizontal, según documentación gráfica de Proyecto.Criterio de medición de obra: Se medirá, en proyección horizontal, la longitud realmente ejecutada según especificaciones de Proyecto. | I40: 9.3 | J40: =D40*I40 -> 877.92 | K40: Fuera de la vivienda (promotor o Knubo)
