Workbook

Sheet Resumen
A1: NÉVOLA (Guadalix de la Sierra): 16 chalets en sistema modular. Estimación de precio
A2: Promotor: Nido Capital. Base: dossier comercial del 22/07/2025 (planos de presentación y memoria de calidades orientativa). Precios: banco de precios Tini/DWHAI 2024, actualizado.
A4: Capítulo | B4: Pareada | C4: Independiente | D4: €/m² pareada | E4: % del total
A5: 01 ESTRUCTURA METÁLICA DE MÓDULOS | B5: ='Presupuesto vivienda'!J6 | C5: ='Presupuesto vivienda'!K6 | D5: =B5/Supuestos!$B$7 | E5: =B5/B18
A6: 02 ENVOLVENTE: FACHADA Y MEDIANERA | B6: ='Presupuesto vivienda'!J11 | C6: ='Presupuesto vivienda'!K11 | D6: =B6/Supuestos!$B$7 | E6: =B6/B18
A7: 03 CUBIERTA PLANA | B7: ='Presupuesto vivienda'!J18 | C7: ='Presupuesto vivienda'!K18 | D7: =B7/Supuestos!$B$7 | E7: =B7/B18
A8: 04 SUELOS Y FORJADO ENTRE PLANTAS | B8: ='Presupuesto vivienda'!J30 | C8: ='Presupuesto vivienda'!K30 | D8: =B8/Supuestos!$B$7 | E8: =B8/B18
A9: 05 ELECTRICIDAD Y TELECOMUNICACIONES | B9: ='Presupuesto vivienda'!J35 | C9: ='Presupuesto vivienda'!K35 | D9: =B9/Supuestos!$B$7 | E9: =B9/B18
A10: 06 FONTANERÍA, SANEAMIENTO Y SANITARIOS | B10: ='Presupuesto vivienda'!J39 | C10: ='Presupuesto vivienda'!K39 | D10: =B10/Supuestos!$B$7 | E10: =B10/B18
A11: 07 CLIMATIZACIÓN, ACS Y VENTILACIÓN | B11: ='Presupuesto vivienda'!J50 | C11: ='Presupuesto vivienda'!K50 | D11: =B11/Supuestos!$B$7 | E11: =B11/B18
A12: 08 CARPINTERÍA EXTERIOR | B12: ='Presupuesto vivienda'!J55 | C12: ='Presupuesto vivienda'!K55 | D12: =B12/Supuestos!$B$7 | E12: =B12/B18
A13: 09 ACABADO EXTERIOR DE FACHADA | B13: ='Presupuesto vivienda'!J59 | C13: ='Presupuesto vivienda'!K59 | D13: =B13/Supuestos!$B$7 | E13: =B13/B18
A14: 10 TABIQUERÍA, TECHOS Y PINTURA | B14: ='Presupuesto vivienda'!J61 | C14: ='Presupuesto vivienda'!K61 | D14: =B14/Supuestos!$B$7 | E14: =B14/B18
A15: 11 PAVIMENTOS Y ESCALERA | B15: ='Presupuesto vivienda'!J69 | C15: ='Presupuesto vivienda'!K69 | D15: =B15/Supuestos!$B$7 | E15: =B15/B18
A16: 12 CARPINTERÍA INTERIOR | B16: ='Presupuesto vivienda'!J74 | C16: ='Presupuesto vivienda'!K74 | D16: =B16/Supuestos!$B$7 | E16: =B16/B18
A17: 13 TRANSPORTE, MONTAJE Y ENTREGA | B17: ='Presupuesto vivienda'!J78 | C17: ='Presupuesto vivienda'!K78 | D17: =B17/Supuestos!$B$7 | E17: =B17/B18
A18: PRECIO DE FÁBRICA POR VIVIENDA | B18: =SUM(B5:B17) | C18: =SUM(C5:C17) | D18: =B18/Supuestos!$B$7
A19: Margen de la empresa vendedora (gastos generales + beneficio) | B19: =B18*Supuestos!$B$46 | C19: =C18*Supuestos!$B$46
A20: PRECIO DE VENTA AL PROMOTOR: VIVIENDA PILOTO (sin IVA) | B20: =B18+B19 | C20: =C18+C19 | D20: =B20/Supuestos!$B$7
A22: SERIE COMPLETA: 16 VIVIENDAS
A23: Concepto | B23: Unidades | C23: Precio unitario | D23: Importe
A24: Viviendas pareadas | B24: =Supuestos!$B$43 | C24: =B20*(1-Supuestos!$B$45) | D24: =B24*C24
A25: Viviendas independientes | B25: =Supuestos!$B$44 | C25: =C20*(1-Supuestos!$B$45) | D25: =B25*C25
A26: TOTAL SERIE (sin IVA) | B26: =B24+B25 | D26: =D24+D25
A27: €/m² construido medio de la serie | D27: =D26/(B26*Supuestos!$B$7)
A28: Precio de serie = precio piloto con el descuento por volumen de «Supuestos». Aplicado a todo el precio: es una simplificación.
A30: QUÉ INCLUYE Y QUÉ NO
A31: INCLUYE | B31: Vivienda terminada en fábrica según la memoria de calidades: estructura, envolvente, cubierta, instalaciones (electricidad, fontanería, suelo radiante, aerotermia, ventilación), carpinterías, acabados y sanitarios. Transporte, grúa, montaje y limpieza.
A32: NO INCLUYE | B32: Cimentación (losa o zapatas) y soleras. Acometidas y urbanización. Terraza y jardín de planta baja, cerramientos de parcela, garaje y zonas comunes (piscina, huerto, jardín).
A33: NO INCLUYE | B33: Muebles de cocina (el dossier la entrega sin amueblar), electrodomésticos, piscina privada.
A34: NO INCLUYE | B34: Proyecto, dirección facultativa, OCT, seguro decenal, licencias, tasas, estudio geotécnico, ensayos y coordinación de seguridad y salud.
A35: REFERENCIA | B35: Obra in situ en Menorca Pino 2024 (cimentación, urbanización, acometidas y cerramiento): 89.194 € para 165 m² (≈ 541 €/m²). Solo orientativo: Menorca no es la Sierra de Madrid.
A38: PUNTOS A CERRAR ANTES DE ENVIAR LA OFERTA
A39: 1. Sistema constructivo: la memoria prevé estructura de hormigón y fachadas con cámara. El promotor tiene que aceptar el cambio a módulo de acero + panel Tabihaus, y el proyecto de ejecución, el OCT y el seguro decenal tienen que admitirlo.
A40: 2. Acero: estimado a 90 kg/m². Con dos plantas, el cálculo de estructura puede subirlo. Pedir a los soldadores el precio actual del kg soldado (en 2024 costó entre 3 y 4,9 €/kg y se vendió a 2,80).
A41: 3. Pedir precio a Tabihaus (paneles 66, 81 y 136 mm, y 8+20+8) y a un carpintero de PVC con persiana monoblock: son las partidas más grandes después de la estructura.
A42: 4. Medidas: ancho y fondo medidos en un plano de presentación. Confirmar con el proyecto básico y ver si los módulos de 2,67 m encajan con la distribución (salón de 28,7 m² y escalera).
A43: 5. Ubicación de la fábrica en 2026: el transporte está calculado desde Seseña.

Sheet Supuestos
A1: NÉVOLA: chalet tipo A pasado a sistema modular (datos de partida)
A2: Amarillo = dato que puedes cambiar. Todo el presupuesto se recalcula a partir de esta hoja.
A4: Concepto | B4: Valor | C4: Origen / comentario
A5: Superficie construida planta baja (m²) | B5: 74.58 | C5: Dossier comercial, vivienda tipo A (pág. 13)
A6: Superficie construida planta primera (m²) | B6: 73.72 | C6: Dossier comercial, vivienda tipo A
A7: TOTAL SUPERFICIE CONSTRUIDA (m²) | B7: =B5+B6 | C7: 148,30 m²; con terrazas, 182,10 m²
A8: Superficie útil (m²) | B8: 123.71 | C8: Suma de estancias del plano: 62,19 en planta baja + 61,52 en planta primera
A9: Terraza de planta primera (m²) | B9: 9.59 | C9: La terraza de planta baja (24,48 m²) es obra in situ: queda fuera
A10: Ancho de la vivienda (m) | B10: 8 | C10: Medido en el plano con la escala gráfica. Comprobar con el proyecto
A11: Fondo de la vivienda (m) | B11: 9.4 | C11: Medido en el plano con la escala gráfica (8,0 × 9,4 ≈ 75 m² por planta)
A12: Módulos por planta | B12: 3 | C12: Módulos de ≈2,67 m de ancho: transporte normal sin escolta
A13: Plantas | B13: 2
A14: Nº de módulos por vivienda | B14: =B12*B13
A15: Ancho de cada módulo (m) | B15: =B10/B12
A16: Altura exterior de módulo (m) | B16: 3 | C16: Pilar de 2,55 m más vigas de suelo y techo (sistema Tini)
A17: Perímetro de fachada por planta (m) | B17: =2*(B10+B11)
A18: Fachada bruta, todas las caras (m²) | B18: =B17*B16*B13
A19: % de huecos sobre fachada | B19: 0.17 | C19: Estimado con los planos: grandes ventanales al salón y a los dormitorios
A20: Superficie de huecos / carpintería (m²) | B20: =B18*B19
A21: Medianera en pareados (m²) | B21: =B11*B16*B13 | C21: Lleva panel, pero no acabado exterior. Doble placa por protección contra incendios
A22: Ratio de acero (kg por m² construido) | B22: 90 | C22: El Boalo 91 kg/m², Menorca 84, Sotopinilla 79. Dos plantas: se toma el alto
A23: Acero estructural (kg) | B23: =B22*B7 | C23: Hasta tener el cálculo de estructura
A24: Tabiquería interior (m² de tabique por m² construido) | B24: 0.9 | C24: Menorca Pino: 0,90
A25: Tabiquería interior (m²) | B25: =B24*B7
A26: Zonas húmedas con gres (m²) | B26: 27.13 | C26: Cocina 8,49 + lavadero 3,98 + baños 3,65 + 3,89 + 7,12
A27: Escalera, superficie en planta (m²) | B27: 6.95 | C27: 2,29 + 4,66
A28: Tarima laminada AC5 (m²) | B28: =B8-B26-B27 | C28: Superficie útil menos zonas húmedas y escalera
A29: Alicatado de baños y frente de cocina (m²) | B29: 56 | C29: Estimado: 2 baños × 20 m² + aseo 12 m² + cocina 4 m²
A30: Puertas interiores de paso | B30: 10 | C30: Contadas en el plano
A31: Baños completos | B31: 2 | C31: Baño 2 con bañera; baño principal con ducha y lavabo doble
A32: Aseos | B32: 1 | C32: Baño 1 de planta baja, con ducha
A33: Canalón (m) | B33: =B10*2
A34: Albardilla / remate de cubierta (m) | B34: =B17
A35: Barandilla de vidrio, terraza de planta primera (m) | B35: 8 | C35: Estimado en el plano
A36: Pliegues y remates de huecos (m) | B36: 60 | C36: Estimado a partir de la superficie de huecos
A37: Rodapié (m) | B37: 110 | C37: Perímetro de las estancias secas, estimado
A38: Actualización de precios 2024→2026 (todas las partidas) | B38: 0.12 | C38: Costes de construcción residencial: +5,46 % en 2025 (ACR); +3,5 % interanual en abril de 2026, máximo histórico (Banco de España); energía y combustible disparados en 2026. Desde mediados de 2024 salen unos 11 puntos: se redondea a 12 %
A39: Horas de montaje in situ por vivienda | B39: 192 | C39: Supuesto: 3 operarios × 8 días (uniones, juntas, remates, conexión de instalaciones)
A40: Precio hora de montaje (€/h) | B40: 40 | C40: Coste completo de fábrica 2024 ≈ 40 €/h. En 2024 se vendía a 30 €/h (por debajo del coste)
A41: Transporte por módulo (€) | B41: 900 | C41: Sotopinilla 2024: 780 €/módulo (Moreno). Guadalix: <100 km de Seseña
A42: Grúa por vivienda (€) | B42: 3120 | C42: Sotopinilla 2024 (Moreno). Con 16 viviendas seguidas debería bajar
A43: Viviendas pareadas | B43: 14 | C43: Plano general: 01-02, 03-04, 06-07, 08-09, 11-12, 13-14 y 15-16
A44: Viviendas independientes | B44: 2 | C44: Viviendas 05 y 10
A45: Descuento por volumen en la serie de 16 | B45: 0.06 | C45: Supuesto: compras de acero, panel y carpintería por 16 viviendas
A46: Margen sobre precio de fábrica (gastos generales + beneficio) | B46: 0.12 | C46: Los precios del banco ya llevan el margen de fábrica de DWHAI. Este es el margen de la empresa que vende al promotor (Tini ponía un 35 %)

Sheet Presupuesto vivienda
A1: PRESUPUESTO POR PARTIDAS: CHALET TIPO A NÉVOLA EN SISTEMA MODULAR (fabricación, transporte y montaje)
A2: Precio 2026 = precio base 2024 × (1 + actualización), en todas las partidas. Fondo naranja = partida sin referencia en el banco: precio base ESTIMADO, pedir oferta a proveedor.
A3: La cantidad «independiente» solo cambia en la medianera: la independiente tiene cuatro fachadas con acabado.
A5: Código | B5: Descripción | C5: Ud | D5: Medición | E5: Cant. pareada | F5: Cant. independiente | G5: Precio base 2024 | H5: Referencia del precio | I5: PRECIO 2026 | J5: Importe pareada | K5: Importe independiente
A6: 01 | B6: ESTRUCTURA METÁLICA DE MÓDULOS | J6: =SUM(J7:J10) | K6: =SUM(K7:K10)
A7: EST | B7: Acero S275JR en pilares, vigas, correas, refuerzos y pletinas, soldado en fábrica | C7: kg | D7: Ratio kg/m² × m² construidos | E7: =Supuestos!$B$23 | F7: =E7 | G7: 2.8 | H7: Todos los proyectos 2024: 2,80 €/kg | I7: =G7*(1+Supuestos!$B$38) | J7: =E7*I7 | K7: =F7*I7
A8: EST_PN_GIM | B8: Granallado e imprimación | C8: kg | D8: = acero | E8: =Supuestos!$B$23 | F8: =E8 | G8: 0.11 | H8: Fenwick, Sotopinilla, El Boalo | I8: =G8*(1+Supuestos!$B$38) | J8: =E8*I8 | K8: =F8*I8
A9: EST_PN_PPV | B9: Pintura de poliuretano (tratamiento C2-C3) | C9: kg | D9: = acero | E9: =Supuestos!$B$23 | F9: =E9 | G9: 0.1 | H9: Sotopinilla 0,10 · Fenwick 0,15 | I9: =G9*(1+Supuestos!$B$38) | J9: =E9*I9 | K9: =F9*I9
A10: EST_PL_AG | B10: Agarraderas de izado (4 por módulo) | C10: u | D10: 4 × nº de módulos | E10: =4*Supuestos!$B$14 | F10: =E10 | G10: 4.48 | H10: Fenwick, Menorca | I10: =G10*(1+Supuestos!$B$38) | J10: =E10*I10 | K10: =F10*I10
A11: 02 | B11: ENVOLVENTE: FACHADA Y MEDIANERA | J11: =SUM(J12:J17) | K11: =SUM(K12:K17)
A12: FAC_SAN_TAH | B12: Panel sándwich Tabihaus 8+50+8 (66 mm) en fachada y medianera | C12: m² | D12: Fachada bruta − huecos | E12: =(Supuestos!$B$18-Supuestos!$B$20) | F12: =E12 | G12: 75 | H12: El Boalo 75 €/m² · Menorca oct-24 82,42 €/m² | I12: =G12*(1+Supuestos!$B$38) | J12: =E12*I12 | K12: =F12*I12
A13: FAC_ATR | B13: Aislamiento térmico reflexivo | C13: m² | D13: = panel de fachada | E13: =(Supuestos!$B$18-Supuestos!$B$20) | F13: =E13 | G13: 11.25 | H13: Todos los proyectos | I13: =G13*(1+Supuestos!$B$38) | J13: =E13*I13 | K13: =F13*I13
A14: FAC_PET80 | B14: Aislamiento de PET reciclado de 80 mm | C14: m² | D14: = panel de fachada | E14: =(Supuestos!$B$18-Supuestos!$B$20) | F14: =E14 | G14: 15.7 | H14: Todos los proyectos | I14: =G14*(1+Supuestos!$B$38) | J14: =E14*I14 | K14: =F14*I14
A15: FAC_U46 | B15: Perfilería U 46 mm cada 60 cm (trasdosado interior) | C15: m² | D15: = panel de fachada | E15: =(Supuestos!$B$18-Supuestos!$B$20) | F15: =E15 | G15: 22 | H15: Todos los proyectos | I15: =G15*(1+Supuestos!$B$38) | J15: =E15*I15 | K15: =F15*I15
A16: TAB_PYL13 | B16: Placa de yeso laminado de 13 mm en trasdosado de fachada | C16: m² | D16: = panel de fachada | E16: =(Supuestos!$B$18-Supuestos!$B$20) | F16: =E16 | G16: 13.56 | H16: Banco (TAB_PYL13) | I16: =G16*(1+Supuestos!$B$38) | J16: =E16*I16 | K16: =F16*I16
A17: TAB_2PLA | B17: Doble placa en medianera (protección contra incendios entre viviendas) | C17: m² | D17: Solo pareadas | E17: =Supuestos!$B$21 | F17: =0 | G17: 27.12 | H17: Menorca (TAB_2PLA) | I17: =G17*(1+Supuestos!$B$38) | J17: =E17*I17 | K17: =F17*I17
A18: 03 | B18: CUBIERTA PLANA | J18: =SUM(J19:J29) | K18: =SUM(K19:K29)
A19: CUB_SAN_TAH | B19: Panel sándwich Tabihaus 8+65+8 (81 mm) de cubierta | C19: m² | D19: Planta primera | E19: =Supuestos!$B$6 | F19: =E19 | G19: 65 | H19: El Boalo 65 · Menorca oct-24 58,37 | I19: =G19*(1+Supuestos!$B$38) | J19: =E19*I19 | K19: =F19*I19
A20: CUB_ATR | B20: Aislamiento térmico reflexivo | C20: m² | D20: = cubierta | E20: =Supuestos!$B$6 | F20: =E20 | G20: 11.25 | H20: Todos los proyectos | I20: =G20*(1+Supuestos!$B$38) | J20: =E20*I20 | K20: =F20*I20
A21: CUB_XPS60 | B21: Aislamiento XPS 60 mm | C21: m² | D21: = cubierta | E21: =Supuestos!$B$6 | F21: =E21 | G21: 10 | H21: Todos los proyectos | I21: =G21*(1+Supuestos!$B$38) | J21: =E21*I21 | K21: =F21*I21
A22: CUB_PET40 | B22: Aislamiento de PET reciclado 40 mm | C22: m² | D22: = cubierta | E22: =Supuestos!$B$6 | F22: =E22 | G22: 10 | H22: Todos los proyectos | I22: =G22*(1+Supuestos!$B$38) | J22: =E22*I22 | K22: =F22*I22
A23: CUB_TAB | B23: Impermeabilización: tela asfáltica bicapa | C23: m² | D23: = cubierta | E23: =Supuestos!$B$6 | F23: =E23 | G23: 36 | H23: Todos los proyectos | I23: =G23*(1+Supuestos!$B$38) | J23: =E23*I23 | K23: =F23*I23
A24: CUB_GRA | B24: Acabado de grava en zona no transitable | C24: m² | D24: Cubierta − terraza | E24: =Supuestos!$B$6-Supuestos!$B$9 | F24: =E24 | G24: 12 | H24: ESTIMADO (no está en el banco) | I24: =G24*(1+Supuestos!$B$38) | J24: =E24*I24 | K24: =F24*I24
A25: CUB_CAN | B25: Canalón de chapa plegada de 2 mm | C25: m | D25: Supuestos | E25: =Supuestos!$B$33 | F25: =E25 | G25: 38 | H25: Todos los proyectos | I25: =G25*(1+Supuestos!$B$38) | J25: =E25*I25 | K25: =F25*I25
A26: CUB_GAR | B26: Gárgola metálica con pieza de EPDM | C26: u | D26: 3 por vivienda | E26: =3 | F26: =E26 | G26: 52 | H26: Todos los proyectos | I26: =G26*(1+Supuestos!$B$38) | J26: =E26*I26 | K26: =F26*I26
A27: CUB_ALB | B27: Albardilla de chapa plegada galvanizada de 2 mm | C27: m | D27: Perímetro de cubierta | E27: =Supuestos!$B$34 | F27: =E27 | G27: 25.05 | H27: Todos los proyectos | I27: =G27*(1+Supuestos!$B$38) | J27: =E27*I27 | K27: =F27*I27
A28: TER_GRES | B28: Gres exterior antideslizante en terraza de planta primera | C28: m² | D28: Supuestos | E28: =Supuestos!$B$9 | F28: =E28 | G28: 45 | H28: Banco (PAV_SOCE, solado cerámico) | I28: =G28*(1+Supuestos!$B$38) | J28: =E28*I28 | K28: =F28*I28
A29: TER_BAR | B29: Barandilla de vidrio de seguridad en terraza | C29: m | D29: Supuestos | E29: =Supuestos!$B$35 | F29: =E29 | G29: 350 | H29: ESTIMADO (en el banco solo hay malla: 217,80 €/m) | I29: =G29*(1+Supuestos!$B$38) | J29: =E29*I29 | K29: =F29*I29
A30: 04 | B30: SUELOS Y FORJADO ENTRE PLANTAS | J30: =SUM(J31:J34) | K30: =SUM(K31:K34)
A31: SUE_SAN_136 | B31: Panel sándwich Tabihaus 8+120+8 (136 mm), suelo de planta baja | C31: m² | D31: Planta baja | E31: =Supuestos!$B$5 | F31: =E31 | G31: 99 | H31: El Boalo 99 · Menorca oct-24 86,09 | I31: =G31*(1+Supuestos!$B$38) | J31: =E31*I31 | K31: =F31*I31
A32: SUE_SAN_81 | B32: Panel sándwich Tabihaus 8+65+8, suelo de módulos de planta primera | C32: m² | D32: Planta primera | E32: =Supuestos!$B$6 | F32: =E32 | G32: 65 | H32: El Boalo (SUE 8+65+8) 65 | I32: =G32*(1+Supuestos!$B$38) | J32: =E32*I32 | K32: =F32*I32
A33: SUE_TEC_40 | B33: Panel Tabihaus 8+20+8, techo de módulos de planta baja | C33: m² | D33: Planta baja | E33: =Supuestos!$B$5 | F33: =E33 | G33: 50 | H33: ESTIMADO: coste de lista 40 €/m² (Mahón) + margen | I33: =G33*(1+Supuestos!$B$38) | J33: =E33*I33 | K33: =F33*I33
A34: SUE_ATR | B34: Aislamiento térmico reflexivo bajo forjado | C34: m² | D34: Planta baja | E34: =Supuestos!$B$5 | F34: =E34 | G34: 11.25 | H34: Menorca, El Boalo | I34: =G34*(1+Supuestos!$B$38) | J34: =E34*I34 | K34: =F34*I34
A35: 05 | B35: ELECTRICIDAD Y TELECOMUNICACIONES | J35: =SUM(J36:J38) | K35: =SUM(K36:K38)
A36: ELE_M2 | B36: Instalación eléctrica completa (cuadro, circuitos, mecanismos Niessen o similar, iluminación, TV y datos en estancias) | C36: m² | D36: m² construidos | E36: =Supuestos!$B$7 | F36: =E36 | G36: 55 | H36: Ratio: Sotopinilla 61 €/m² · Menorca 39 €/m² (sin el error de la toma de tierras) | I36: =G36*(1+Supuestos!$B$38) | J36: =E36*I36 | K36: =F36*I36
A37: ELE_POR | B37: Portero automático | C37: u | D37: 1 | E37: =1 | F37: =E37 | G37: 350 | H37: ESTIMADO | I37: =G37*(1+Supuestos!$B$38) | J37: =E37*I37 | K37: =F37*I37
A38: ELE_VE | B38: Preinstalación de punto de recarga de vehículo eléctrico | C38: u | D38: 1 | E38: =1 | F38: =E38 | G38: 450 | H38: ESTIMADO | I38: =G38*(1+Supuestos!$B$38) | J38: =E38*I38 | K38: =F38*I38
A39: 06 | B39: FONTANERÍA, SANEAMIENTO Y SANITARIOS | J39: =SUM(J40:J49) | K39: =SUM(K40:K49)
A40: BAN_INS | B40: Instalación completa de fontanería y saneamiento por baño o aseo | C40: u | D40: Baños + aseo | E40: =Supuestos!$B$31+Supuestos!$B$32 | F40: =E40 | G40: 494 | H40: Todos los proyectos | I40: =G40*(1+Supuestos!$B$38) | J40: =E40*I40 | K40: =F40*I40
A41: 09TLAV | B41: Tomas de agua y desagüe: cocina, lavadora, secadora y pila de lavadero | C41: u | D41: 4 tomas | E41: =4 | F41: =E41 | G41: 75 | H41: Menorca (toma de lavadora) | I41: =G41*(1+Supuestos!$B$38) | J41: =E41*I41 | K41: =F41*I41
A42: BAN_IMP | B42: Impermeabilización de plato de ducha | C42: u | D42: 2 duchas | E42: =2 | F42: =E42 | G42: 50 | H42: Todos los proyectos | I42: =G42*(1+Supuestos!$B$38) | J42: =E42*I42 | K42: =F42*I42
A43: BAN_INO | B43: Inodoro de porcelana vitrificada (Gala o similar) | C43: u | D43: 3 | E43: =Supuestos!$B$31+Supuestos!$B$32 | F43: =E43 | G43: 280 | H43: ESTIMADO: gama media (en 2024 se usó Tesi suspendido, 811 €) | I43: =G43*(1+Supuestos!$B$38) | J43: =E43*I43 | K43: =F43*I43
A44: BAN_LAV | B44: Lavabo de porcelana (baño principal con lavabo doble) | C44: u | D44: 4 | E44: =4 | F44: =E44 | G44: 96.38 | H44: Banco (Starbath) | I44: =G44*(1+Supuestos!$B$38) | J44: =E44*I44 | K44: =F44*I44
A45: BAN_GRI_ETN | B45: Grifería monomando de lavabo | C45: u | D45: 4 | E45: =4 | F45: =E45 | G45: 57.6 | H45: Banco (Imex Etna) | I45: =G45*(1+Supuestos!$B$38) | J45: =E45*I45 | K45: =F45*I45
A46: BAN_DUC_THA | B46: Conjunto de ducha monomando | C46: u | D46: 2 | E46: =2 | F46: =E46 | G46: 159.5 | H46: Banco (Imex Thalos) | I46: =G46*(1+Supuestos!$B$38) | J46: =E46*I46 | K46: =F46*I46
A47: BAN_DUC_PLA | B47: Plato de ducha extraplano 80×100 | C47: u | D47: 2 | E47: =2 | F47: =E47 | G47: 300 | H47: Banco (BAN_DUC_PLA_80X100) | I47: =G47*(1+Supuestos!$B$38) | J47: =E47*I47 | K47: =F47*I47
A48: BAN_BAN | B48: Bañera acrílica blanca con grifería | C48: u | D48: 1 | E48: =1 | F48: =E48 | G48: 450 | H48: ESTIMADO | I48: =G48*(1+Supuestos!$B$38) | J48: =E48*I48 | K48: =F48*I48
A49: BAN_MAM | B49: Mampara de vidrio (baño principal) | C49: u | D49: 1 | E49: =1 | F49: =E49 | G49: 400 | H49: Menorca oct-24, El Boalo | I49: =G49*(1+Supuestos!$B$38) | J49: =E49*I49 | K49: =F49*I49
A50: 07 | B50: CLIMATIZACIÓN, ACS Y VENTILACIÓN | J50: =SUM(J51:J54) | K50: =SUM(K51:K54)
A51: CLI_RAD_SUE | B51: Suelo radiante y refrescante | C51: m² | D51: Superficie útil | E51: =Supuestos!$B$8 | F51: =E51 | G51: 74.2 | H51: Banco (CLI_RAD_SUE) | I51: =G51*(1+Supuestos!$B$38) | J51: =E51*I51 | K51: =F51*I51
A52: AER_120_150 | B52: Aerotermia Panasonic para 120–150 m² (climatización y ACS) | C52: u | D52: 1 | E52: =1 | F52: =E52 | G52: 9731 | H52: Banco (Fenwick, catálogo) | I52: =G52*(1+Supuestos!$B$38) | J52: =E52*I52 | K52: =F52*I52
A53: CLI_TER | B53: Termostatos por estancia | C53: u | D53: 5 | E53: =5 | F53: =E53 | G53: 50 | H53: Banco (CLI_TER_AAC) | I53: =G53*(1+Supuestos!$B$38) | J53: =E53*I53 | K53: =F53*I53
A54: VEN_MEC | B54: Ventilación mecánica de simple flujo (extracción en baños y cocina, admisión en secos) | C54: u | D54: 1 | E54: =1 | F54: =E54 | G54: 2200 | H54: ESTIMADO (no está en el banco) | I54: =G54*(1+Supuestos!$B$38) | J54: =E54*I54 | K54: =F54*I54
A55: 08 | B55: CARPINTERÍA EXTERIOR | J55: =SUM(J56:J58) | K55: =SUM(K56:K58)
A56: CAE_PVC | B56: Carpintería de PVC o aluminio con RPT, vidrio bajo emisivo, con persiana monoblock | C56: m² | D56: Superficie de huecos | E56: =Supuestos!$B$20 | F56: =E56 | G56: 400 | H56: ESTIMADO: 400 €/m². COR-Vision 2024 ≈ 500–590 €/m² en aluminio de gama alta | I56: =G56*(1+Supuestos!$B$38) | J56: =E56*I56 | K56: =F56*I56
A57: LEA010 | B57: Puerta de entrada acorazada | C57: u | D57: 1 | E57: =1 | F57: =E57 | G57: 1786.35 | H57: Banco (LEA010) | I57: =G57*(1+Supuestos!$B$38) | J57: =E57*I57 | K57: =F57*I57
A58: ACF_PLA | B58: Pliegues y remates de chapa en huecos | C58: m | D58: Supuestos | E58: =Supuestos!$B$36 | F58: =E58 | G58: 35 | H58: Menorca, Fenwick | I58: =G58*(1+Supuestos!$B$38) | J58: =E58*I58 | K58: =F58*I58
A59: 09 | B59: ACABADO EXTERIOR DE FACHADA | J59: =SUM(J60:J60) | K59: =SUM(K60:K60)
A60: ACF_ENF | B60: Revestimiento exterior mixto: placa de cemento con acabado continuo o piezas cerámicas o metálicas | C60: m² | D60: Fachada − huecos − medianera | E60: =(Supuestos!$B$18-Supuestos!$B$20-Supuestos!$B$21) | F60: =(Supuestos!$B$18-Supuestos!$B$20) | G60: 76 | H60: Banco (ACF_ENF, Aquapanel con enfoscado). Madera 106 · Viroc 58 · minionda 46 | I60: =G60*(1+Supuestos!$B$38) | J60: =E60*I60 | K60: =F60*I60
A61: 10 | B61: TABIQUERÍA, TECHOS Y PINTURA | J61: =SUM(J62:J68) | K61: =SUM(K62:K68)
A62: TAB_INT | B62: Tabique de PYL: perfilería, PET 40 mm y placa de 13 mm por las dos caras | C62: m² | D62: Ratio × m² construidos | E62: =Supuestos!$B$25 | F62: =E62 | G62: 59.12 | H62: Compuesto con el banco: perfil 22 + PET 10 + 2 × placa 13,56 | I62: =G62*(1+Supuestos!$B$38) | J62: =E62*I62 | K62: =F62*I62
A63: TAB_HID | B63: Suplemento de placa hidrófuga en zonas húmedas | C63: m² | D63: Alicatado + 20 % | E63: =Supuestos!$B$29*1.2 | F63: =E63 | G63: 5.47 | H63: Diferencia hidrófuga − normal (19,03 − 13,56) | I63: =G63*(1+Supuestos!$B$38) | J63: =E63*I63 | K63: =F63*I63
A64: TAB_CER | B64: Alicatado de gres en baños y frente de cocina | C64: m² | D64: Supuestos | E64: =Supuestos!$B$29 | F64: =E64 | G64: 45 | H64: Menorca, El Boalo | I64: =G64*(1+Supuestos!$B$38) | J64: =E64*I64 | K64: =F64*I64
A65: TEC_PLA | B65: Techo de placa de yeso laminado de 15 mm | C65: m² | D65: Superficie útil | E65: =Supuestos!$B$8 | F65: =E65 | G65: 13.56 | H65: Todos los proyectos | I65: =G65*(1+Supuestos!$B$38) | J65: =E65*I65 | K65: =F65*I65
A66: TEC_PLH | B66: Suplemento hidrófugo en techos de zonas húmedas | C66: m² | D66: Zonas húmedas | E66: =Supuestos!$B$26 | F66: =E66 | G66: 5.47 | H66: Diferencia hidrófuga − normal | I66: =G66*(1+Supuestos!$B$38) | J66: =E66*I66 | K66: =F66*I66
A67: 114PPLAS | B67: Pintura plástica lisa en paredes | C67: m² | D67: Tabiques × 2 caras + trasdosado de fachada − alicatado | E67: =Supuestos!$B$25*2+(Supuestos!$B$18-Supuestos!$B$20)-Supuestos!$B$29 | F67: =E67 | G67: 7.1 | H67: Menorca | I67: =G67*(1+Supuestos!$B$38) | J67: =E67*I67 | K67: =F67*I67
A68: TEC_PIN_B | B68: Pintura blanca mate en techos | C68: m² | D68: Superficie útil | E68: =Supuestos!$B$8 | F68: =E68 | G68: 7.1 | H68: Menorca | I68: =G68*(1+Supuestos!$B$38) | J68: =E68*I68 | K68: =F68*I68
A69: 11 | B69: PAVIMENTOS Y ESCALERA | J69: =SUM(J70:J73) | K69: =SUM(K70:K73)
A70: PAV_LAM | B70: Tarima laminada sintética AC5 | C70: m² | D70: Supuestos | E70: =Supuestos!$B$28 | F70: =E70 | G70: 32 | H70: ESTIMADO (en el banco solo hay roble, 78 €/m²) | I70: =G70*(1+Supuestos!$B$38) | J70: =E70*I70 | K70: =F70*I70
A71: PAV_SOCE | B71: Solado de gres en baños, cocina y lavadero | C71: m² | D71: Zonas húmedas | E71: =Supuestos!$B$26 | F71: =E71 | G71: 45 | H71: Banco (PAV_SOCE) | I71: =G71*(1+Supuestos!$B$38) | J71: =E71*I71 | K71: =F71*I71
A72: PAV_RODMPVC | B72: Rodapié a juego con la carpintería interior | C72: m | D72: Supuestos | E72: =Supuestos!$B$37 | F72: =E72 | G72: 16.2 | H72: Todos los proyectos | I72: =G72*(1+Supuestos!$B$38) | J72: =E72*I72 | K72: =F72*I72
A73: ESC | B73: Escalera interior: estructura metálica con peldaños de gres | C73: u | D73: 1 | E73: =1 | F73: =E73 | G73: 3200 | H73: ESTIMADO: coste 2024 de escalera instalada 2.275 € (Guadalajara) | I73: =G73*(1+Supuestos!$B$38) | J73: =E73*I73 | K73: =F73*I73
A74: 12 | B74: CARPINTERÍA INTERIOR | J74: =SUM(J75:J77) | K74: =SUM(K75:K77)
A75: CAI_PUE_DML_1HA72 | B75: Puerta de paso lacada lisa de 725 mm, abatible | C75: u | D75: Contadas en el plano | E75: =Supuestos!$B$30 | F75: =E75 | G75: 744 | H75: Banco | I75: =G75*(1+Supuestos!$B$38) | J75: =E75*I75 | K75: =F75*I75
A76: CAI_ARM | B76: Armario empotrado de 2 puertas en distribuidor (revestido, balda y barra) | C76: u | D76: 1 | E76: =1 | F76: =E76 | G76: 1500 | H76: ESTIMADO: la mitad del armario de 4 puertas de Menorca (2.866 €) | I76: =G76*(1+Supuestos!$B$38) | J76: =E76*I76 | K76: =F76*I76
A77: CAI_VES | B77: Vestidor abierto en dormitorio principal (revestido, maletero y barra) | C77: u | D77: 1 | E77: =1 | F77: =E77 | G77: 1200 | H77: ESTIMADO | I77: =G77*(1+Supuestos!$B$38) | J77: =E77*I77 | K77: =F77*I77
A78: 13 | B78: TRANSPORTE, MONTAJE Y ENTREGA | J78: =SUM(J79:J82) | K78: =SUM(K79:K82)
A79: TRA | B79: Transporte de módulos de Seseña a Guadalix de la Sierra | C79: u | D79: Nº de módulos | E79: =Supuestos!$B$14 | F79: =E79 | G79: =Supuestos!$B$41 | H79: Supuestos (Sotopinilla 2024: 780 €/módulo) | I79: =G79*(1+Supuestos!$B$38) | J79: =E79*I79 | K79: =F79*I79
A80: GRU | B80: Grúa para colocación | C80: u | D80: 1 por vivienda | E80: =1 | F80: =E80 | G80: =Supuestos!$B$42 | H80: Supuestos (Sotopinilla 2024: 3.120 €) | I80: =G80*(1+Supuestos!$B$38) | J80: =E80*I80 | K80: =F80*I80
A81: OPE | B81: Montaje in situ: uniones, juntas de fachada y cubierta, conexión de instalaciones | C81: h | D81: Supuestos | E81: =Supuestos!$B$39 | F81: =E81 | G81: =Supuestos!$B$40 | H81: Supuestos (coste completo de fábrica ≈ 40 €/h) | I81: =G81*(1+Supuestos!$B$38) | J81: =E81*I81 | K81: =F81*I81
A82: LIM | B82: Limpieza final | C82: m² | D82: m² construidos | E82: =Supuestos!$B$7 | F82: =E82 | G82: 5 | H82: Todos los proyectos | I82: =G82*(1+Supuestos!$B$38) | J82: =E82*I82 | K82: =F82*I82
B84: PRECIO DE FÁBRICA POR VIVIENDA (fabricación + transporte + montaje) | J84: =J6+J11+J18+J30+J35+J39+J50+J55+J59+J61+J69+J74+J78 | K84: =K6+K11+K18+K30+K35+K39+K50+K55+K59+K61+K69+K74+K78
B85: €/m² construido | J85: =J84/Supuestos!$B$7 | K85: =K84/Supuestos!$B$7
B86: de ello, partidas con precio ESTIMADO (fondo naranja) | J86: =SUMPRODUCT(ISNUMBER(SEARCH("ESTIMADO",H7:H82))*J7:J82) | K86: =J86/J84
